Workbook
Name COLOR: #REF!
Name Size: #REF!

Sheet Axkid Template
A1: Axkid Product Template | I1: Change RRP currency --> | J1: EUR | R1: Product size | V1: Box size
A2: Article Number | B2: Article Name | C2: Color | D2: EAN code | E2: Status | F2: Category | G2: Approval description | H2: Recommended age | I2: Range limit | J2: Currency | K2: Recommended Retail Price | L2: Full container qty | M2: Master box quantity | N2: Sales qty | O2: Qty per pallet | P2: Country of origin | Q2: HS code | R2: Width in CM | S2: Height in cm | T2: Depth in cm | U2: Net weight kg | V2: Lenght in cm | W2: Width in cm2 | X2: Height in cm2 | Y2: Gross weight kg | Z2: Volume m3 | AA2: Washing instruction | AB2: Product images & movies | AC2: Product manual
A3: 20050002 | B3: Axkid Babyfix Grey | C3: Grey | D3: 7350057581933 | E3: Active | F3: Infant carrier | G3: ECE R44 | H3: 0-1 years | I3: 0-13kg | J3: =$J$1 -> EUR | K3: =IF($J$1="SEK / NOK",(VLOOKUP(A3,'RRP data'!A:C,3,FALSE)),(IF($J$1="DKK",(VLOOKUP('RRP data'!A3,'RRP data'!A:D,4,FALSE)),(IF($J$1="EUR",(VLOOKUP(A3,'RRP data'!A:E,5,FALSE))))))) -> 149 | M3: 1 | N3: 1 | P3: CN | Q3: 94018000 | R3: 43 | S3: 54 | T3: 65 | U3: 3.4 | V3: 45 | W3: 58 | X3: 67 | Y3: 5.79 | Z3: =PRODUCT(V3:X3)/1000000 -> 0.17487 | AA3: 30°
A4: 20050003 | B4: Axkid Babyfix Black | C4: Black | D4: 7350057581940 | E4: Active | F4: Infant carrier | G4: ECE R44 | H4: 0-1 years | I4: 0-13kg | J4: =$J$1 -> EUR | K4: =IF($J$1="SEK / NOK",(VLOOKUP(A4,'RRP data'!A:C,3,FALSE)),(IF($J$1="DKK",(VLOOKUP('RRP data'!A4,'RRP data'!A:D,4,FALSE)),(IF($J$1="EUR",(VLOOKUP(A4,'RRP data'!A:E,5,FALSE))))))) -> 149 | M4: 1 | N4: 1 | P4: CN | Q4: 94018000 | R4: 43 | S4: 54 | T4: 65 | U4: 3.4 | V4: 45 | W4: 58 | X4: 67 | Y4: 5.79 | Z4: =PRODUCT(V4:X4)/1000000 -> 0.17487 | AA4: 30°
A5: 210103 | B5: Axkid Babyfix Base Black | C5: Black | D5: 7350057580042 | E5: Active | F5: Base | G5: ECE R44 | H5: n/a | I5: n/a | J5: =$J$1 -> EUR | K5: =IF($J$1="SEK / NOK",(VLOOKUP(A5,'RRP data'!A:C,3,FALSE)),(IF($J$1="DKK",(VLOOKUP('RRP data'!A5,'RRP data'!A:D,4,FALSE)),(IF($J$1="EUR",(VLOOKUP(A5,'RRP data'!A:E,5,FALSE))))))) -> 100 | M5: 1 | N5: 1 | P5: CN | Q5: 94018000 | R5: 33 | S5: 43 | T5: 69 | U5: 4.63 | V5: 34 | W5: 20 | X5: 60.5 | Y5: 5.45 | Z5: =PRODUCT(V5:X5)/1000000 -> 0.04114 | AA5: 30°
A6: 22150116 | B6: Axkid Minikid 3 Tar | C6: Tar Black | D6: 7350057586723 | E6: Active | F6: Rear-facing car seat | G6: UN R129 | H6: 0-7 years | I6: 36kg | J6: =$J$1 -> EUR | K6: =IF($J$1="SEK / NOK",(VLOOKUP(A6,'RRP data'!A:C,3,FALSE)),(IF($J$1="DKK",(VLOOKUP('RRP data'!A6,'RRP data'!A:D,4,FALSE)),(IF($J$1="EUR",(VLOOKUP(A6,'RRP data'!A:E,5,FALSE))))))) -> 549 | M6: 1 | N6: 1 | P6: CN | Q6: 94018000 | R6: 44 | S6: 65 | T6: 54 | U6: 11 | V6: 46 | W6: 58 | X6: 66 | Y6: 14 | Z6: =PRODUCT(V6:X6)/1000000 -> 0.176088 | AA6: 30°
A7: 22150117 | B7: Axkid Minikid 3 Granite | C7: Granite Grey | D7: 7350057586730 | E7: Active | F7: Rear-facing car seat | G7: UN R129 | H7: 0-7 years | I7: 61-125cm (max 36kg) | J7: =$J$1 -> EUR | K7: =IF($J$1="SEK / NOK",(VLOOKUP(A7,'RRP data'!A:C,3,FALSE)),(IF($J$1="DKK",(VLOOKUP('RRP data'!A7,'RRP data'!A:D,4,FALSE)),(IF($J$1="EUR",(VLOOKUP(A7,'RRP data'!A:E,5,FALSE))))))) -> 549 | M7: 1 | N7: 1 | P7: CN | Q7: 94018000 | R7: 44 | S7: 65 | T7: 54 | U7: 11 | V7: 46 | W7: 58 | X7: 66 | Y7: 14 | Z7: =PRODUCT(V7:X7)/1000000 -> 0.176088 | AA7: 30°
A8: 22150118 | B8: Axkid Minikid 3 Shellfish | C8: Shellfish Red | D8: 7350057586747 | E8: Active | F8: Rear-facing car seat | G8: UN R129 | H8: 0-7 years | I8: 61-125cm (max 36kg) | J8: =$J$1 -> EUR | K8: =IF($J$1="SEK / NOK",(VLOOKUP(A8,'RRP data'!A:C,3,FALSE)),(IF($J$1="DKK",(VLOOKUP('RRP data'!A8,'RRP data'!A:D,4,FALSE)),(IF($J$1="EUR",(VLOOKUP(A8,'RRP data'!A:E,5,FALSE))))))) -> 549 | M8: 1 | N8: 1 | P8: CN | Q8: 94018000 | R8: 44 | S8: 65 | T8: 54 | U8: 11 | V8: 46 | W8: 58 | X8: 66 | Y8: 14 | Z8: =PRODUCT(V8:X8)/1000000 -> 0.176088 | AA8: 30°
A9: 22150119 | B9: Axkid Minikid 3 Sea | C9: Sea Blue | D9: 7350057586754 | E9: Active | F9: Rear-facing car seat | G9: UN R129 | H9: 0-7 years | I9: 61-125cm (max 36kg) | J9: =$J$1 -> EUR | K9: =IF($J$1="SEK / NOK",(VLOOKUP(A9,'RRP data'!A:C,3,FALSE)),(IF($J$1="DKK",(VLOOKUP('RRP data'!A9,'RRP data'!A:D,4,FALSE)),(IF($J$1="EUR",(VLOOKUP(A9,'RRP data'!A:E,5,FALSE))))))) -> 549 | M9: 1 | N9: 1 | P9: CN | Q9: 94018000 | R9: 44 | S9: 65 | T9: 54 | U9: 11 | V9: 46 | W9: 58 | X9: 66 | Y9: 14 | Z9: =PRODUCT(V9:X9)/1000000 -> 0.176088 | AA9: 30°
A10: 22150120 | B10: Axkid Minikid 3 Moss | C10: Moss Green | D10: 7350057586761 | E10: Active | F10: Rear-facing car seat | G10: UN R129 | H10: 0-7 years | I10: 61-125cm (max 36kg) | J10: =$J$1 -> EUR | K10: =IF($J$1="SEK / NOK",(VLOOKUP(A10,'RRP data'!A:C,3,FALSE)),(IF($J$1="DKK",(VLOOKUP('RRP data'!A10,'RRP data'!A:D,4,FALSE)),(IF($J$1="EUR",(VLOOKUP(A10,'RRP data'!A:E,5,FALSE))))))) -> 549 | M10: 1 | N10: 1 | P10: CN | Q10: 94018000 | R10: 44 | S10: 65 | T10: 54 | U10: 11 | V10: 46 | W10: 58 | X10: 66 | Y10: 14 | Z10: =PRODUCT(V10:X10)/1000000 -> 0.176088 | AA10: 30°
A11: 22150121 | B11: Axkid Minikid 3 Premium Shell Black | C11: Shell black | D11: 7350057586778 | E11: Active | F11: Rear-facing car seat | G11: UN R129 | H11: 0-7 years | I11: 61-125cm (max 36kg) | J11: =$J$1 -> EUR | K11: =IF($J$1="SEK / NOK",(VLOOKUP(A11,'RRP data'!A:C,3,FALSE)),(IF($J$1="DKK",(VLOOKUP('RRP data'!A11,'RRP data'!A:D,4,FALSE)),(IF($J$1="EUR",(VLOOKUP(A11,'RRP data'!A:E,5,FALSE))))))) -> 599 | M11: 1 | N11: 1 | P11: CN | Q11: 94018000 | R11: 44 | S11: 65 | T11: 54 | U11: 11 | V11: 46 | W11: 58 | X11: 66 | Y11: 14 | Z11: =PRODUCT(V11:X11)/1000000 -> 0.176088 | AA11: 30°
A12: 22150122 | B12: Axkid Minikid 3 Premium Granite Melange | C12: Granite Grey Melange | D12: 7350057586785 | E12: Active | F12: Rear-facing car seat | G12: UN R129 | H12: 0-7 years | I12: 61-125cm (max 36kg) | J12: =$J$1 -> EUR | K12: =IF($J$1="SEK / NOK",(VLOOKUP(A12,'RRP data'!A:C,3,FALSE)),(IF($J$1="DKK",(VLOOKUP('RRP data'!A12,'RRP data'!A:D,4,FALSE)),(IF($J$1="EUR",(VLOOKUP(A12,'RRP data'!A:E,5,FALSE))))))) -> 599 | M12: 1 | N12: 1 | P12: CN | Q12: 94018000 | R12: 44 | S12: 65 | T12: 54 | U12: 11 | V12: 46 | W12: 58 | X12: 66 | Y12: 14 | Z12: =PRODUCT(V12:X12)/1000000 -> 0.176088 | AA12: 30°
A13: 22140316 | B13: Axkid Minikid 2 (2022/23) Tar | C13: Tar Black | D13: 7350057585870 | E13: Active | F13: Rear-facing car seat | G13: ECE R44 | H13: 0-7 years | I13: 0-25kg | J13: =$J$1 -> EUR | K13: =IF($J$1="SEK / NOK",(VLOOKUP(A13,'RRP data'!A:C,3,FALSE)),(IF($J$1="DKK",(VLOOKUP('RRP data'!A13,'RRP data'!A:D,4,FALSE)),(IF($J$1="EUR",(VLOOKUP(A13,'RRP data'!A:E,5,FALSE))))))) -> 429 | M13: 1 | N13: 1 | P13: CN | Q13: 94018000 | R13: 44 | S13: 62 | T13: 56 | U13: 11.4 | V13: 46 | W13: 58 | X13: 66 | Y13: 13.8 | Z13: =PRODUCT(V13:X13)/1000000 -> 0.176088 | AA13: 30°
A14: 22140317 | B14: Axkid Minikid 2 (2022/23) Granite | C14: Granite Grey | D14: 7350057585887 | E14: Active | F14: Rear-facing car seat | G14: ECE R44 | H14: 0-7 years | I14: 0-25kg | J14: =$J$1 -> EUR | K14: =IF($J$1="SEK / NOK",(VLOOKUP(A14,'RRP data'!A:C,3,FALSE)),(IF($J$1="DKK",(VLOOKUP('RRP data'!A14,'RRP data'!A:D,4,FALSE)),(IF($J$1="EUR",(VLOOKUP(A14,'RRP data'!A:E,5,FALSE))))))) -> 429 | M14: 1 | N14: 1 | P14: CN | Q14: 94018000 | R14: 44 | S14: 62 | T14: 56 | U14: 11.4 | V14: 46 | W14: 58 | X14: 66 | Y14: 13.8 | Z14: =PRODUCT(V14:X14)/1000000 -> 0.176088 | AA14: 30°
... A45: 24100021 | B45: Axkid Modukid Seat Premium Shell black | C45: Shell black | D45: 7350057584484 | E45: Active | F45: Rear-facing car seat | G45: UN R129 | H45: 6 months - 4 years | I45: 61-105cm (max 18kg) | J45: =$J$1 -> EUR | K45: =IF($J$1="SEK / NOK",(VLOOKUP(A45,'RRP data'!A:C,3,FALSE)),(IF($J$1="DKK",(VLOOKUP('RRP data'!A45,'RRP data'!A:D,4,FALSE)),(IF($J$1="EUR",(VLOOKUP(A45,'RRP data'!A:E,5,FALSE))))))) -> 275 | M45: 1 | N45: 1 | P45: CN | Q45: 94018000 | R45: 43 | S45: 62 | T45: 52 | U45: 7.5 | V45: 71 | W45: 47 | X45: 44 | Y45: 10.5 | Z45: =PRODUCT(V45:X45)/1000000 -> 0.146828 | AA45: 30°
A46: 24100022 | B46: Axkid Modukid Seat Premium Granite Melange | C46: Granite Melange | D46: 7350057584491 | E46: Active | F46: Rear-facing car seat | G46: UN R129 | H46: 6 months - 4 years | I46: 61-105cm (max 18kg) | J46: =$J$1 -> EUR | K46: =IF($J$1="SEK / NOK",(VLOOKUP(A46,'RRP data'!A:C,3,FALSE)),(IF($J$1="DKK",(VLOOKUP('RRP data'!A46,'RRP data'!A:D,4,FALSE)),(IF($J$1="EUR",(VLOOKUP(A46,'RRP data'!A:E,5,FALSE))))))) -> 275 | M46: 1 | N46: 1 | P46: CN | Q46: 94018000 | R46: k | S46: 62 | T46: 52 | U46: 7.5 | V46: 71 | W46: 47 | X46: 44 | Y46: 10.5 | Z46: =PRODUCT(V46:X46)/1000000 -> 0.146828 | AA46: 30°
A47: 24100023 | B47: Axkid Modukid Seat Premium Sky Grey | C47: Sky Grey | D47: 7350057584507 | E47: Active | F47: Rear-facing car seat | G47: UN R129 | H47: 6 months - 4 years | I47: 61-105cm (max 18kg) | J47: =$J$1 -> EUR | K47: =IF($J$1="SEK / NOK",(VLOOKUP(A47,'RRP data'!A:C,3,FALSE)),(IF($J$1="DKK",(VLOOKUP('RRP data'!A47,'RRP data'!A:D,4,FALSE)),(IF($J$1="EUR",(VLOOKUP(A47,'RRP data'!A:E,5,FALSE))))))) -> 275 | M47: 1 | N47: 1 | P47: CN | Q47: 94018000 | R47: 43 | S47: 62 | T47: 52 | U47: 7.5 | V47: 71 | W47: 47 | X47: 44 | Y47: 10.5 | Z47: =PRODUCT(V47:X47)/1000000 -> 0.146828 | AA47: 30°
A48: 21020003 | B48: Axkid Modukid Base | C48: Black | D48: 7350057582732 | E48: Active | F48: Base | G48: UN R129 | H48: n/a | I48: n/a | J48: =$J$1 -> EUR | K48: =IF($J$1="SEK / NOK",(VLOOKUP(A48,'RRP data'!A:C,3,FALSE)),(IF($J$1="DKK",(VLOOKUP('RRP data'!A48,'RRP data'!A:D,4,FALSE)),(IF($J$1="EUR",(VLOOKUP(A48,'RRP data'!A:E,5,FALSE))))))) -> 100 | M48: 1 | N48: 1 | P48: CN | Q48: 94018000 | R48: 43 | S48: 30 | T48: 65 | U48: 7 | V48: 61 | W48: 39 | X48: 23 | Y48: 8.8 | Z48: =PRODUCT(V48:X48)/1000000 -> 0.054717 | AA48: 30°
A49: 25110116 | B49: Axkid ONE 2 Tar | C49: Tar Black | D49: 7350057586648 | E49: Active | F49: Rear-facing car seat | G49: UN R129 | H49: 6 months - 7 years | I49: 61-125cm (max 23kg) | J49: =$J$1 -> EUR | K49: =IF($J$1="SEK / NOK",(VLOOKUP(A49,'RRP data'!A:C,3,FALSE)),(IF($J$1="DKK",(VLOOKUP('RRP data'!A49,'RRP data'!A:D,4,FALSE)),(IF($J$1="EUR",(VLOOKUP(A49,'RRP data'!A:E,5,FALSE))))))) -> 799 | M49: 1 | N49: 1 | P49: CN | Q49: 94018000 | R49: 44 | S49: 76 | T49: 54 | U49: 9.99 | V49: 87 | W49: 46 | X49: 52 | Y49: 16.3 | Z49: =PRODUCT(V49:X49)/1000000 -> 0.208104 | AA49: 30°
A50: 25110121 | B50: Axkid ONE 2 Granite Melange | C50: Granite Grey Melange | D50: 7350057586655 | E50: Active | F50: Rear-facing car seat | G50: UN R129 | H50: 6 months - 7 years | I50: 61-125cm (max 23kg) | J50: =$J$1 -> EUR | K50: =IF($J$1="SEK / NOK",(VLOOKUP(A50,'RRP data'!A:C,3,FALSE)),(IF($J$1="DKK",(VLOOKUP('RRP data'!A50,'RRP data'!A:D,4,FALSE)),(IF($J$1="EUR",(VLOOKUP(A50,'RRP data'!A:E,5,FALSE))))))) -> 799 | M50: 1 | N50: 1 | P50: CN | Q50: 94018000 | R50: 44 | S50: 76 | T50: 54 | U50: 9.99 | V50: 87 | W50: 46 | X50: 52 | Y50: 16.3 | Z50: =PRODUCT(V50:X50)/1000000 -> 0.208104 | AA50: 30°
A51: 25110124 | B51: Axkid ONE 2 Brick Melange | C51: Brick Beige Melange | D51: 7350057586662 | E51: Active | F51: Rear-facing car seat | G51: UN R129 | H51: 6 months - 7 years | I51: 61-125cm (max 23kg) | J51: =$J$1 -> EUR | K51: =IF($J$1="SEK / NOK",(VLOOKUP(A51,'RRP data'!A:C,3,FALSE)),(IF($J$1="DKK",(VLOOKUP('RRP data'!A51,'RRP data'!A:D,4,FALSE)),(IF($J$1="EUR",(VLOOKUP(A51,'RRP data'!A:E,5,FALSE))))))) -> 799 | M51: 1 | N51: 1 | P51: CN | Q51: 94018000 | R51: 44 | S51: 76 | T51: 54 | U51: 9.99 | V51: 87 | W51: 46 | X51: 52 | Y51: 16.3 | Z51: =PRODUCT(V51:X51)/1000000 -> 0.208104 | AA51: 30°
A52: 25110125 | B52: Axkid ONE 2 Tile Melange | C52: Tile Red Melange | D52: 7350057586679 | E52: Active | F52: Rear-facing car seat | G52: UN R129 | H52: 6 months - 7 years | I52: 61-125cm (max 23kg) | J52: =$J$1 -> EUR | K52: =IF($J$1="SEK / NOK",(VLOOKUP(A52,'RRP data'!A:C,3,FALSE)),(IF($J$1="DKK",(VLOOKUP('RRP data'!A52,'RRP data'!A:D,4,FALSE)),(IF($J$1="EUR",(VLOOKUP(A52,'RRP data'!A:E,5,FALSE))))))) -> 799 | M52: 1 | N52: 1 | P52: CN | Q52: 94018000 | R52: 44 | S52: 76 | T52: 54 | U52: 9.99 | V52: 87 | W52: 46 | X52: 52 | Y52: 16.3 | Z52: =PRODUCT(V52:X52)/1000000 -> 0.208104 | AA52: 30°
A53: 25120116 | B53: Axkid ONE+ 2 Tar | C53: Tar Black | D53: 7350057586686 | E53: Active | F53: Rear-facing car seat | G53: UN R129 | H53: 0-7 years | I53: 40-125cm (max 23kg) | J53: =$J$1 -> EUR | K53: =IF($J$1="SEK / NOK",(VLOOKUP(A53,'RRP data'!A:C,3,FALSE)),(IF($J$1="DKK",(VLOOKUP('RRP data'!A53,'RRP data'!A:D,4,FALSE)),(IF($J$1="EUR",(VLOOKUP(A53,'RRP data'!A:E,5,FALSE))))))) -> 849 | M53: 1 | N53: 1 | P53: CN | Q53: 94018000 | R53: 44 | S53: 76 | T53: 54 | U53: 9.99 | V53: 87 | W53: 46 | X53: 52 | Y53: 16.7 | Z53: =PRODUCT(V53:X53)/1000000 -> 0.208104 | AA53: 30°
A54: 25120121 | B54: Axkid ONE+ 2 Granite Melange | C54: Granite Grey Melange | D54: 7350057586693 | E54: Active | F54: Rear-facing car seat | G54: UN R129 | H54: 0-7 years | I54: 40-125cm (max 23kg) | J54: =$J$1 -> EUR | K54: =IF($J$1="SEK / NOK",(VLOOKUP(A54,'RRP data'!A:C,3,FALSE)),(IF($J$1="DKK",(VLOOKUP('RRP data'!A54,'RRP data'!A:D,4,FALSE)),(IF($J$1="EUR",(VLOOKUP(A54,'RRP data'!A:E,5,FALSE))))))) -> 849 | M54: 1 | N54: 1 | P54: CN | Q54: 94018000 | R54: 44 | S54: 76 | T54: 54 | U54: 9.99 | V54: 87 | W54: 46 | X54: 52 | Y54: 16.7 | Z54: =PRODUCT(V54:X54)/1000000 -> 0.208104 | AA54: 30°
A55: 25120124 | B55: Axkid ONE+ 2 Brick Melange | C55: Brick Beige Melange | D55: 7350057586709 | E55: Active | F55: Rear-facing car seat | G55: UN R129 | H55: 0-7 years | I55: 40-125cm (max 23kg) | J55: =$J$1 -> EUR | K55: =IF($J$1="SEK / NOK",(VLOOKUP(A55,'RRP data'!A:C,3,FALSE)),(IF($J$1="DKK",(VLOOKUP('RRP data'!A55,'RRP data'!A:D,4,FALSE)),(IF($J$1="EUR",(VLOOKUP(A55,'RRP data'!A:E,5,FALSE))))))) -> 849 | M55: 1 | N55: 1 | P55: CN | Q55: 94018000 | R55: 44 | S55: 76 | T55: 54 | U55: 9.99 | V55: 87 | W55: 46 | X55: 52 | Y55: 16.7 | Z55: =PRODUCT(V55:X55)/1000000 -> 0.208104 | AA55: 30°
A56: 25120125 | B56: Axkid ONE+ 2 Tile Melange | C56: Tile Red Melange | D56: 7350057586716 | E56: Active | F56: Rear-facing car seat | G56: UN R129 | H56: 0-7 years | I56: 40-125cm (max 23kg) | J56: =$J$1 -> EUR | K56: =IF($J$1="SEK / NOK",(VLOOKUP(A56,'RRP data'!A:C,3,FALSE)),(IF($J$1="DKK",(VLOOKUP('RRP data'!A56,'RRP data'!A:D,4,FALSE)),(IF($J$1="EUR",(VLOOKUP(A56,'RRP data'!A:E,5,FALSE))))))) -> 849 | M56: 1 | N56: 1 | P56: CN | Q56: 94018000 | R56: 44 | S56: 76 | T56: 54 | U56: 9.99 | V56: 87 | W56: 46 | X56: 52 | Y56: 16.7 | Z56: =PRODUCT(V56:X56)/1000000 -> 0.208104 | AA56: 30°
A57: 25110016 | B57: Axkid ONE Tar | C57: Tar | D57: 7350057584590 | E57: Discontinued | F57: Rear-facing car seat | G57: UN R129 | H57: 6 months - 7 years | I57: 61-125cm (max 23kg) | J57: =$J$1 -> EUR | K57: =IF($J$1="SEK / NOK",(VLOOKUP(A57,'RRP data'!A:C,3,FALSE)),(IF($J$1="DKK",(VLOOKUP('RRP data'!A57,'RRP data'!A:D,4,FALSE)),(IF($J$1="EUR",(VLOOKUP(A57,'RRP data'!A:E,5,FALSE))))))) -> 749 | M57: 1 | N57: 1 | P57: CN | Q57: 94018000 | R57: 44 | S57: 76 | T57: 54 | U57: 9.99 | V57: 82 | W57: 46 | X57: 60 | Y57: 16.3 | Z57: =PRODUCT(V57:X57)/1000000 -> 0.22632 | AA57: 30°
A58: 25110021 | B58: Axkid ONE Granite Melange | C58: Granite Melange | D58: 7350057584606 | E58: Discontinued | F58: Rear-facing car seat | G58: UN R129 | H58: 6 months - 7 years | I58: 61-125cm (max 23kg) | J58: =$J$1 -> EUR | K58: =IF($J$1="SEK / NOK",(VLOOKUP(A58,'RRP data'!A:C,3,FALSE)),(IF($J$1="DKK",(VLOOKUP('RRP data'!A58,'RRP data'!A:D,4,FALSE)),(IF($J$1="EUR",(VLOOKUP(A58,'RRP data'!A:E,5,FALSE))))))) -> 749 | M58: 1 | N58: 1 | P58: CN | Q58: 94018000 | R58: 44 | S58: 76 | T58: 54 | U58: 9.99 | V58: 82 | W58: 46 | X58: 60 | Y58: 16.3 | Z58: =PRODUCT(V58:X58)/1000000 -> 0.22632 | AA58: 30°
... A90: 801403 | B90: Axkid Angle adjusting wedge | C90: Black | D90: 7350057581087 | E90: Active | F90: Accessory | G90: EN1888 | H90: - | I90: - | J90: =$J$1 -> EUR | K90: =IF($J$1="SEK / NOK",(VLOOKUP(A90,'RRP data'!A:C,3,FALSE)),(IF($J$1="DKK",(VLOOKUP('RRP data'!A90,'RRP data'!A:D,4,FALSE)),(IF($J$1="EUR",(VLOOKUP(A90,'RRP data'!A:E,5,FALSE))))))) -> 17 | M90: 40 | N90: 1 | P90: CN | Q90: 94019990 | R90: 16.5 | S90: 23 | T90: 7.5 | U90: 0.263 | V90: 30 | W90: 8 | X90: 20 | Y90: 0.44 | Z90: =PRODUCT(V90:X90)/1000000 -> 0.0048 | AA90: Not washable
A91: 803303 | B91: Axkid Baby mirror | C91: Black | D91: 7350057581339 | E91: Active | F91: Accessory | G91: EN1888 | H91: - | I91: - | J91: =$J$1 -> EUR | K91: =IF($J$1="SEK / NOK",(VLOOKUP(A91,'RRP data'!A:C,3,FALSE)),(IF($J$1="DKK",(VLOOKUP('RRP data'!A91,'RRP data'!A:D,4,FALSE)),(IF($J$1="EUR",(VLOOKUP(A91,'RRP data'!A:E,5,FALSE))))))) -> 19 | M91: 10 | N91: 1 | P91: CN | Q91: 94019990 | R91: 21.5 | S91: 17.5 | U91: 0.71 | V91: 30 | W91: 8 | X91: 20 | Y91: 1.05 | Z91: =PRODUCT(V91:X91)/1000000 -> 0.0048 | AA91: Not washable
A92: 803803 | B92: Axkid Seat protection Premium | C92: Black | D92: 7350057582008 | E92: Active | F92: Accessory | G92: EN1888 | H92: - | I92: - | J92: =$J$1 -> EUR | K92: =IF($J$1="SEK / NOK",(VLOOKUP(A92,'RRP data'!A:C,3,FALSE)),(IF($J$1="DKK",(VLOOKUP('RRP data'!A92,'RRP data'!A:D,4,FALSE)),(IF($J$1="EUR",(VLOOKUP(A92,'RRP data'!A:E,5,FALSE))))))) -> 50 | M92: 10 | N92: 1 | P92: CN | Q92: 94019990 | R92: 122 | S92: 47 | T92: 1 | U92: 0.5 | V92: 29.5 | W92: 8 | X92: 58 | Y92: 1 | Z92: =PRODUCT(V92:X92)/1000000 -> 0.013688 | AA92: Not washable
A93: 803906 | B93: Axkid Sunshades for window self attaching | C93: Grey | D93: 7350057582015 | E93: Active | F93: Accessory | G93: EN1888 | H93: - | I93: - | J93: =$J$1 -> EUR | K93: =IF($J$1="SEK / NOK",(VLOOKUP(A93,'RRP data'!A:C,3,FALSE)),(IF($J$1="DKK",(VLOOKUP('RRP data'!A93,'RRP data'!A:D,4,FALSE)),(IF($J$1="EUR",(VLOOKUP(A93,'RRP data'!A:E,5,FALSE))))))) -> 9 | M93: 48 | N93: 1 | P93: CN | Q93: 94019990 | R93: 38 | S93: 44 | T93: 0.2 | U93: 0.16 | V93: 18 | W93: 6 | X93: 16 | Y93: 0.33 | Z93: =PRODUCT(V93:X93)/1000000 -> 0.001728 | AA93: Not washable
A94: 804003 | B94: Axkid iPad holder | C94: Black | D94: 7350057582022 | E94: Active | F94: Accessory | G94: EN1888 | H94: - | I94: - | J94: =$J$1 -> EUR | K94: =IF($J$1="SEK / NOK",(VLOOKUP(A94,'RRP data'!A:C,3,FALSE)),(IF($J$1="DKK",(VLOOKUP('RRP data'!A94,'RRP data'!A:D,4,FALSE)),(IF($J$1="EUR",(VLOOKUP(A94,'RRP data'!A:E,5,FALSE))))))) -> 18 | M94: 20 | N94: 1 | P94: CN | Q94: 94019990 | R94: 27.5 | S94: 19.5 | T94: 2 | U94: 0.24 | V94: 30 | W94: 8 | X94: 20 | Y94: 0.45 | Z94: =PRODUCT(V94:X94)/1000000 -> 0.0048 | AA94: Not washable
A95: 804103 | B95: Axkid Backseat organizer | C95: Black | D95: 7350057582039 | E95: Active | F95: Accessory | G95: EN1888 | H95: - | I95: - | J95: =$J$1 -> EUR | K95: =IF($J$1="SEK / NOK",(VLOOKUP(A95,'RRP data'!A:C,3,FALSE)),(IF($J$1="DKK",(VLOOKUP('RRP data'!A95,'RRP data'!A:D,4,FALSE)),(IF($J$1="EUR",(VLOOKUP(A95,'RRP data'!A:E,5,FALSE))))))) -> 19 | M95: 20 | N95: 1 | P95: CN | Q95: 94019990 | R95: 42.5 | S95: 57 | T95: 1 | U95: 0.16 | V95: 23.5 | W95: 7 | X95: 37 | Y95: 0.16 | Z95: =PRODUCT(V95:X95)/1000000 -> 0.0060865 | AA95: Not washable
A96: 804303 | B96: Axkid Tether straps for Move | C96: Black | D96: 7350057582060 | E96: Active | F96: Accessory | G96: EN1888 | H96: - | I96: - | J96: =$J$1 -> EUR | K96: =IF($J$1="SEK / NOK",(VLOOKUP(A96,'RRP data'!A:C,3,FALSE)),(IF($J$1="DKK",(VLOOKUP('RRP data'!A96,'RRP data'!A:D,4,FALSE)),(IF($J$1="EUR",(VLOOKUP(A96,'RRP data'!A:E,5,FALSE))))))) -> 29 | M96: 100 | N96: 1 | P96: CN | Q96: 94019990 | R96: 4 | S96: 133 | T96: 0.2 | U96: 0.14 | V96: 18 | W96: 6 | X96: 16 | Y96: 0.15 | Z96: =PRODUCT(V96:X96)/1000000 -> 0.001728 | AA96: Not washable
A97: 804403 | B97: Axkid Swedish safety kit | C97: Black | D97: 7350057582121 | E97: Active | F97: Accessory | G97: EN1888 | H97: - | I97: - | J97: =$J$1 -> EUR | K97: =IF($J$1="SEK / NOK",(VLOOKUP(A97,'RRP data'!A:C,3,FALSE)),(IF($J$1="DKK",(VLOOKUP('RRP data'!A97,'RRP data'!A:D,4,FALSE)),(IF($J$1="EUR",(VLOOKUP(A97,'RRP data'!A:E,5,FALSE))))))) -> 55 | M97: 1 | N97: 1 | P97: CN | Q97: 94019990 | R97: - | S97: - | T97: - | U97: 1.5 | V97: 29.5 | W97: 8 | X97: 58 | Y97: 2 | Z97: =PRODUCT(V97:X97)/1000000 -> 0.013688 | AA97: Not washable
A98: 804503 | B98: Axkid Sun cover (seat sunshade) | C98: Black | D98: 7350057582749 | E98: Active | F98: Accessory | G98: EN1888 | H98: - | I98: - | J98: =$J$1 -> EUR | K98: =IF($J$1="SEK / NOK",(VLOOKUP(A98,'RRP data'!A:C,3,FALSE)),(IF($J$1="DKK",(VLOOKUP('RRP data'!A98,'RRP data'!A:D,4,FALSE)),(IF($J$1="EUR",(VLOOKUP(A98,'RRP data'!A:E,5,FALSE))))))) -> 35 | M98: 40 | N98: 1 | P98: CN | Q98: 94019990 | R98: 41 | S98: 21 | T98: 47 | U98: 0.3 | V98: 30 | W98: 8 | X98: 20 | Y98: 0.61 | Z98: =PRODUCT(V98:X98)/1000000 -> 0.0048 | AA98: Not washable
A99: 804603 | B99: Axkid Support leg adapter | C99: Black | D99: 7350057582756 | E99: Active | F99: Accessory | G99: EN1888 | H99: - | I99: - | J99: =$J$1 -> EUR | K99: =IF($J$1="SEK / NOK",(VLOOKUP(A99,'RRP data'!A:C,3,FALSE)),(IF($J$1="DKK",(VLOOKUP('RRP data'!A99,'RRP data'!A:D,4,FALSE)),(IF($J$1="EUR",(VLOOKUP(A99,'RRP data'!A:E,5,FALSE))))))) -> 29 | M99: 10 | N99: 1 | P99: CN | Q99: 94019990 | R99: 8 | S99: 27.5 | T99: 3.5 | U99: 0.5 | V99: 30 | W99: 8 | X99: 20 | Y99: 0.8 | Z99: =PRODUCT(V99:X99)/1000000 -> 0.0048 | AA99: Not washable
A100: 804916 | B100: Axkid Connect | C100: Tar Black | D100: 7350057584347 | E100: Active | F100: Accessory | G100: EN1888 | H100: - | I100: - | J100: =$J$1 -> EUR | K100: =IF($J$1="SEK / NOK",(VLOOKUP(A100,'RRP data'!A:C,3,FALSE)),(IF($J$1="DKK",(VLOOKUP('RRP data'!A100,'RRP data'!A:D,4,FALSE)),(IF($J$1="EUR",(VLOOKUP(A100,'RRP data'!A:E,5,FALSE))))))) -> 99 | M100: 1 | N100: 1 | P100: CN | Q100: 94019990 | R100: 21 | S100: 1.5 | T100: 17 | U100: 0.4 | V100: 23.5 | W100: 3.8 | X100: 19.3 | Y100: 0.8 | Z100: =PRODUCT(V100:X100)/1000000 -> 0.00172349 | AA100: Not washable
A101: 805006 | B101: Axkid Bamboo Summer cover Minikid 2 | C101: White | D101: 7350057584798 | E101: Active | F101: Accessory | G101: EN1888 | H101: - | I101: - | J101: =$J$1 -> EUR | K101: =IF($J$1="SEK / NOK",(VLOOKUP(A101,'RRP data'!A:C,3,FALSE)),(IF($J$1="DKK",(VLOOKUP('RRP data'!A101,'RRP data'!A:D,4,FALSE)),(IF($J$1="EUR",(VLOOKUP(A101,'RRP data'!A:E,5,FALSE))))))) -> 50 | M101: 1 | N101: 1 | P101: CN | Q101: 94019990 | R101: 85 | S101: 45 | T101: 0.2 | U101: 0.2 | V101: 7 | W101: 20 | X101: 30 | Y101: 0.25 | Z101: =PRODUCT(V101:X101)/1000000 -> 0.0042 | AA101: 30°
A102: 805007 | B102: Axkid Bamboo Summer cover ONE | C102: White | D102: 7350057587843 | E102: Active | F102: Accessory | G102: EN1888 | H102: - | I102: - | J102: =$J$1 -> EUR | K102: =IF($J$1="SEK / NOK",(VLOOKUP(A102,'RRP data'!A:C,3,FALSE)),(IF($J$1="DKK",(VLOOKUP('RRP data'!A102,'RRP data'!A:D,4,FALSE)),(IF($J$1="EUR",(VLOOKUP(A102,'RRP data'!A:E,5,FALSE))))))) -> 50 | M102: 1 | N102: 1 | P102: CN | Q102: 94019990 | R102: 85 | S102: 45 | T102: 0.2 | U102: 0.2 | V102: 7 | W102: 20 | X102: 30 | Y102: 0.25 | Z102: =PRODUCT(V102:X102)/1000000 -> 0.0042 | AA102: 30°
A103: 805008 | B103: Axkid Bamboo Summer cover Bigkid | C103: White | D103: 7350057587850 | E103: Active | F103: Accessory | G103: EN1888 | H103: - | I103: - | J103: =$J$1 -> EUR | K103: =IF($J$1="SEK / NOK",(VLOOKUP(A103,'RRP data'!A:C,3,FALSE)),(IF($J$1="DKK",(VLOOKUP('RRP data'!A103,'RRP data'!A:D,4,FALSE)),(IF($J$1="EUR",(VLOOKUP(A103,'RRP data'!A:E,5,FALSE))))))) -> 50 | M103: 1 | N103: 1 | P103: CN | Q103: 94019990 | R103: 85 | S103: 45 | T103: 0.2 | U103: 0.2 | V103: 7 | W103: 20 | X103: 30 | Y103: 0.25 | Z103: =PRODUCT(V103:X103)/1000000 -> 0.0042 | AA103: 30°
A104: 805201 | B104: Axkid Cooling Pads by AeroMoov group 1/2 | C104: Grey | D104: 5413421814456 | E104: Active | F104: Accessory | H104: - | I104: - | J104: =$J$1 -> EUR | K104: =IF($J$1="SEK / NOK",(VLOOKUP(A104,'RRP data'!A:C,3,FALSE)),(IF($J$1="DKK",(VLOOKUP('RRP data'!A104,'RRP data'!A:D,4,FALSE)),(IF($J$1="EUR",(VLOOKUP(A104,'RRP data'!A:E,5,FALSE))))))) -> 40 | M104: 10 | N104: 1 | P104: TR | Q104: 94019990 | R104: 24 | S104: 74 | T104: 1 | U104: 0.2 | V104: 4 | W104: 22.5 | X104: 36.5 | Y104: 0.3 | Z104: =PRODUCT(V104:X104)/1000000 -> 0.003285 | AA104: 40°
A105: 806201 | B105: Axkid Cooling Pads by AeroMoov group 2/3 | C105: Grey | D105: 7350057588420 | E105: Active | F105: Accessory | H105: - | I105: - | J105: =$J$1 -> EUR | K105: =IF($J$1="SEK / NOK",(VLOOKUP(A105,'RRP data'!A:C,3,FALSE)),(IF($J$1="DKK",(VLOOKUP('RRP data'!A105,'RRP data'!A:D,4,FALSE)),(IF($J$1="EUR",(VLOOKUP(A105,'RRP data'!A:E,5,FALSE))))))) -> 40 | M105: 10 | N105: 1 | P105: TR | Q105: 94019990 | R105: 34 | S105: 89 | T105: 1 | U105: 0.3 | V105: 6 | W105: 22.5 | X105: 36.5 | Y105: 0.4 | Z105: =PRODUCT(V105:X105)/1000000 -> 0.0049275 | AA105: 40°
A106: 805016 | B106: Axkid x Geggamoja Car Seat Cover Minikid 2/Move | C106: Wildlife | D106: 7350057589274 | E106: Active | F106: Accessory | G106: EN1888 | H106: - | I106: - | J106: =$J$1 -> EUR | K106: =IF($J$1="SEK / NOK",(VLOOKUP(A106,'RRP data'!A:C,3,FALSE)),(IF($J$1="DKK",(VLOOKUP('RRP data'!A106,'RRP data'!A:D,4,FALSE)),(IF($J$1="EUR",(VLOOKUP(A106,'RRP data'!A:E,5,FALSE))))))) -> 69 | P106: CN | Q106: 94019990 | R106: 85 | S106: 45 | T106: 0.2 | U106: 0.1 | V106: 30 | W106: 30 | X106: 0.5 | Y106: 0.103 | Z106: =PRODUCT(V106:X106)/1000000 -> 0.00045 | AA106: 30°
A107: 805026 | B107: Axkid x Geggamoja Car Seat Cover Minikid 2/Move | C107: Dreamer | D107: 7350057589281 | E107: Active | F107: Accessory | G107: EN1888 | H107: - | I107: - | J107: =$J$1 -> EUR | K107: =IF($J$1="SEK / NOK",(VLOOKUP(A107,'RRP data'!A:C,3,FALSE)),(IF($J$1="DKK",(VLOOKUP('RRP data'!A107,'RRP data'!A:D,4,FALSE)),(IF($J$1="EUR",(VLOOKUP(A107,'RRP data'!A:E,5,FALSE))))))) -> 69 | P107: CN | Q107: 94019990 | R107: 85 | S107: 45 | T107: 0.2 | U107: 0.1 | V107: 30 | W107: 30 | X107: 0.5 | Y107: 0.103 | Z107: =PRODUCT(V107:X107)/1000000 -> 0.00045 | AA107: 30°
A108: 805019 | B108: Axkid x Geggamoja Car Seat Cover Minikid 3 | C108: Wildlife | D108: 7350057589311 | E108: Active | F108: Accessory | G108: EN1888 | H108: - | I108: - | J108: =$J$1 -> EUR | K108: =IF($J$1="SEK / NOK",(VLOOKUP(A108,'RRP data'!A:C,3,FALSE)),(IF($J$1="DKK",(VLOOKUP('RRP data'!A108,'RRP data'!A:D,4,FALSE)),(IF($J$1="EUR",(VLOOKUP(A108,'RRP data'!A:E,5,FALSE))))))) -> 69 | P108: CN | Q108: 94019990 | R108: 85 | S108: 45 | T108: 0.2 | U108: 0.1 | V108: 30 | W108: 30 | X108: 0.5 | Y108: 0.103 | Z108: =PRODUCT(V108:X108)/1000000 -> 0.00045 | AA108: 30°
A109: 805029 | B109: Axkid x Geggamoja Car Seat Cover Minikid 3 | C109: Dreamer | D109: 7350057589328 | E109: Active | F109: Accessory | G109: EN1888 | H109: - | I109: - | J109: =$J$1 -> EUR | K109: =IF($J$1="SEK / NOK",(VLOOKUP(A109,'RRP data'!A:C,3,FALSE)),(IF($J$1="DKK",(VLOOKUP('RRP data'!A109,'RRP data'!A:D,4,FALSE)),(IF($J$1="EUR",(VLOOKUP(A109,'RRP data'!A:E,5,FALSE))))))) -> 69 | P109: CN | Q109: 94019990 | R109: 85 | S109: 45 | T109: 0.2 | U109: 0.1 | V109: 30 | W109: 30 | X109: 0.5 | Y109: 0.103 | Z109: =PRODUCT(V109:X109)/1000000 -> 0.00045 | AA109: 30°
A110: 805017 | B110: Axkid x Geggamoja Car Seat Cover ONE | C110: Wildlife | D110: 7350057589298 | E110: Active | F110: Accessory | G110: EN1888 | H110: - | I110: - | J110: =$J$1 -> EUR | K110: =IF($J$1="SEK / NOK",(VLOOKUP(A110,'RRP data'!A:C,3,FALSE)),(IF($J$1="DKK",(VLOOKUP('RRP data'!A110,'RRP data'!A:D,4,FALSE)),(IF($J$1="EUR",(VLOOKUP(A110,'RRP data'!A:E,5,FALSE))))))) -> 69 | P110: CN | Q110: 94019990 | R110: 85 | S110: 45 | T110: 0.2 | U110: 0.1 | V110: 30 | W110: 30 | X110: 0.5 | Y110: 0.103 | Z110: =PRODUCT(V110:X110)/1000000 -> 0.00045 | AA110: 30°
A111: 805027 | B111: Axkid x Geggamoja Car Seat Cover ONE | C111: Dreamer | D111: 7350057589304 | E111: Active | F111: Accessory | G111: EN1888 | H111: - | I111: - | J111: =$J$1 -> EUR | K111: =IF($J$1="SEK / NOK",(VLOOKUP(A111,'RRP data'!A:C,3,FALSE)),(IF($J$1="DKK",(VLOOKUP('RRP data'!A111,'RRP data'!A:D,4,FALSE)),(IF($J$1="EUR",(VLOOKUP(A111,'RRP data'!A:E,5,FALSE))))))) -> 69 | P111: CN | Q111: 94019990 | R111: 85 | S111: 45 | T111: 0.2 | U111: 0.1 | V111: 30 | W111: 30 | X111: 0.5 | Y111: 0.103 | Z111: =PRODUCT(V111:X111)/1000000 -> 0.00045 | AA111: 30°
A112: 803916 | B112: Axkid x Geggamoja Sunshades for Window | C112: Wildlife | D112: 7350057589335 | E112: Active | F112: Accessory | G112: EN1888 | H112: - | I112: - | J112: =$J$1 -> EUR | K112: =IF($J$1="SEK / NOK",(VLOOKUP(A112,'RRP data'!A:C,3,FALSE)),(IF($J$1="DKK",(VLOOKUP('RRP data'!A112,'RRP data'!A:D,4,FALSE)),(IF($J$1="EUR",(VLOOKUP(A112,'RRP data'!A:E,5,FALSE))))))) -> 69 | P112: CN | Q112: 94019990 | R112: 38 | S112: 44 | T112: 0.2 | U112: 0.16 | V112: 18 | W112: 6 | X112: 16 | Y112: 0.33 | Z112: =PRODUCT(V112:X112)/1000000 -> 0.001728 | AA112: Not washable
A113: 803926 | B113: Axkid x Geggamoja Sunshades for Window | C113: Dreamer | D113: 7350057589342 | E113: Active | F113: Accessory | G113: EN1888 | H113: - | I113: - | J113: =$J$1 -> EUR | K113: =IF($J$1="SEK / NOK",(VLOOKUP(A113,'RRP data'!A:C,3,FALSE)),(IF($J$1="DKK",(VLOOKUP('RRP data'!A113,'RRP data'!A:D,4,FALSE)),(IF($J$1="EUR",(VLOOKUP(A113,'RRP data'!A:E,5,FALSE))))))) -> 69 | P113: CN | Q113: 94019990 | R113: 38 | S113: 44 | T113: 0.2 | U113: 0.16 | V113: 18 | W113: 6 | X113: 16 | Y113: 0.33 | Z113: =PRODUCT(V113:X113)/1000000 -> 0.001728 | AA113: Not washable
A114: 20060016 | B114: Axkid Envirobaby Tar | C114: Tar Black | D114: 7350057587812 | E114: Upcoming | F114: Infant carrier | G114: UN R129 | H114: 0-1 years | I114: 40-75cm | J114: =$J$1 -> EUR | K114: =IF($J$1="SEK / NOK",(VLOOKUP(A114,'RRP data'!A:C,3,FALSE)),(IF($J$1="DKK",(VLOOKUP('RRP data'!A114,'RRP data'!A:D,4,FALSE)),(IF($J$1="EUR",(VLOOKUP(A114,'RRP data'!A:E,5,FALSE))))))) -> 299.9 | L114: 230 | M114: 1 | N114: 1 | P114: CN | Q114: 94018000 | R114: 43 | S114: 54 | T114: 65 | U114: 3.7 | V114: 71 | W114: 44 | X114: 36 | Y114: 5.6 | Z114: =PRODUCT(V114:X114)/1000000 -> 0.112464 | AA114: 30°
A115: 20060017 | B115: Axkid Envirobaby Granite | C115: Granite Grey | D115: 7350057588468 | E115: Upcoming | F115: Infant carrier | G115: UN R129 | H115: 0-1 years | I115: 40-75cm | J115: =$J$1 -> EUR | K115: =IF($J$1="SEK / NOK",(VLOOKUP(A115,'RRP data'!A:C,3,FALSE)),(IF($J$1="DKK",(VLOOKUP('RRP data'!A115,'RRP data'!A:D,4,FALSE)),(IF($J$1="EUR",(VLOOKUP(A115,'RRP data'!A:E,5,FALSE))))))) -> 299.9 | L115: 230 | M115: 1 | N115: 1 | P115: CN | Q115: 94018000 | R115: 43 | S115: 54 | T115: 65 | U115: 3.7 | V115: 71 | W115: 44 | X115: 36 | Y115: 5.6 | Z115: =PRODUCT(V115:X115)/1000000 -> 0.112464 | AA115: 30°
A116: 20060028 | B116: Axkid Envirobaby Forest | C116: Forest Green | D116: 7350057588475 | E116: Upcoming | F116: Infant carrier | G116: UN R129 | H116: 0-1 years | I116: 40-75cm | J116: =$J$1 -> EUR | K116: =IF($J$1="SEK / NOK",(VLOOKUP(A116,'RRP data'!A:C,3,FALSE)),(IF($J$1="DKK",(VLOOKUP('RRP data'!A116,'RRP data'!A:D,4,FALSE)),(IF($J$1="EUR",(VLOOKUP(A116,'RRP data'!A:E,5,FALSE))))))) -> 299.9 | L116: 230 | M116: 1 | N116: 1 | P116: CN | Q116: 94018000 | R116: 43 | S116: 54 | T116: 65 | U116: 3.7 | V116: 71 | W116: 44 | X116: 36 | Y116: 5.6 | Z116: =PRODUCT(V116:X116)/1000000 -> 0.112464 | AA116: 30°
A117: 21030003 | B117: Axkid Envirobase | C117: Black | D117: 7350057588482 | E117: Upcoming | F117: Base | G117: UN R129 | H117: n/a | I117: - | J117: =$J$1 -> EUR | K117: =IF($J$1="SEK / NOK",(VLOOKUP(A117,'RRP data'!A:C,3,FALSE)),(IF($J$1="DKK",(VLOOKUP('RRP data'!A117,'RRP data'!A:D,4,FALSE)),(IF($J$1="EUR",(VLOOKUP(A117,'RRP data'!A:E,5,FALSE))))))) -> 199.9 | L117: 500 | M117: 1 | N117: 1 | P117: CN | Q117: 94018000 | R117: 43 | S117: 30 | T117: 65 | U117: 7 | V117: 61 | W117: 39 | X117: 23 | Y117: 8.8 | Z117: =PRODUCT(V117:X117)/1000000 -> 0.054717 | AA117: 30°
A118: 24100316 | B118: Axkid Envirokid Tar | C118: Tar Black | D118: 7350057588499 | E118: Upcoming | F118: Rear-facing car seat | G118: UN R129 | H118: 6 months - 4 years | I118: 61-105cm (max 18kg) | J118: =$J$1 -> EUR | K118: =IF($J$1="SEK / NOK",(VLOOKUP(A118,'RRP data'!A:C,3,FALSE)),(IF($J$1="DKK",(VLOOKUP('RRP data'!A118,'RRP data'!A:D,4,FALSE)),(IF($J$1="EUR",(VLOOKUP(A118,'RRP data'!A:E,5,FALSE))))))) -> 399.9 | L118: 210 | M118: 1 | N118: 1 | P118: CN | Q118: 94018000 | R118: 43 | S118: 62 | T118: 52 | U118: 7.5 | V118: 71 | W118: 47 | X118: 44 | Y118: 10.5 | Z118: =PRODUCT(V118:X118)/1000000 -> 0.146828 | AA118: 30°
A119: 24100317 | B119: Axkid Envirokid Granite | C119: Granite Grey | D119: 7350057588505 | E119: Upcoming | F119: Rear-facing car seat | G119: UN R129 | H119: 6 months - 4 years | I119: 61-105cm (max 18kg) | J119: =$J$1 -> EUR | K119: =IF($J$1="SEK / NOK",(VLOOKUP(A119,'RRP data'!A:C,3,FALSE)),(IF($J$1="DKK",(VLOOKUP('RRP data'!A119,'RRP data'!A:D,4,FALSE)),(IF($J$1="EUR",(VLOOKUP(A119,'RRP data'!A:E,5,FALSE))))))) -> 399.9 | L119: 210 | M119: 1 | N119: 1 | P119: CN | Q119: 94018000 | R119: 43 | S119: 62 | T119: 52 | U119: 7.5 | V119: 71 | W119: 47 | X119: 44 | Y119: 10.5 | Z119: =PRODUCT(V119:X119)/1000000 -> 0.146828 | AA119: 30°
A120: 24100328 | B120: Axkid Envirokid Forest | C120: Forest Green | D120: 7350057588512 | E120: Upcoming | F120: Rear-facing car seat | G120: UN R129 | H120: 6 months - 4 years | I120: 61-105cm (max 18kg) | J120: =$J$1 -> EUR | K120: =IF($J$1="SEK / NOK",(VLOOKUP(A120,'RRP data'!A:C,3,FALSE)),(IF($J$1="DKK",(VLOOKUP('RRP data'!A120,'RRP data'!A:D,4,FALSE)),(IF($J$1="EUR",(VLOOKUP(A120,'RRP data'!A:E,5,FALSE))))))) -> 399.9 | L120: 210 | M120: 1 | N120: 1 | P120: CN | Q120: 94018000 | R120: 43 | S120: 62 | T120: 52 | U120: 7.5 | V120: 71 | W120: 47 | X120: 44 | Y120: 10.5 | Z120: =PRODUCT(V120:X120)/1000000 -> 0.146828 | AA120: 30°
A121: 24110116 | B121: Axkid Spinkid Solid Tar | C121: Tar Black | D121: 7350057589731 | E121: Upcoming | F121: Rear-facing car seat | G121: UN R129 | I121: 40-105cm (max18kg) | J121: =$J$1 -> EUR | K121: =IF($J$1="SEK / NOK",(VLOOKUP(A121,'RRP data'!A:C,3,FALSE)),(IF($J$1="DKK",(VLOOKUP('RRP data'!A121,'RRP data'!A:D,4,FALSE)),(IF($J$1="EUR",(VLOOKUP(A121,'RRP data'!A:E,5,FALSE))))))) -> 499.9 | L121: 351 | M121: 1 | N121: 1 | P121: CN | Q121: 94018000 | R121: 44 | S121: 63 | T121: 63 | U121: 14.5 | V121: 78 | W121: 58 | X121: 46 | Y121: 17.5 | Z121: =PRODUCT(V121:X121)/1000000 -> 0.208104 | AA121: 30°
A122: 24110121 | B122: Axkid Spinkid Granite Melange | C122: Granite Grey Melange | D122: 7350057589748 | E122: Upcoming | F122: Rear-facing car seat | G122: UN R129 | I122: 40-105cm (max18kg) | J122: =$J$1 -> EUR | K122: =IF($J$1="SEK / NOK",(VLOOKUP(A122,'RRP data'!A:C,3,FALSE)),(IF($J$1="DKK",(VLOOKUP('RRP data'!A122,'RRP data'!A:D,4,FALSE)),(IF($J$1="EUR",(VLOOKUP(A122,'RRP data'!A:E,5,FALSE))))))) -> 499.9 | L122: 351 | M122: 1 | N122: 1 | P122: CN | Q122: 94018000 | R122: 44 | S122: 63 | T122: 63 | U122: 14.5 | V122: 78 | W122: 58 | X122: 46 | Y122: 17.5 | Z122: =PRODUCT(V122:X122)/1000000 -> 0.208104 | AA122: 30°
A123: 24110124 | B123: Axkid Spinkid Brick Melange | C123: Brick Beige Melange | D123: 7350057589755 | E123: Upcoming | F123: Rear-facing car seat | G123: UN R129 | I123: 40-105cm (max18kg) | J123: =$J$1 -> EUR | K123: =IF($J$1="SEK / NOK",(VLOOKUP(A123,'RRP data'!A:C,3,FALSE)),(IF($J$1="DKK",(VLOOKUP('RRP data'!A123,'RRP data'!A:D,4,FALSE)),(IF($J$1="EUR",(VLOOKUP(A123,'RRP data'!A:E,5,FALSE))))))) -> 499.9 | L123: 351 | M123: 1 | N123: 1 | P123: CN | Q123: 94018000 | R123: 44 | S123: 63 | T123: 63 | U123: 14.5 | V123: 78 | W123: 58 | X123: 46 | Y123: 17.5 | Z123: =PRODUCT(V123:X123)/1000000 -> 0.208104 | AA123: 30°
A124: 24110125 | B124: Axkid Spinkid Tile Melange | C124: Tile Red Melange | D124: 7350057589762 | E124: Upcoming | F124: Rear-facing car seat | G124: UN R129 | I124: 40-105cm (max18kg) | J124: =$J$1 -> EUR | K124: =IF($J$1="SEK / NOK",(VLOOKUP(A124,'RRP data'!A:C,3,FALSE)),(IF($J$1="DKK",(VLOOKUP('RRP data'!A124,'RRP data'!A:D,4,FALSE)),(IF($J$1="EUR",(VLOOKUP(A124,'RRP data'!A:E,5,FALSE))))))) -> 499.9 | L124: 351 | M124: 1 | N124: 1 | P124: CN | Q124: 94018000 | R124: 44 | S124: 63 | T124: 63 | U124: 14.5 | V124: 78 | W124: 58 | X124: 46 | Y124: 17.5 | Z124: =PRODUCT(V124:X124)/1000000 -> 0.208104 | AA124: 30°
A125: 27060123 | B125: Axkid Nextkid Shell Black | C125: Shell Black | D125: 7350057589793 | E125: Upcoming | F125: Booster seat | G125: UN R129 | I125: 100-150 cm or 15-36kg | J125: =$J$1 -> EUR | K125: =IF($J$1="SEK / NOK",(VLOOKUP(A125,'RRP data'!A:C,3,FALSE)),(IF($J$1="DKK",(VLOOKUP('RRP data'!A125,'RRP data'!A:D,4,FALSE)),(IF($J$1="EUR",(VLOOKUP(A125,'RRP data'!A:E,5,FALSE))))))) -> 249.9 | L125: 521 | M125: 1 | N125: 1 | P125: CN | Q125: 94018000 | R125: 44 | S125: 63.4 | T125: 47.3 | U125: 7.5 | V125: 64 | W125: 46.5 | X125: 45 | Y125: 9 | Z125: =PRODUCT(V125:X125)/1000000 -> 0.13392 | AA125: 30°
A126: 27060121 | B126: Axkid Nextkid Granite Melange | C126: Granite Grey Melange | D126: 7350057589809 | E126: Upcoming | F126: Booster seat | G126: UN R129 | I126: 100-150 cm or 15-36kg | J126: =$J$1 -> EUR | K126: =IF($J$1="SEK / NOK",(VLOOKUP(A126,'RRP data'!A:C,3,FALSE)),(IF($J$1="DKK",(VLOOKUP('RRP data'!A126,'RRP data'!A:D,4,FALSE)),(IF($J$1="EUR",(VLOOKUP(A126,'RRP data'!A:E,5,FALSE))))))) -> 249.9 | L126: 521 | M126: 1 | N126: 1 | P126: CN | Q126: 94018000 | R126: 44 | S126: 63.4 | T126: 47.3 | U126: 7.5 | V126: 64 | W126: 46.5 | X126: 45 | Y126: 9 | Z126: =PRODUCT(V126:X126)/1000000 -> 0.13392 | AA126: 30°
A127: 27060190 | B127: Axkid Nextkid Cloud Grey | C127: Cloud Grey | D127: 7350150970139 | E127: Upcoming | F127: Booster seat | G127: UN R129 | I127: 100-150 cm or 15-36kg | J127: =$J$1 -> EUR | K127: =IF($J$1="SEK / NOK",(VLOOKUP(A127,'RRP data'!A:C,3,FALSE)),(IF($J$1="DKK",(VLOOKUP('RRP data'!A127,'RRP data'!A:D,4,FALSE)),(IF($J$1="EUR",(VLOOKUP(A127,'RRP data'!A:E,5,FALSE))))))) -> 249.9 | L127: 521 | M127: 1 | N127: 1 | P127: CN | Q127: 94018000 | R127: 44 | S127: 63.4 | T127: 47.3 | U127: 7.5 | V127: 64 | W127: 46.5 | X127: 45 | Y127: 9 | Z127: =PRODUCT(V127:X127)/1000000 -> 0.13392 | AA127: 30°
A128: 801803 | B128: Axkid Baby Cushion Premium | C128: Black | D128: 7350057589953 | E128: Upcoming | F128: Accessory | G128: - | I128: - | J128: =$J$1 -> EUR | K128: =IF($J$1="SEK / NOK",(VLOOKUP(A128,'RRP data'!A:C,3,FALSE)),(IF($J$1="DKK",(VLOOKUP('RRP data'!A128,'RRP data'!A:D,4,FALSE)),(IF($J$1="EUR",(VLOOKUP(A128,'RRP data'!A:E,5,FALSE))))))) -> 24.9 | L128: 3700 | M128: 40 | N128: 1 | P128: CN | Q128: 94019990 | R128: 39 | S128: 5 | T128: 49 | U128: 0.14 | V128: 37.5 | W128: 24 | X128: 7 | Y128: 0.25 | Z128: =PRODUCT(V128:X128)/1000000 -> 0.0063 | AA128: Not washable
A129: 806601 | B129: Axkid Lower tether anchorages 120mm | C129: Black | D129: 7350057589670 | E129: Upcoming | F129: Accessory | G129: SS-ISO 13216 | H129: - | I129: - | J129: =$J$1 -> EUR | K129: =IF($J$1="SEK / NOK",(VLOOKUP(A129,'RRP data'!A:C,3,FALSE)),(IF($J$1="DKK",(VLOOKUP('RRP data'!A129,'RRP data'!A:D,4,FALSE)),(IF($J$1="EUR",(VLOOKUP(A129,'RRP data'!A:E,5,FALSE))))))) -> 22.9 | L129: - | N129: 1 | P129: CN | Q129: 94019990 | R129: 12 | S129: 8 | T129: 3 | U129: 0.17 | V129: 12 | W129: 8 | X129: 3 | Y129: 0.17 | Z129: =PRODUCT(V129:X129)/1000000 -> 0.000288 | AA129: Not washable
A130: 806602 | B130: Axkid Lower tether anchorages 160mm | C130: Black | D130: 7350057589687 | E130: Upcoming | F130: Accessory | G130: SS-ISO 13216 | H130: - | I130: - | J130: =$J$1 -> EUR | K130: =IF($J$1="SEK / NOK",(VLOOKUP(A130,'RRP data'!A:C,3,FALSE)),(IF($J$1="DKK",(VLOOKUP('RRP data'!A130,'RRP data'!A:D,4,FALSE)),(IF($J$1="EUR",(VLOOKUP(A130,'RRP data'!A:E,5,FALSE))))))) -> 24.9 | L130: - | N130: 1 | P130: CN | Q130: 94019990 | R130: 140 | S130: 100 | T130: 3 | U130: 0.12 | V130: 140 | W130: 100 | X130: 3 | Y130: 0.12 | Z130: =PRODUCT(V130:X130)/1000000 -> 0.042 | AA130: -
A131: 31000016 | B131: Axkid Grand Tour Black | C131: Black | D131: 7350057589977 | E131: Upcoming | F131: Urban Safety | G131: EN15918:2011+A2:2017 EN1888-1:2018 EK2/AK2.3 14-01.1:2015 EN71-3:2019+A1:2021 | H131: 6 mån-4years | I131: 45 kg + 111cm | J131: =$J$1 -> EUR | K131: 849.9 | L131: 350 | M131: 1 | N131: 1 | P131: CN | Q131: 8715000010 | R131: 80 | S131: 91 | T131: 143 | U131: 18.8 | V131: 100 | W131: 28 | X131: 69 | Y131: 20.8 | Z131: =PRODUCT(V131:X131)/1000000 -> 0.1932 | AA131: Do not wash in the washing machine. Clean your pack and components in a bathtub or large sink using mild detergent and warm water. Hang to dry outdoors or in a well-ventilated area out of direct sunlight.
A132: 801114 | B132: Grand Tour Jogging Wheel | C132: Black | D132: 7350150970009 | E132: Upcoming | F132: Urban Safety | G132: - | H132: - | I132: - | J132: =$J$1 -> EUR | K132: 99.9 | M132: 80 | N132: 1 | P132: CN | Q132: 8715000010 | R132: 43 | S132: 38 | T132: 13 | U132: 1.5 | V132: 44 | W132: 14 | X132: 39 | Y132: 2 | Z132: =PRODUCT(V132:X132)/1000000 -> 0.024024
A133: 801214 | B133: Grand Tour Rain Cover | C133: Transparent | D133: 7350150970016 | E133: Upcoming | F133: Urban Safety | G133: - | H133: - | I133: - | J133: =$J$1 -> EUR | K133: 49.9 | M133: 100 | N133: 1 | P133: CN | Q133: 8715000010 | U133: 0.35 | V133: 35 | W133: 23 | X133: 4 | Y133: 0.42 | Z133: =PRODUCT(V133:X133)/1000000 -> 0.00322
A134: 801314 | B134: Grand Tour Storage Cover | C134: Black | D134: 7350150970177 | E134: Upcoming | F134: Urban Safety | G134: - | H134: - | I134: - | J134: =$J$1 -> EUR | K134: 49.9 | M134: 100 | N134: 1 | P134: CN | Q134: 8715000010 | U134: 0.3 | V134: 33 | W134: 31 | X134: 5 | Y134: 0.37 | Z134: =PRODUCT(V134:X134)/1000000 -> 0.005115
A135: 801515 | B135: Grand Tour Cup Holder | C135: Black | D135: 7350150970191 | E135: Upcoming | F135: Urban Safety | G135: - | H135: - | I135: - | J135: =$J$1 -> EUR | K135: 29.9 | M135: 70 | N135: 1 | P135: CN | Q135: 8715000010 | R135: 15 | S135: 11 | T135: 11 | U135: 0.17 | V135: 18 | W135: 13 | X135: 12 | Y135: 0.27 | Z135: =PRODUCT(V135:X135)/1000000 -> 0.002808
A136: 801414 | B136: Grand Tour Baby Insert | C136: Black | D136: 7350150970184 | E136: Upcoming | F136: Urban Safety | G136: - | H136: - | J136: =$J$1 -> EUR | P136: CN | Q136: 8715000010 | Z136: =PRODUCT(V136:X136)/1000000 -> 0
A137: 1104933 | B137: Bike Adapter (GT) | C137: Black | D137: 7350150970061 | E137: Upcoming | F137: Urban Safety | G137: - | H137: - | I137: - | J137: =$J$1 -> EUR | K137: 19.9 | L137: - | P137: CN | Q137: 8715000010 | Z137: =PRODUCT(V137:X137)/1000000 -> 0
A138: 32000016 | B138: Axkid Tour Tar | C138: Tar Black | D138: 7350057589984 | E138: Upcoming | F138: Urban Safety | G138: EN 13209-1:2022 | I138: max 18 kg | J138: =$J$1 -> EUR | K138: =IF($J$1="SEK / NOK",(VLOOKUP(A138,'RRP data'!A:C,3,FALSE)),(IF($J$1="DKK",(VLOOKUP('RRP data'!A132,'RRP data'!A:D,4,FALSE)),(IF($J$1="EUR",(VLOOKUP(A138,'RRP data'!A:E,5,FALSE))))))) -> - | L138: 900 | M138: 1 | N138: 1 | P138: CN | Q138: 4202129000 | R138: 39 | S138: 68 | T138: 52 | U138: 3.1 | V138: 76 | W138: 40 | X138: 26 | Y138: 4 | Z138: =PRODUCT(V138:X138)/1000000 -> 0.07904 | AA138: Do not wash in the washing machine. Clean your pack and components in a bathtub or large sink using mild detergent and warm water. Hang to dry outdoors or in a well-ventilated area out of direct sunlight.
A139: 32000019 | B139: Axkid Tour Sea | C139: Sea Blue | D139: 7350057589991 | E139: Upcoming | F139: Urban Safety | G139: EN 13209-1:2023 | I139: max 18 kg | J139: =$J$1 -> EUR | K139: =IF($J$1="SEK / NOK",(VLOOKUP(A139,'RRP data'!A:C,3,FALSE)),(IF($J$1="DKK",(VLOOKUP('RRP data'!A133,'RRP data'!A:D,4,FALSE)),(IF($J$1="EUR",(VLOOKUP(A139,'RRP data'!A:E,5,FALSE))))))) -> - | L139: 900 | M139: 1 | N139: 1 | P139: CN | Q139: 4202129000 | R139: 39 | S139: 68 | T139: 52 | U139: 3.1 | V139: 76 | W139: 40 | X139: 26 | Y139: 4 | Z139: =PRODUCT(V139:X139)/1000000 -> 0.07904 | AA139: Do not wash in the washing machine. Clean your pack and components in a bathtub or large sink using mild detergent and warm water. Hang to dry outdoors or in a well-ventilated area out of direct sunlight.
A140: 22150216 | B140: Axkid Minikid 4 Tar | C140: Tar Black | D140: 7350057589601 | E140: Upcoming | F140: Rear-facing car seat | G140: UN R129 | H140: 0-7 years | I140: 61-125cm (max 36kg) | J140: =$J$1 -> EUR | K140: =IF($J$1="SEK / NOK",(VLOOKUP(A140,'RRP data'!A:C,3,FALSE)),(IF($J$1="DKK",(VLOOKUP('RRP data'!A134,'RRP data'!A:D,4,FALSE)),(IF($J$1="EUR",(VLOOKUP(A140,'RRP data'!A:E,5,FALSE))))))) -> 649.9 | L140: 509 | M140: 1 | N140: 1 | P140: CN | Q140: 94018000 | R140: 44 | S140: 65 | T140: 54 | U140: 11 | V140: 46 | W140: 58 | X140: 66 | Y140: 14 | Z140: =PRODUCT(V140:X140)/1000000 -> 0.176088 | AA140: 30°
A141: 22150221 | B141: Axkid Minikid 4 Granite Melange | C141: Granite Grey Melange | D141: 7350057589663 | E141: Upcoming | F141: Rear-facing car seat | G141: UN R129 | H141: 0-7 years | I141: 61-125cm (max 36kg) | J141: =$J$1 -> EUR | K141: =IF($J$1="SEK / NOK",(VLOOKUP(A141,'RRP data'!A:C,3,FALSE)),(IF($J$1="DKK",(VLOOKUP('RRP data'!A135,'RRP data'!A:D,4,FALSE)),(IF($J$1="EUR",(VLOOKUP(A141,'RRP data'!A:E,5,FALSE))))))) -> 649.9 | L141: 509 | M141: 1 | N141: 1 | P141: CN | Q141: 94018000 | R141: 44 | S141: 65 | T141: 54 | U141: 11 | V141: 46 | W141: 58 | X141: 66 | Y141: 14 | Z141: =PRODUCT(V141:X141)/1000000 -> 0.176088 | AA141: 30°
A142: 22150224 | B142: Axkid Minikid 4 Brick Melange | C142: Brick Beige Melange | D142: 7350057589618 | E142: Upcoming | F142: Rear-facing car seat | G142: UN R129 | H142: 0-7 years | I142: 61-125cm (max 36kg) | J142: =$J$1 -> EUR | K142: =IF($J$1="SEK / NOK",(VLOOKUP(A142,'RRP data'!A:C,3,FALSE)),(IF($J$1="DKK",(VLOOKUP('RRP data'!A136,'RRP data'!A:D,4,FALSE)),(IF($J$1="EUR",(VLOOKUP(A142,'RRP data'!A:E,5,FALSE))))))) -> 649.9 | L142: 509 | M142: 1 | N142: 1 | P142: CN | Q142: 94018000 | R142: 44 | S142: 65 | T142: 54 | U142: 11 | V142: 46 | W142: 58 | X142: 66 | Y142: 14 | Z142: =PRODUCT(V142:X142)/1000000 -> 0.176088 | AA142: 30°
A143: 22150225 | B143: Axkid Minikid 4 Tile Melange | C143: Tile Red Melange | D143: 7350057589625 | E143: Upcoming | F143: Rear-facing car seat | G143: UN R129 | H143: 0-7 years | I143: 61-125cm (max 36kg) | J143: =$J$1 -> EUR | K143: =IF($J$1="SEK / NOK",(VLOOKUP(A143,'RRP data'!A:C,3,FALSE)),(IF($J$1="DKK",(VLOOKUP('RRP data'!A137,'RRP data'!A:D,4,FALSE)),(IF($J$1="EUR",(VLOOKUP(A143,'RRP data'!A:E,5,FALSE))))))) -> 649.9 | L143: 509 | M143: 1 | N143: 1 | P143: CN | Q143: 94018000 | R143: 44 | S143: 65 | T143: 54 | U143: 11 | V143: 46 | W143: 58 | X143: 66 | Y143: 14 | Z143: =PRODUCT(V143:X143)/1000000 -> 0.176088 | AA143: 30°
A144: 801215 | B144: Axkid Cup Holder Nextkid | C144: Black | D144: 7350150970160 | E144: Upcoming | F144: Accessory | H144: - | I144: - | J144: =$J$1 -> EUR | K144: =IF($J$1="SEK / NOK",(VLOOKUP(A144,'RRP data'!A:C,3,FALSE)),(IF($J$1="DKK",(VLOOKUP('RRP data'!A138,'RRP data'!A:D,4,FALSE)),(IF($J$1="EUR",(VLOOKUP(A144,'RRP data'!A:E,5,FALSE))))))) -> 24.9 | L144: - | P144: CN | Q144: 94019990 | R144: 12 | S144: 8.5 | T144: 9 | U144: 62 | V144: 12 | W144: 12 | X144: 10 | Y144: 0.1 | Z144: =PRODUCT(V144:X144)/1000000 -> 0.00144 | AA144: -
A145: 22170016 | B145: Axkid Movekid Tar | C145: Tar Black | D145: 7350150970238 | E145: Upcoming | F145: Rear-facing car seat | J145: =$J$1 -> EUR | K145: =IF($J$1="SEK / NOK",(VLOOKUP(A145,'RRP data'!A:C,3,FALSE)),(IF($J$1="DKK",(VLOOKUP('RRP data'!A139,'RRP data'!A:D,4,FALSE)),(IF($J$1="EUR",(VLOOKUP(A145,'RRP data'!A:E,5,FALSE))))))) -> 449.9 | L145: 509 | M145: 1 | N145: 1 | P145: CN | Q145: 94018000 | V145: 46 | W145: 58 | X145: 66 | Z145: =PRODUCT(V145:X145)/1000000 -> 0.176088 | AA145: 30°
A146: 22170017 | B146: Axkid Movekid Granite | C146: Granite Grey | D146: 7350150970245 | E146: Upcoming | F146: Rear-facing car seat | J146: =$J$1 -> EUR | K146: =IF($J$1="SEK / NOK",(VLOOKUP(A146,'RRP data'!A:C,3,FALSE)),(IF($J$1="DKK",(VLOOKUP('RRP data'!A140,'RRP data'!A:D,4,FALSE)),(IF($J$1="EUR",(VLOOKUP(A146,'RRP data'!A:E,5,FALSE))))))) -> 449.9 | L146: 509 | M146: 1 | N146: 1 | P146: CN | Q146: 94018000 | V146: 46 | W146: 58 | X146: 66 | Z146: =PRODUCT(V146:X146)/1000000 -> 0.176088 | AA146: 30°

Sheet RRP data
A1: Item number | B1: Name | C1: SEK/NOK | D1: DKK | E1: EUR | AB1: SEK / NOK
A2: 200302 | B2: =VLOOKUP(Table2[[#This Row],[Item number]],'Axkid Template'!A:C,2,FALSE) -> #N/A | C2: 1499 | D2: 999 | E2: 149 | AB2: DKK
A3: 200303 | B3: =VLOOKUP(Table2[[#This Row],[Item number]],'Axkid Template'!A:C,2,FALSE) -> #N/A | C3: 1499 | D3: 999 | E3: 149 | AB3: EUR
A4: 210103 | B4: =VLOOKUP(Table2[[#This Row],[Item number]],'Axkid Template'!A:C,2,FALSE) -> Axkid Babyfix Base Black | C4: 1000 | D4: 500 | E4: 100
A5: 22140201 | B5: =VLOOKUP(Table2[[#This Row],[Item number]],'Axkid Template'!A:C,2,FALSE) -> #N/A | C5: 3999 | D5: 2999 | E5: 399
A6: 22140202 | B6: =VLOOKUP(Table2[[#This Row],[Item number]],'Axkid Template'!A:C,2,FALSE) -> #N/A | C6: 3999 | D6: 2999 | E6: 399
A7: 22140203 | B7: =VLOOKUP(Table2[[#This Row],[Item number]],'Axkid Template'!A:C,2,FALSE) -> #N/A | C7: 3999 | D7: 2999 | E7: 399
A8: 22140210 | B8: =VLOOKUP(Table2[[#This Row],[Item number]],'Axkid Template'!A:C,2,FALSE) -> #N/A | C8: 3999 | D8: 2999 | E8: 399
A9: 22140211 | B9: =VLOOKUP(Table2[[#This Row],[Item number]],'Axkid Template'!A:C,2,FALSE) -> #N/A | C9: 3999 | D9: 2999 | E9: 399
A10: 22140213 | B10: =VLOOKUP(Table2[[#This Row],[Item number]],'Axkid Template'!A:C,2,FALSE) -> #N/A | C10: 3999 | D10: 2999 | E10: 399
A11: 22120102 | B11: =VLOOKUP(Table2[[#This Row],[Item number]],'Axkid Template'!A:C,2,FALSE) -> Axkid Move Grey | C11: 2999 | D11: 1799 | E11: 279
A12: 22120103 | B12: =VLOOKUP(Table2[[#This Row],[Item number]],'Axkid Template'!A:C,2,FALSE) -> Axkid Move Black | C12: 2999 | D12: 1799 | E12: 279
A13: 20040001 | B13: =VLOOKUP(Table2[[#This Row],[Item number]],'Axkid Template'!A:C,2,FALSE) -> #N/A | C13: 1999 | D13: 1450 | E13: 199
A14: 20040002 | B14: =VLOOKUP(Table2[[#This Row],[Item number]],'Axkid Template'!A:C,2,FALSE) -> #N/A | C14: 1999 | D14: 1450 | E14: 199
A15: 20040003 | B15: =VLOOKUP(Table2[[#This Row],[Item number]],'Axkid Template'!A:C,2,FALSE) -> #N/A | C15: 1999 | D15: 1450 | E15: 199
... A17: 20040013 | B17: =VLOOKUP(Table2[[#This Row],[Item number]],'Axkid Template'!A:C,2,FALSE) -> #N/A | C17: 1999 | D17: 1450 | E17: 199
A18: 21020003 | B18: =VLOOKUP(Table2[[#This Row],[Item number]],'Axkid Template'!A:C,2,FALSE) -> Axkid Modukid Base | C18: 2499 | D18: - | E18: 100
A19: 24100001 | B19: =VLOOKUP(Table2[[#This Row],[Item number]],'Axkid Template'!A:C,2,FALSE) -> #N/A | C19: 3499 | D19: 2599 | E19: 349
A20: 24100002 | B20: =VLOOKUP(Table2[[#This Row],[Item number]],'Axkid Template'!A:C,2,FALSE) -> #N/A | C20: 3499 | D20: 2599 | E20: 349
A21: 24100003 | B21: =VLOOKUP(Table2[[#This Row],[Item number]],'Axkid Template'!A:C,2,FALSE) -> #N/A | C21: 3499 | D21: 2599 | E21: 349
A22: 24100011 | B22: =VLOOKUP(Table2[[#This Row],[Item number]],'Axkid Template'!A:C,2,FALSE) -> #N/A | C22: 3499 | D22: 2599 | E22: 349
A23: 24100013 | B23: =VLOOKUP(Table2[[#This Row],[Item number]],'Axkid Template'!A:C,2,FALSE) -> #N/A | C23: 3499 | D23: 2599 | E23: 349
A24: 260301 | B24: =VLOOKUP(Table2[[#This Row],[Item number]],'Axkid Template'!A:C,2,FALSE) -> Axkid Rekid Red | C24: 4999 | D24: 3999 | E24: 469
A25: 260302 | B25: =VLOOKUP(Table2[[#This Row],[Item number]],'Axkid Template'!A:C,2,FALSE) -> Axkid Rekid Grey | C25: 4999 | D25: 3999 | E25: 469
A26: 260303 | B26: =VLOOKUP(Table2[[#This Row],[Item number]],'Axkid Template'!A:C,2,FALSE) -> Axkid Rekid Black | C26: 4999 | D26: 3999 | E26: 469
A27: 260311 | B27: =VLOOKUP(Table2[[#This Row],[Item number]],'Axkid Template'!A:C,2,FALSE) -> Axkid Rekid Petrol | C27: 4999 | D27: 3999 | E27: 469
A28: 27040002 | B28: =VLOOKUP(Table2[[#This Row],[Item number]],'Axkid Template'!A:C,2,FALSE) -> #N/A | C28: 2399 | D28: 1699 | E28: 239
A29: 27040003 | B29: =VLOOKUP(Table2[[#This Row],[Item number]],'Axkid Template'!A:C,2,FALSE) -> #N/A | C29: 2399 | D29: 1699 | E29: 239
A30: 26040002 | B30: =VLOOKUP(Table2[[#This Row],[Item number]],'Axkid Template'!A:C,2,FALSE) -> Axkid Bigkid Grey | C30: 1899 | D30: 1399 | E30: 189
... A37: 800507 | B37: =VLOOKUP(Table2[[#This Row],[Item number]],'Axkid Template'!A:C,2,FALSE) -> Axkid Baby on board sign | C37: 99 | D37: 45 | E37: 19
A38: 800608 | B38: =VLOOKUP(Table2[[#This Row],[Item number]],'Axkid Template'!A:C,2,FALSE) -> Axkid Attachment loops | C38: 199 | D38: - | E38: 19.9
A39: 800803 | B39: =VLOOKUP(Table2[[#This Row],[Item number]],'Axkid Template'!A:C,2,FALSE) -> Axkid Baby cushion | C39: 199 | D39: 109 | E39: 19
A40: 801003 | B40: =VLOOKUP(Table2[[#This Row],[Item number]],'Axkid Template'!A:C,2,FALSE) -> Axkid Adapter babyfix | C40: 249 | D40: 189 | E40: 19
A41: 801106 | B41: =VLOOKUP(Table2[[#This Row],[Item number]],'Axkid Template'!A:C,2,FALSE) -> Axkid Summer cover Minikid, rekid & Modukid seat | C41: 249 | D41: 199 | E41: 19
A42: 801206 | B42: =VLOOKUP(Table2[[#This Row],[Item number]],'Axkid Template'!A:C,2,FALSE) -> Axkid Summer cover Dallas/Grow | C42: 249 | D42: 199 | E42: 19
A43: 801403 | B43: =VLOOKUP(Table2[[#This Row],[Item number]],'Axkid Template'!A:C,2,FALSE) -> Axkid Angle adjusting wedge | C43: 169 | D43: 129 | E43: 17
A44: 803303 | B44: =VLOOKUP(Table2[[#This Row],[Item number]],'Axkid Template'!A:C,2,FALSE) -> Axkid Baby mirror | C44: 299 | D44: 149 | E44: 19
A45: 803803 | B45: =VLOOKUP(Table2[[#This Row],[Item number]],'Axkid Template'!A:C,2,FALSE) -> Axkid Seat protection Premium | C45: 649 | D45: 349 | E45: 50
A46: 803906 | B46: =VLOOKUP(Table2[[#This Row],[Item number]],'Axkid Template'!A:C,2,FALSE) -> Axkid Sunshades for window self attaching | C46: 199 | D46: 75 | E46: 9
A47: 804003 | B47: =VLOOKUP(Table2[[#This Row],[Item number]],'Axkid Template'!A:C,2,FALSE) -> Axkid iPad holder | C47: 199 | D47: 129 | E47: 18
A48: 804103 | B48: =VLOOKUP(Table2[[#This Row],[Item number]],'Axkid Template'!A:C,2,FALSE) -> Axkid Backseat organizer | C48: 299 | D48: 189 | E48: 19
A49: 804303 | B49: =VLOOKUP(Table2[[#This Row],[Item number]],'Axkid Template'!A:C,2,FALSE) -> Axkid Tether straps for Move | C49: 349 | D49: 189 | E49: 29
A50: 804503 | B50: =VLOOKUP(Table2[[#This Row],[Item number]],'Axkid Template'!A:C,2,FALSE) -> Axkid Sun cover (seat sunshade) | C50: 369 | D50: 219 | E50: 35
... A115: 25120125 | B115: =VLOOKUP(Table2[[#This Row],[Item number]],'Axkid Template'!A:C,2,FALSE) -> Axkid ONE+ 2 Tile Melange | C115: 10499 | D115: 6299 | E115: 849
A116: 22140316 | B116: =VLOOKUP(Table2[[#This Row],[Item number]],'Axkid Template'!A:C,2,FALSE) -> Axkid Minikid 2 (2022/23) Tar | C116: 4999 | D116: - | E116: 429
A117: 22140317 | B117: =VLOOKUP(Table2[[#This Row],[Item number]],'Axkid Template'!A:C,2,FALSE) -> Axkid Minikid 2 (2022/23) Granite | C117: 4999 | D117: - | E117: 429
A118: 22140318 | B118: =VLOOKUP(Table2[[#This Row],[Item number]],'Axkid Template'!A:C,2,FALSE) -> Axkid Minikid 2 (2022/23) Shellfish | C118: 4999 | D118: - | E118: 429
A119: 22140319 | B119: =VLOOKUP(Table2[[#This Row],[Item number]],'Axkid Template'!A:C,2,FALSE) -> Axkid Minikid 2 (2022/23) Sea | C119: 4999 | D119: - | E119: 429
A120: 22140320 | B120: =VLOOKUP(Table2[[#This Row],[Item number]],'Axkid Template'!A:C,2,FALSE) -> Axkid Minikid 2 (2022/23) Moss | C120: 4999 | D120: - | E120: 429
A121: 22140321 | B121: =VLOOKUP(Table2[[#This Row],[Item number]],'Axkid Template'!A:C,2,FALSE) -> Axkid Minikid 2 (2022/23) Premium Shell Black | C121: 5299 | D121: - | E121: 449
A122: 22140322 | B122: =VLOOKUP(Table2[[#This Row],[Item number]],'Axkid Template'!A:C,2,FALSE) -> Axkid Minikid 2 (2022/23) Premium Granite Melange | C122: 5299 | D122: - | E122: 449
A123: 22120227 | B123: =VLOOKUP(Table2[[#This Row],[Item number]],'Axkid Template'!A:C,2,FALSE) -> Axkid Move (2022/23) Granite | C123: 2999 | D123: - | E123: 299
A124: 22120226 | B124: =VLOOKUP(Table2[[#This Row],[Item number]],'Axkid Template'!A:C,2,FALSE) -> Axkid Move (2022/23) Tar | C124: 2999 | D124: - | E124: 299
A125: 22150116 | B125: =VLOOKUP(Table2[[#This Row],[Item number]],'Axkid Template'!A:C,2,FALSE) -> Axkid Minikid 3 Tar | C125: 6499 | D125: - | E125: 549
A126: 22150117 | B126: =VLOOKUP(Table2[[#This Row],[Item number]],'Axkid Template'!A:C,2,FALSE) -> Axkid Minikid 3 Granite | C126: 6499 | D126: - | E126: 549
A127: 22150118 | B127: =VLOOKUP(Table2[[#This Row],[Item number]],'Axkid Template'!A:C,2,FALSE) -> Axkid Minikid 3 Shellfish | C127: 6499 | D127: - | E127: 549
... A131: 22150122 | B131: =VLOOKUP(Table2[[#This Row],[Item number]],'Axkid Template'!A:C,2,FALSE) -> Axkid Minikid 3 Premium Granite Melange | C131: 6799 | D131: - | E131: 599
A132: 22150123 | B132: =VLOOKUP(Table2[[#This Row],[Item number]],'Axkid Template'!A:C,2,FALSE) -> #N/A | C132: 6799 | E132: 599
A133: 28100026 | B133: =VLOOKUP(Table2[[#This Row],[Item number]],'Axkid Template'!A:C,2,FALSE) -> Axkid Mate Tar | C133: 499 | D133: - | E133: 40
A134: 28100027 | B134: =VLOOKUP(Table2[[#This Row],[Item number]],'Axkid Template'!A:C,2,FALSE) -> Axkid Mate Granite | C134: 499 | D134: - | E134: 40
A135: 806201 | B135: =VLOOKUP(Table2[[#This Row],[Item number]],'Axkid Template'!A:C,2,FALSE) -> Axkid Cooling Pads by AeroMoov group 2/3 | C135: 499 | D135: 299 | E135: 40
A136: 805007 | B136: =VLOOKUP(Table2[[#This Row],[Item number]],'Axkid Template'!A:C,2,FALSE) -> Axkid Bamboo Summer cover ONE | C136: 599 | D136: 349 | E136: 50
A137: 805008 | B137: =VLOOKUP(Table2[[#This Row],[Item number]],'Axkid Template'!A:C,2,FALSE) -> Axkid Bamboo Summer cover Bigkid | C137: 599 | D137: 349 | E137: 50
A138: 805016 | B138: =VLOOKUP(Table2[[#This Row],[Item number]],'Axkid Template'!A:C,2,FALSE) -> Axkid x Geggamoja Car Seat Cover Minikid 2/Move | C138: 699 | D138: - | E138: 69
A139: 805026 | B139: =VLOOKUP(Table2[[#This Row],[Item number]],'Axkid Template'!A:C,2,FALSE) -> Axkid x Geggamoja Car Seat Cover Minikid 2/Move | C139: 699 | D139: - | E139: 69
A140: 805019 | B140: =VLOOKUP(Table2[[#This Row],[Item number]],'Axkid Template'!A:C,2,FALSE) -> Axkid x Geggamoja Car Seat Cover Minikid 3 | C140: 699 | D140: - | E140: 69
A141: 805029 | B141: =VLOOKUP(Table2[[#This Row],[Item number]],'Axkid Template'!A:C,2,FALSE) -> Axkid x Geggamoja Car Seat Cover Minikid 3 | C141: 699 | D141: - | E141: 69
A142: 805017 | B142: =VLOOKUP(Table2[[#This Row],[Item number]],'Axkid Template'!A:C,2,FALSE) -> Axkid x Geggamoja Car Seat Cover ONE | C142: 699 | D142: - | E142: 69
A143: 805027 | B143: =VLOOKUP(Table2[[#This Row],[Item number]],'Axkid Template'!A:C,2,FALSE) -> Axkid x Geggamoja Car Seat Cover ONE | C143: 699 | D143: - | E143: 69
A144: 803916 | B144: =VLOOKUP(Table2[[#This Row],[Item number]],'Axkid Template'!A:C,2,FALSE) -> Axkid x Geggamoja Sunshades for Window | C144: 199 | D144: - | E144: 69
A145: 803926 | B145: =VLOOKUP(Table2[[#This Row],[Item number]],'Axkid Template'!A:C,2,FALSE) -> Axkid x Geggamoja Sunshades for Window | C145: 199 | D145: - | E145: 69
A146: 20060016 | B146: =VLOOKUP(Table2[[#This Row],[Item number]],'Axkid Template'!A:C,2,FALSE) -> Axkid Envirobaby Tar | C146: 2999 | D146: - | E146: 299.9
A147: 20060017 | B147: =VLOOKUP(Table2[[#This Row],[Item number]],'Axkid Template'!A:C,2,FALSE) -> Axkid Envirobaby Granite | C147: 2999 | D147: - | E147: 299.9
A148: 20060026 | B148: =VLOOKUP(Table2[[#This Row],[Item number]],'Axkid Template'!A:C,2,FALSE) -> #N/A | C148: - | D148: - | E148: -
A149: 21020103 | B149: =VLOOKUP(Table2[[#This Row],[Item number]],'Axkid Template'!A:C,2,FALSE) -> #N/A | C149: - | D149: - | E149: -
A150: 24100316 | B150: =VLOOKUP(Table2[[#This Row],[Item number]],'Axkid Template'!A:C,2,FALSE) -> Axkid Envirokid Tar | C150: 3999 | D150: - | E150: 399.9
A151: 24100317 | B151: =VLOOKUP(Table2[[#This Row],[Item number]],'Axkid Template'!A:C,2,FALSE) -> Axkid Envirokid Granite | C151: 3999 | D151: - | E151: 399.9
A152: 24100326 | B152: =VLOOKUP(Table2[[#This Row],[Item number]],'Axkid Template'!A:C,2,FALSE) -> #N/A | C152: - | D152: - | E152: -
A153: 24110116 | B153: =VLOOKUP(Table2[[#This Row],[Item number]],'Axkid Template'!A:C,2,FALSE) -> Axkid Spinkid Solid Tar | C153: 4999 | D153: - | E153: 499.9
A154: 24110121 | B154: =VLOOKUP(Table2[[#This Row],[Item number]],'Axkid Template'!A:C,2,FALSE) -> Axkid Spinkid Granite Melange | C154: 4999 | D154: - | E154: 499.9
A155: 24110124 | B155: =VLOOKUP(Table2[[#This Row],[Item number]],'Axkid Template'!A:C,2,FALSE) -> Axkid Spinkid Brick Melange | C155: 4999 | D155: - | E155: 499.9
A156: 24110125 | B156: =VLOOKUP(Table2[[#This Row],[Item number]],'Axkid Template'!A:C,2,FALSE) -> Axkid Spinkid Tile Melange | C156: 4999 | D156: - | E156: 499.9
A157: 27060123 | B157: =VLOOKUP(Table2[[#This Row],[Item number]],'Axkid Template'!A:C,2,FALSE) -> Axkid Nextkid Shell Black | C157: 2499 | D157: - | E157: 249.9
A158: 27060121 | B158: =VLOOKUP(Table2[[#This Row],[Item number]],'Axkid Template'!A:C,2,FALSE) -> Axkid Nextkid Granite Melange | C158: 2499 | D158: - | E158: 249.9
A159: 27060190 | B159: =VLOOKUP(Table2[[#This Row],[Item number]],'Axkid Template'!A:C,2,FALSE) -> Axkid Nextkid Cloud Grey | C159: 2499 | D159: - | E159: 249.9
A160: 801803 | B160: =VLOOKUP(Table2[[#This Row],[Item number]],'Axkid Template'!A:C,2,FALSE) -> Axkid Baby Cushion Premium | C160: 249 | D160: - | E160: 24.9
A161: 806601 | B161: =VLOOKUP(Table2[[#This Row],[Item number]],'Axkid Template'!A:C,2,FALSE) -> Axkid Lower tether anchorages 120mm | C161: 229 | D161: - | E161: 22.9
A162: 806602 | B162: =VLOOKUP(Table2[[#This Row],[Item number]],'Axkid Template'!A:C,2,FALSE) -> Axkid Lower tether anchorages 160mm | C162: 249 | D162: - | E162: 24.9
A163: 31000016 | B163: =VLOOKUP(Table2[[#This Row],[Item number]],'Axkid Template'!A:C,2,FALSE) -> Axkid Grand Tour Black | C163: - | D163: - | E163: -
A164: 32000016 | B164: =VLOOKUP(Table2[[#This Row],[Item number]],'Axkid Template'!A:C,2,FALSE) -> Axkid Tour Tar | C164: - | D164: - | E164: -
A165: 32000019 | B165: =VLOOKUP(Table2[[#This Row],[Item number]],'Axkid Template'!A:C,2,FALSE) -> Axkid Tour Sea | C165: - | D165: - | E165: -
A166: 22150216 | B166: =VLOOKUP(Table2[[#This Row],[Item number]],'Axkid Template'!A:C,2,FALSE) -> Axkid Minikid 4 Tar | C166: 6499 | D166: - | E166: 649.9
A167: 22150221 | B167: =VLOOKUP(Table2[[#This Row],[Item number]],'Axkid Template'!A:C,2,FALSE) -> Axkid Minikid 4 Granite Melange | C167: 6499 | D167: - | E167: 649.9
A168: 22150224 | B168: =VLOOKUP(Table2[[#This Row],[Item number]],'Axkid Template'!A:C,2,FALSE) -> Axkid Minikid 4 Brick Melange | C168: 6499 | D168: - | E168: 649.9
A169: 22150225 | B169: =VLOOKUP(Table2[[#This Row],[Item number]],'Axkid Template'!A:C,2,FALSE) -> Axkid Minikid 4 Tile Melange | C169: 6499 | E169: 649.9
A170: 20060028 | B170: =VLOOKUP(Table2[[#This Row],[Item number]],'Axkid Template'!A:C,2,FALSE) -> Axkid Envirobaby Forest | C170: 2999 | E170: 299.9
A171: 21030003 | B171: =VLOOKUP(Table2[[#This Row],[Item number]],'Axkid Template'!A:C,2,FALSE) -> Axkid Envirobase | C171: 1999 | E171: 199.9
A172: 24100328 | B172: =VLOOKUP(Table2[[#This Row],[Item number]],'Axkid Template'!A:C,2,FALSE) -> Axkid Envirokid Forest | C172: 3999 | E172: 399.9
A173: 801215 | B173: =VLOOKUP(Table2[[#This Row],[Item number]],'Axkid Template'!A:C,2,FALSE) -> Axkid Cup Holder Nextkid | C173: 249 | E173: 24.9
A174: 22170016 | B174: =VLOOKUP(Table2[[#This Row],[Item number]],'Axkid Template'!A:C,2,FALSE) -> Axkid Movekid Tar | C174: 4499 | E174: 449.9
...

Sheet Axkid Template - SE
A1: Axkid Template | J1: SEK / NOK | Q1: Produkt storlek | T1: Kartongstorlek
A2: Artikel Namn | B2: Artikel Nummer | C2: Färg | D2: EAN kod | E2: Modell | F2: Modell beskrivning | G2: Rekommenderad ålder | H2: Grupp | I2: Maxvikt | J2: Valuta | K2: Rek Pris | L2: Inköpskvantitet | M2: Försäljningskvantitet | N2: Beskrivning | O2: Ursprungsland | P2: Intrastat nummer | Q2: Bredd i CM | R2: Höjd i CM | S2: Djup i CM | T2: Längd i CM | U2: Bredd i CM | V2: Höjd i CM | W2: Brutto vikt | X2: Netto vikt | Y2: Tvättbar | Z2: Egenskaper
A3: Axkid Babyfix Grå | B3: 200302 | C3: Grå | D3: 7350057581933 | E3: 0-13KG | F3: Babyskydd ECE R44 | G3: - | I3: 13kg | J3: =$J$1 -> SEK / NOK | K3: =IF(J3="SEK / NOK",(VLOOKUP(B3,'RRP data'!A:E,2,FALSE)),(IF(J3="DKK",(VLOOKUP('Axkid Template - SE'!B3,'RRP data'!A:E,4,FALSE)),(IF(J3="EUR",(VLOOKUP(B3,'RRP data'!A:E,5,FALSE))))))) -> #N/A | L3: 1 | M3: 1 | N3: Babyskyddet Axkid Babyfix ger maximal säkerhet och trygghet för det nyfödda barnet under de första månaderna i livet. Att det också är ett av marknadens lättaste babyskydd med en vikt på 3,5 kg gör inte saken sämre. Nackkudden tillsammans med de mjuka axelmuddarna gör resan bekväm för ditt barn. En extra urtagbar babydyna levereras med babyskyddet, för de allra minsta. Axkid Babyfix är godkänd 0–13 kg enligt ECE R44/04. Vi rekommenderar alltid att börja med babyskyddet eftersom det är bäst anpassat för de allra minsta. När ditt barn växt ur babyskyddet är det dags att byta till en bakåtvänd bilbarnstol. Axkid Babyfix installerar du smidigast med Axkid Babyfix Bas. Basen installerar du antingen med bilens trepunktsbälte eller med ISOFIX. Med ett enkelt klick tar du babyskyddet i eller ur bilen och ditt barn kan tryggt sova vidare i Axkid Babyfix. Väljer du att installera Axkid Babyfix utan bas använder du dig av bilens trepunktsbälte. När babyskyddet inte är installerat i bilen kan det användas som gungstol, matstol eller babysitter tack vare att handtaget kan justeras i fem olika lägen. Solskyddet har en extra utvikningsbar skärm för att skydda ditt barn från solens starka strålar. | O3: CN | P3: 94018000 | Q3: 43 | R3: 54 | S3: 65 | T3: 45 | U3: 58 | V3: 67 | W3: 5.79 | X3: 3.4 | Y3: 30° | Z3: Best Budget Choice - Bäst-i-test.se
A4: Axkid Babyfix Svart | B4: 200303 | C4: Svart | D4: 7350057581940 | E4: 0-13KG | F4: Babyskydd ECE R44 | G4: - | I4: 13kg | J4: =$J$1 -> SEK / NOK | K4: =IF(J4="SEK / NOK",(VLOOKUP(B4,'RRP data'!A:E,2,FALSE)),(IF(J4="DKK",(VLOOKUP('Axkid Template - SE'!B4,'RRP data'!A:E,4,FALSE)),(IF(J4="EUR",(VLOOKUP(B4,'RRP data'!A:E,5,FALSE))))))) -> #N/A | L4: 1 | M4: 1 | N4: Babyskyddet Axkid Babyfix ger maximal säkerhet och trygghet för det nyfödda barnet under de första månaderna i livet. Att det också är ett av marknadens lättaste babyskydd med en vikt på 3,5 kg gör inte saken sämre. Nackkudden tillsammans med de mjuka axelmuddarna gör resan bekväm för ditt barn. En extra urtagbar babydyna levereras med babyskyddet, för de allra minsta. Axkid Babyfix är godkänd 0–13 kg enligt ECE R44/04. Vi rekommenderar alltid att börja med babyskyddet eftersom det är bäst anpassat för de allra minsta. När ditt barn växt ur babyskyddet är det dags att byta till en bakåtvänd bilbarnstol. Axkid Babyfix installerar du smidigast med Axkid Babyfix Bas. Basen installerar du antingen med bilens trepunktsbälte eller med ISOFIX. Med ett enkelt klick tar du babyskyddet i eller ur bilen och ditt barn kan tryggt sova vidare i Axkid Babyfix. Väljer du att installera Axkid Babyfix utan bas använder du dig av bilens trepunktsbälte. När babyskyddet inte är installerat i bilen kan det användas som gungstol, matstol eller babysitter tack vare att handtaget kan justeras i fem olika lägen. Solskyddet har en extra utvikningsbar skärm för att skydda ditt barn från solens starka strålar. | O4: CN | P4: 94018000 | Q4: 43 | R4: 54 | S4: 65 | T4: 45 | U4: 58 | V4: 67 | W4: 5.79 | X4: 3.4 | Y4: 30° | Z4: Best Budget Choice - Bäst-i-test.se
A5: Axkid Babyfix Bas Svart | B5: 210103 | C5: Svart | D5: 7350057580042 | E5: ISOFIX BAS | F5: Bas till Babyskydd ECE R44 | G5: - | I5: 13kg | J5: =$J$1 -> SEK / NOK | K5: =IF(J5="SEK / NOK",(VLOOKUP(B5,'RRP data'!A:E,2,FALSE)),(IF(J5="DKK",(VLOOKUP('Axkid Template - SE'!B5,'RRP data'!A:E,4,FALSE)),(IF(J5="EUR",(VLOOKUP(B5,'RRP data'!A:E,5,FALSE))))))) -> Axkid Babyfix Base Black | L5: 1 | M5: 1 | N5: Babyskyddet Axkid Babyfix ger maximal säkerhet och trygghet för det nyfödda barnet under de första månaderna i livet. Att det också är ett av marknadens lättaste babyskydd med en vikt på 3,5 kg gör inte saken sämre. Nackkudden tillsammans med de mjuka axelmuddarna gör resan bekväm för ditt barn. En extra urtagbar babydyna levereras med babyskyddet, för de allra minsta. Axkid Babyfix är godkänd 0–13 kg enligt ECE R44/04. Vi rekommenderar alltid att börja med babyskyddet eftersom det är bäst anpassat för de allra minsta. När ditt barn växt ur babyskyddet är det dags att byta till en bakåtvänd bilbarnstol. Axkid Babyfix installerar du smidigast med Axkid Babyfix Bas. Basen installerar du antingen med bilens trepunktsbälte eller med ISOFIX. Med ett enkelt klick tar du babyskyddet i eller ur bilen och ditt barn kan tryggt sova vidare i Axkid Babyfix. Väljer du att installera Axkid Babyfix utan bas använder du dig av bilens trepunktsbälte. När babyskyddet inte är installerat i bilen kan det användas som gungstol, matstol eller babysitter tack vare att handtaget kan justeras i fem olika lägen. Solskyddet har en extra utvikningsbar skärm för att skydda ditt barn från solens starka strålar. | O5: CN | P5: 94018000 | Q5: 33 | R5: 43 | S5: 69 | T5: 34 | U5: 20 | V5: 60.5 | W5: 5.45 | X5: 4.63 | Y5: 30° | Z5: Best Budget Choice - Bäst-i-test.se
A6: Axkid Minikid Röd | B6: 22140201 | C6: Röd | D6: 7350057582350 | E6: 0-25KG | F6: Bilbarnstol ECE R44 | G6: - | I6: 25kg | J6: =$J$1 -> SEK / NOK | K6: =IF(J6="SEK / NOK",(VLOOKUP(B6,'RRP data'!A:E,2,FALSE)),(IF(J6="DKK",(VLOOKUP('Axkid Template - SE'!B6,'RRP data'!A:E,4,FALSE)),(IF(J6="EUR",(VLOOKUP(B6,'RRP data'!A:E,5,FALSE))))))) -> #N/A | L6: 1 | M6: 1 | N6: Den bakåtvända bilbarnstolen, Axkid Minikid 2018, är framtagen för att ge bästa möjliga säkerhet och komfort för både små och stora barn, och möjliggör bakåtvänt åkande så länge som möjligt. Nya Axkid Minikid levereras med det innovativa sidokrocksskyddet – ASIP (Axkid Side Impact Protection) som är framtaget tillsammans med ett erkänt krockinstitiut i Tyskland, och ger bästa möjliga skydd för barnet vid eventuell krock från sidan. ASIP ska användas på den sidan av bilbarnstolen som är ut mot bildörren, vid användning i mitten behöver inte ASIP användas. Stödbenet på bilbarnstolen Axkid Minikid har utvecklats och förbättrats, och kommer nu att kunna sträckas ut med enbart en knapp, som enklare går att komma åt. Klädseln har förbättrats och momentet att trä av och på klädseln har förenklats, så att möjligheten att tvätta klädseln blir smidigare. Nackstödet är tjockare och mer ombonat, för optimal komfort för barnet när de sover. Den unika funktionen med nackstödet och internselen, som justeras automatiskt efter barnets längd och storlek när du drar åt bältet, finns kvar med en tydligare nackstödsbroms. De självåtdragande underförankringsbanden gör installationen smidig, då bilbarnstolen vickas på plats. De fem främre lutningslägena möjliggör optimal lutning för just ditt barn, beroende på ålder och längd. Skulle det behövas ännu mer lutning är vår lutningskil ett bra komplement. Axkid Minikid är godkänd 0–25 kg (cirka 125 cm, 6 år) och har fått utmärkta omdömen av flera oberoende testinstitut. Den är Plusgodkänd upp till 25 kg, fått utmärkelsen ”Bra Val 2015” av Folksam, ”Bästa prisvärde” av Bäst-i-Test.se och är Rollover-godkänd av VCA. Axkid Minikid levereras alltid med en svart babydyna, för att ge bättre support för de allra minsta barnen. Axkid Minikid, 0–25 kg, ersätter inte babyskyddet. Vi rekommenderar alltid att börja med babyskyddet eftersom det är bäst anpassat för de allra minsta. När ditt barn växt ur babyskyddet är Axkid Minikid ett bra val för ditt barn att åka bakåtvänt i länge. | O6: CN | P6: 94018000 | Q6: 44 | R6: 62 | S6: 56 | T6: 46 | U6: 58 | V6: 66 | W6: 13.8 | X6: 11.4 | Y6: 30° | Z6: Plus approved up to 25kg , Good Chocie 2015 by Folksam, Best cost Value - Bäst-i-test.se, Rullover approved, REACH tested
A7: Axkid Minikid Grå | B7: 22140202 | C7: Grå | D7: 7350057582366 | E7: 0-25KG | F7: Bilbarnstol ECE R44 | G7: - | I7: 25kg | J7: =$J$1 -> SEK / NOK | K7: =IF(J7="SEK / NOK",(VLOOKUP(B7,'RRP data'!A:E,2,FALSE)),(IF(J7="DKK",(VLOOKUP('Axkid Template - SE'!B7,'RRP data'!A:E,4,FALSE)),(IF(J7="EUR",(VLOOKUP(B7,'RRP data'!A:E,5,FALSE))))))) -> #N/A | L7: 1 | M7: 1 | N7: Den bakåtvända bilbarnstolen, Axkid Minikid 2018, är framtagen för att ge bästa möjliga säkerhet och komfort för både små och stora barn, och möjliggör bakåtvänt åkande så länge som möjligt. Nya Axkid Minikid levereras med det innovativa sidokrocksskyddet – ASIP (Axkid Side Impact Protection) som är framtaget tillsammans med ett erkänt krockinstitiut i Tyskland, och ger bästa möjliga skydd för barnet vid eventuell krock från sidan. ASIP ska användas på den sidan av bilbarnstolen som är ut mot bildörren, vid användning i mitten behöver inte ASIP användas. Stödbenet på bilbarnstolen Axkid Minikid har utvecklats och förbättrats, och kommer nu att kunna sträckas ut med enbart en knapp, som enklare går att komma åt. Klädseln har förbättrats och momentet att trä av och på klädseln har förenklats, så att möjligheten att tvätta klädseln blir smidigare. Nackstödet är tjockare och mer ombonat, för optimal komfort för barnet när de sover. Den unika funktionen med nackstödet och internselen, som justeras automatiskt efter barnets längd och storlek när du drar åt bältet, finns kvar med en tydligare nackstödsbroms. De självåtdragande underförankringsbanden gör installationen smidig, då bilbarnstolen vickas på plats. De fem främre lutningslägena möjliggör optimal lutning för just ditt barn, beroende på ålder och längd. Skulle det behövas ännu mer lutning är vår lutningskil ett bra komplement. Axkid Minikid är godkänd 0–25 kg (cirka 125 cm, 6 år) och har fått utmärkta omdömen av flera oberoende testinstitut. Den är Plusgodkänd upp till 25 kg, fått utmärkelsen ”Bra Val 2015” av Folksam, ”Bästa prisvärde” av Bäst-i-Test.se och är Rollover-godkänd av VCA. Axkid Minikid levereras alltid med en svart babydyna, för att ge bättre support för de allra minsta barnen. Axkid Minikid, 0–25 kg, ersätter inte babyskyddet. Vi rekommenderar alltid att börja med babyskyddet eftersom det är bäst anpassat för de allra minsta. När ditt barn växt ur babyskyddet är Axkid Minikid ett bra val för ditt barn att åka bakåtvänt i länge. | O7: CN | P7: 94018000 | Q7: 44 | R7: 62 | S7: 56 | T7: 46 | U7: 58 | V7: 66 | W7: 13.8 | X7: 11.4 | Y7: 30° | Z7: Plus approved up to 25kg , Good Chocie 2015 by Folksam, Best cost Value - Bäst-i-test.se, Rullover approved, REACH tested
A8: Axkid Minikid Svart | B8: 22140203 | C8: Svart | D8: 7350057582374 | E8: 0-25KG | F8: Bilbarnstol ECE R44 | G8: - | I8: 25kg | J8: =$J$1 -> SEK / NOK | K8: =IF(J8="SEK / NOK",(VLOOKUP(B8,'RRP data'!A:E,2,FALSE)),(IF(J8="DKK",(VLOOKUP('Axkid Template - SE'!B8,'RRP data'!A:E,4,FALSE)),(IF(J8="EUR",(VLOOKUP(B8,'RRP data'!A:E,5,FALSE))))))) -> #N/A | L8: 1 | M8: 1 | N8: Den bakåtvända bilbarnstolen, Axkid Minikid 2018, är framtagen för att ge bästa möjliga säkerhet och komfort för både små och stora barn, och möjliggör bakåtvänt åkande så länge som möjligt. Nya Axkid Minikid levereras med det innovativa sidokrocksskyddet – ASIP (Axkid Side Impact Protection) som är framtaget tillsammans med ett erkänt krockinstitiut i Tyskland, och ger bästa möjliga skydd för barnet vid eventuell krock från sidan. ASIP ska användas på den sidan av bilbarnstolen som är ut mot bildörren, vid användning i mitten behöver inte ASIP användas. Stödbenet på bilbarnstolen Axkid Minikid har utvecklats och förbättrats, och kommer nu att kunna sträckas ut med enbart en knapp, som enklare går att komma åt. Klädseln har förbättrats och momentet att trä av och på klädseln har förenklats, så att möjligheten att tvätta klädseln blir smidigare. Nackstödet är tjockare och mer ombonat, för optimal komfort för barnet när de sover. Den unika funktionen med nackstödet och internselen, som justeras automatiskt efter barnets längd och storlek när du drar åt bältet, finns kvar med en tydligare nackstödsbroms. De självåtdragande underförankringsbanden gör installationen smidig, då bilbarnstolen vickas på plats. De fem främre lutningslägena möjliggör optimal lutning för just ditt barn, beroende på ålder och längd. Skulle det behövas ännu mer lutning är vår lutningskil ett bra komplement. Axkid Minikid är godkänd 0–25 kg (cirka 125 cm, 6 år) och har fått utmärkta omdömen av flera oberoende testinstitut. Den är Plusgodkänd upp till 25 kg, fått utmärkelsen ”Bra Val 2015” av Folksam, ”Bästa prisvärde” av Bäst-i-Test.se och är Rollover-godkänd av VCA. Axkid Minikid levereras alltid med en svart babydyna, för att ge bättre support för de allra minsta barnen. Axkid Minikid, 0–25 kg, ersätter inte babyskyddet. Vi rekommenderar alltid att börja med babyskyddet eftersom det är bäst anpassat för de allra minsta. När ditt barn växt ur babyskyddet är Axkid Minikid ett bra val för ditt barn att åka bakåtvänt i länge. | O8: CN | P8: 94018000 | Q8: 44 | R8: 62 | S8: 56 | T8: 46 | U8: 58 | V8: 66 | W8: 13.8 | X8: 11.4 | Y8: 30° | Z8: Plus approved up to 25kg , Good Chocie 2015 by Folksam, Best cost Value - Bäst-i-test.se, Rullover approved, REACH tested
A9: Axkid Minikid Grön | B9: 22140210 | C9: Grön | D9: 7350057582381 | E9: 0-25KG | F9: Bilbarnstol ECE R44 | G9: - | I9: 25kg | J9: =$J$1 -> SEK / NOK | K9: =IF(J9="SEK / NOK",(VLOOKUP(B9,'RRP data'!A:E,2,FALSE)),(IF(J9="DKK",(VLOOKUP('Axkid Template - SE'!B9,'RRP data'!A:E,4,FALSE)),(IF(J9="EUR",(VLOOKUP(B9,'RRP data'!A:E,5,FALSE))))))) -> #N/A | L9: 1 | M9: 1 | N9: Den bakåtvända bilbarnstolen, Axkid Minikid 2018, är framtagen för att ge bästa möjliga säkerhet och komfort för både små och stora barn, och möjliggör bakåtvänt åkande så länge som möjligt. Nya Axkid Minikid levereras med det innovativa sidokrocksskyddet – ASIP (Axkid Side Impact Protection) som är framtaget tillsammans med ett erkänt krockinstitiut i Tyskland, och ger bästa möjliga skydd för barnet vid eventuell krock från sidan. ASIP ska användas på den sidan av bilbarnstolen som är ut mot bildörren, vid användning i mitten behöver inte ASIP användas. Stödbenet på bilbarnstolen Axkid Minikid har utvecklats och förbättrats, och kommer nu att kunna sträckas ut med enbart en knapp, som enklare går att komma åt. Klädseln har förbättrats och momentet att trä av och på klädseln har förenklats, så att möjligheten att tvätta klädseln blir smidigare. Nackstödet är tjockare och mer ombonat, för optimal komfort för barnet när de sover. Den unika funktionen med nackstödet och internselen, som justeras automatiskt efter barnets längd och storlek när du drar åt bältet, finns kvar med en tydligare nackstödsbroms. De självåtdragande underförankringsbanden gör installationen smidig, då bilbarnstolen vickas på plats. De fem främre lutningslägena möjliggör optimal lutning för just ditt barn, beroende på ålder och längd. Skulle det behövas ännu mer lutning är vår lutningskil ett bra komplement. Axkid Minikid är godkänd 0–25 kg (cirka 125 cm, 6 år) och har fått utmärkta omdömen av flera oberoende testinstitut. Den är Plusgodkänd upp till 25 kg, fått utmärkelsen ”Bra Val 2015” av Folksam, ”Bästa prisvärde” av Bäst-i-Test.se och är Rollover-godkänd av VCA. Axkid Minikid levereras alltid med en svart babydyna, för att ge bättre support för de allra minsta barnen. Axkid Minikid, 0–25 kg, ersätter inte babyskyddet. Vi rekommenderar alltid att börja med babyskyddet eftersom det är bäst anpassat för de allra minsta. När ditt barn växt ur babyskyddet är Axkid Minikid ett bra val för ditt barn att åka bakåtvänt i länge. | O9: CN | P9: 94018000 | Q9: 44 | R9: 62 | S9: 56 | T9: 46 | U9: 58 | V9: 66 | W9: 13.8 | X9: 11.4 | Y9: 30° | Z9: Plus approved up to 25kg , Good Chocie 2015 by Folksam, Best cost Value - Bäst-i-test.se, Rullover approved, REACH tested
A10: Axkid Minikid Petrol | B10: 22140211 | C10: Petrol | D10: 7350057582398 | E10: 0-25KG | F10: Bilbarnstol ECE R44 | G10: - | I10: 25kg | J10: =$J$1 -> SEK / NOK | K10: =IF(J10="SEK / NOK",(VLOOKUP(B10,'RRP data'!A:E,2,FALSE)),(IF(J10="DKK",(VLOOKUP('Axkid Template - SE'!B10,'RRP data'!A:E,4,FALSE)),(IF(J10="EUR",(VLOOKUP(B10,'RRP data'!A:E,5,FALSE))))))) -> #N/A | L10: 1 | M10: 1 | N10: Den bakåtvända bilbarnstolen, Axkid Minikid 2018, är framtagen för att ge bästa möjliga säkerhet och komfort för både små och stora barn, och möjliggör bakåtvänt åkande så länge som möjligt. Nya Axkid Minikid levereras med det innovativa sidokrocksskyddet – ASIP (Axkid Side Impact Protection) som är framtaget tillsammans med ett erkänt krockinstitiut i Tyskland, och ger bästa möjliga skydd för barnet vid eventuell krock från sidan. ASIP ska användas på den sidan av bilbarnstolen som är ut mot bildörren, vid användning i mitten behöver inte ASIP användas. Stödbenet på bilbarnstolen Axkid Minikid har utvecklats och förbättrats, och kommer nu att kunna sträckas ut med enbart en knapp, som enklare går att komma åt. Klädseln har förbättrats och momentet att trä av och på klädseln har förenklats, så att möjligheten att tvätta klädseln blir smidigare. Nackstödet är tjockare och mer ombonat, för optimal komfort för barnet när de sover. Den unika funktionen med nackstödet och internselen, som justeras automatiskt efter barnets längd och storlek när du drar åt bältet, finns kvar med en tydligare nackstödsbroms. De självåtdragande underförankringsbanden gör installationen smidig, då bilbarnstolen vickas på plats. De fem främre lutningslägena möjliggör optimal lutning för just ditt barn, beroende på ålder och längd. Skulle det behövas ännu mer lutning är vår lutningskil ett bra komplement. Axkid Minikid är godkänd 0–25 kg (cirka 125 cm, 6 år) och har fått utmärkta omdömen av flera oberoende testinstitut. Den är Plusgodkänd upp till 25 kg, fått utmärkelsen ”Bra Val 2015” av Folksam, ”Bästa prisvärde” av Bäst-i-Test.se och är Rollover-godkänd av VCA. Axkid Minikid levereras alltid med en svart babydyna, för att ge bättre support för de allra minsta barnen. Axkid Minikid, 0–25 kg, ersätter inte babyskyddet. Vi rekommenderar alltid att börja med babyskyddet eftersom det är bäst anpassat för de allra minsta. När ditt barn växt ur babyskyddet är Axkid Minikid ett bra val för ditt barn att åka bakåtvänt i länge. | O10: CN | P10: 94018000 | Q10: 44 | R10: 62 | S10: 56 | T10: 46 | U10: 58 | V10: 66 | W10: 13.8 | X10: 11.4 | Y10: 30° | Z10: Plus approved up to 25kg , Good Chocie 2015 by Folksam, Best cost Value - Bäst-i-test.se, Rullover approved, REACH tested
A11: Axkid Minikid Rosa | B11: 22140213 | C11: Rosa | D11: 7350057582404 | E11: 0-25KG | F11: Bilbarnstol ECE R44 | G11: - | I11: 25kg | J11: =$J$1 -> SEK / NOK | K11: =IF(J11="SEK / NOK",(VLOOKUP(B11,'RRP data'!A:E,2,FALSE)),(IF(J11="DKK",(VLOOKUP('Axkid Template - SE'!B11,'RRP data'!A:E,4,FALSE)),(IF(J11="EUR",(VLOOKUP(B11,'RRP data'!A:E,5,FALSE))))))) -> #N/A | L11: 1 | M11: 1 | N11: Den bakåtvända bilbarnstolen, Axkid Minikid 2018, är framtagen för att ge bästa möjliga säkerhet och komfort för både små och stora barn, och möjliggör bakåtvänt åkande så länge som möjligt. Nya Axkid Minikid levereras med det innovativa sidokrocksskyddet – ASIP (Axkid Side Impact Protection) som är framtaget tillsammans med ett erkänt krockinstitiut i Tyskland, och ger bästa möjliga skydd för barnet vid eventuell krock från sidan. ASIP ska användas på den sidan av bilbarnstolen som är ut mot bildörren, vid användning i mitten behöver inte ASIP användas. Stödbenet på bilbarnstolen Axkid Minikid har utvecklats och förbättrats, och kommer nu att kunna sträckas ut med enbart en knapp, som enklare går att komma åt. Klädseln har förbättrats och momentet att trä av och på klädseln har förenklats, så att möjligheten att tvätta klädseln blir smidigare. Nackstödet är tjockare och mer ombonat, för optimal komfort för barnet när de sover. Den unika funktionen med nackstödet och internselen, som justeras automatiskt efter barnets längd och storlek när du drar åt bältet, finns kvar med en tydligare nackstödsbroms. De självåtdragande underförankringsbanden gör installationen smidig, då bilbarnstolen vickas på plats. De fem främre lutningslägena möjliggör optimal lutning för just ditt barn, beroende på ålder och längd. Skulle det behövas ännu mer lutning är vår lutningskil ett bra komplement. Axkid Minikid är godkänd 0–25 kg (cirka 125 cm, 6 år) och har fått utmärkta omdömen av flera oberoende testinstitut. Den är Plusgodkänd upp till 25 kg, fått utmärkelsen ”Bra Val 2015” av Folksam, ”Bästa prisvärde” av Bäst-i-Test.se och är Rollover-godkänd av VCA. Axkid Minikid levereras alltid med en svart babydyna, för att ge bättre support för de allra minsta barnen. Axkid Minikid, 0–25 kg, ersätter inte babyskyddet. Vi rekommenderar alltid att börja med babyskyddet eftersom det är bäst anpassat för de allra minsta. När ditt barn växt ur babyskyddet är Axkid Minikid ett bra val för ditt barn att åka bakåtvänt i länge. | O11: CN | P11: 94018000 | Q11: 44 | R11: 62 | S11: 56 | T11: 46 | U11: 58 | V11: 66 | W11: 13.8 | X11: 11.4 | Y11: 30° | Z11: Plus approved up to 25kg , Good Chocie 2015 by Folksam, Best cost Value - Bäst-i-test.se, Rullover approved, REACH tested
A12: Axkid Minikid 2 Tar | B12: 22140216 | C12: Tar | D12: 7350057584354 | E12: 0-25KG | F12: Bilbarnstol ECE R44 | G12: - | I12: 25kg | J12: =$J$1 -> SEK / NOK | K12: =IF(J12="SEK / NOK",(VLOOKUP(B12,'RRP data'!A:E,2,FALSE)),(IF(J12="DKK",(VLOOKUP('Axkid Template - SE'!B12,'RRP data'!A:E,4,FALSE)),(IF(J12="EUR",(VLOOKUP(B12,'RRP data'!A:E,5,FALSE))))))) -> Axkid Minikid 2 Solid Tar | L12: 1 | M12: 1 | O12: CN | P12: 94018000 | Q12: 44 | R12: 62 | S12: 56 | T12: 46 | U12: 58 | V12: 66 | W12: 13.8 | X12: 11.4 | Y12: 30° | Z12: Plus approved up to 25kg , Good Chocie 2015 by Folksam, Best cost Value - Bäst-i-test.se, Rullover approved, REACH tested
A13: Axkid Minikid 2 Granite | B13: 22140217 | C13: Granite | D13: 7350057584361 | E13: 0-25KG | F13: Bilbarnstol ECE R44 | G13: - | I13: 25kg | J13: =$J$1 -> SEK / NOK | K13: =IF(J13="SEK / NOK",(VLOOKUP(B13,'RRP data'!A:E,2,FALSE)),(IF(J13="DKK",(VLOOKUP('Axkid Template - SE'!B21,'RRP data'!A:E,4,FALSE)),(IF(J13="EUR",(VLOOKUP(B13,'RRP data'!A:E,5,FALSE))))))) -> Axkid Minikid 2 Solid Granite | L13: 1 | M13: 1 | O13: CN | P13: 94018000 | Q13: 44 | R13: 62 | S13: 56 | T13: 46 | U13: 58 | V13: 66 | W13: 13.8 | X13: 11.4 | Y13: 30° | Z13: Plus approved up to 25kg , Good Chocie 2015 by Folksam, Best cost Value - Bäst-i-test.se, Rullover approved, REACH tested
A14: Axkid Minikid 2 Shellfish | B14: 22140218 | C14: Shellfish | D14: 7350057584378 | E14: 0-25KG | F14: Bilbarnstol ECE R44 | G14: - | I14: 25kg | J14: =$J$1 -> SEK / NOK | K14: =IF(J14="SEK / NOK",(VLOOKUP(B14,'RRP data'!A:E,2,FALSE)),(IF(J14="DKK",(VLOOKUP('Axkid Template - SE'!B38,'RRP data'!A:E,4,FALSE)),(IF(J14="EUR",(VLOOKUP(B14,'RRP data'!A:E,5,FALSE))))))) -> Axkid Minikid 2 Solid Shellfish | L14: 1 | M14: 1 | O14: CN | P14: 94018000 | Q14: 44 | R14: 62 | S14: 56 | T14: 46 | U14: 58 | V14: 66 | W14: 13.8 | X14: 11.4 | Y14: 30° | Z14: Plus approved up to 25kg , Good Chocie 2015 by Folksam, Best cost Value - Bäst-i-test.se, Rullover approved, REACH tested
A15: Axkid Minikid 2 Sea | B15: 22140219 | C15: Sea | D15: 7350057584385 | E15: 0-25KG | F15: Bilbarnstol ECE R44 | G15: - | I15: 25kg | J15: =$J$1 -> SEK / NOK | K15: =IF(J15="SEK / NOK",(VLOOKUP(B15,'RRP data'!A:E,2,FALSE)),(IF(J15="DKK",(VLOOKUP('Axkid Template - SE'!B39,'RRP data'!A:E,4,FALSE)),(IF(J15="EUR",(VLOOKUP(B15,'RRP data'!A:E,5,FALSE))))))) -> Axkid Minikid 2 Solid Sea | L15: 1 | M15: 1 | O15: CN | P15: 94018000 | Q15: 44 | R15: 62 | S15: 56 | T15: 46 | U15: 58 | V15: 66 | W15: 13.8 | X15: 11.4 | Y15: 30° | Z15: Plus approved up to 25kg , Good Chocie 2015 by Folksam, Best cost Value - Bäst-i-test.se, Rullover approved, REACH tested
A16: Axkid Minikid 2 Moss | B16: 22140220 | C16: Moss | D16: 7350057584392 | E16: 0-25KG | F16: Bilbarnstol ECE R44 | G16: - | I16: 25kg | J16: =$J$1 -> SEK / NOK | K16: =IF(J16="SEK / NOK",(VLOOKUP(B16,'RRP data'!A:E,2,FALSE)),(IF(J16="DKK",(VLOOKUP('Axkid Template - SE'!B40,'RRP data'!A:E,4,FALSE)),(IF(J16="EUR",(VLOOKUP(B16,'RRP data'!A:E,5,FALSE))))))) -> Axkid Minikid 2 Solid Moss | L16: 1 | M16: 1 | O16: CN | P16: 94018000 | Q16: 44 | R16: 62 | S16: 56 | T16: 46 | U16: 58 | V16: 66 | W16: 13.8 | X16: 11.4 | Y16: 30° | Z16: Plus approved up to 25kg , Good Chocie 2015 by Folksam, Best cost Value - Bäst-i-test.se, Rullover approved, REACH tested
A17: Axkid Minikid 2 Shell black | B17: 22140221 | C17: Shell black | D17: 7350057584408 | E17: 0-25KG | F17: Bilbarnstol ECE R44 | G17: - | I17: 25kg | J17: =$J$1 -> SEK / NOK | K17: =IF(J17="SEK / NOK",(VLOOKUP(B17,'RRP data'!A:E,2,FALSE)),(IF(J17="DKK",(VLOOKUP('Axkid Template - SE'!B41,'RRP data'!A:E,4,FALSE)),(IF(J17="EUR",(VLOOKUP(B17,'RRP data'!A:E,5,FALSE))))))) -> Axkid Minikid 2 Premium Shell black | L17: 1 | M17: 1 | O17: CN | P17: 94018000 | Q17: 44 | R17: 62 | S17: 56 | T17: 46 | U17: 58 | V17: 66 | W17: 13.8 | X17: 11.4 | Y17: 30° | Z17: Plus approved up to 25kg , Good Chocie 2015 by Folksam, Best cost Value - Bäst-i-test.se, Rullover approved, REACH tested
A18: Axkid Minikid 2 Granite Melange | B18: 22140222 | C18: Granite Melange | D18: 7350057584415 | E18: 0-25KG | F18: Bilbarnstol ECE R44 | G18: - | I18: 25kg | J18: =$J$1 -> SEK / NOK | K18: =IF(J18="SEK / NOK",(VLOOKUP(B18,'RRP data'!A:E,2,FALSE)),(IF(J18="DKK",(VLOOKUP('Axkid Template - SE'!B42,'RRP data'!A:E,4,FALSE)),(IF(J18="EUR",(VLOOKUP(B18,'RRP data'!A:E,5,FALSE))))))) -> Axkid Minikid 2 Premium Granite Melange | L18: 1 | M18: 1 | O18: CN | P18: 94018000 | Q18: 44 | R18: 62 | S18: 56 | T18: 46 | U18: 58 | V18: 66 | W18: 13.8 | X18: 11.4 | Y18: 30° | Z18: Plus approved up to 25kg , Good Chocie 2015 by Folksam, Best cost Value - Bäst-i-test.se, Rullover approved, REACH tested
A19: Axkid Minikid 2 Sky Grey | B19: 22140223 | C19: Sky Grey | D19: 7350057584422 | E19: 0-25KG | F19: Bilbarnstol ECE R44 | G19: - | I19: 25kg | J19: =$J$1 -> SEK / NOK | K19: =IF(J19="SEK / NOK",(VLOOKUP(B19,'RRP data'!A:E,2,FALSE)),(IF(J19="DKK",(VLOOKUP('Axkid Template - SE'!B43,'RRP data'!A:E,4,FALSE)),(IF(J19="EUR",(VLOOKUP(B19,'RRP data'!A:E,5,FALSE))))))) -> Axkid Minikid 2 Premium Sky Grey | L19: 1 | M19: 1 | O19: CN | P19: 94018000 | Q19: 44 | R19: 62 | S19: 56 | T19: 46 | U19: 58 | V19: 66 | W19: 13.8 | X19: 11.4 | Y19: 30° | Z19: Plus approved up to 25kg , Good Chocie 2015 by Folksam, Best cost Value - Bäst-i-test.se, Rullover approved, REACH tested
A20: Axkid Move Grå | B20: 22120102 | C20: Grå | D20: 7350057582411 | E20: 9-25KG | F20: Bilbarnstol ECE R44 | G20: - | I20: 25kg | J20: =$J$1 -> SEK / NOK | K20: =IF(J20="SEK / NOK",(VLOOKUP(B20,'RRP data'!A:E,2,FALSE)),(IF(J20="DKK",(VLOOKUP('Axkid Template - SE'!B20,'RRP data'!A:E,4,FALSE)),(IF(J20="EUR",(VLOOKUP(B20,'RRP data'!A:E,5,FALSE))))))) -> Axkid Move Grey | L20: 1 | M20: 1 | N20: Den bakåtvända bilbarnstolen Axkid Move är för dig som söker en prisvärd och säker lösning. Du kan låta ditt barn åka bakåtvänt länge, och du installerar den lätt med bilens trepunktsbälte. Axkid Move tar mycket liten plats i bilen, så du kan installera den i både små och stora bilar. Axkid Move levereras med det innovativa sidokrocksskyddet – ASIP (Axkid Side Impact Protection) som är framtaget tillsammans med ett erkänt krockinstitiut i Tyskland, och ger bästa möjliga skydd för barnet vid eventuell krock från sidan. ASIP ska användas på den sidan av bilbarnstolen som är ut mot bildörren, vid användning i mitten behöver inte ASIP användas. Stödbenet på Axkid Move sträcks ut med enbart en knapp på sidan av stödbenet, som enkelt går att komma åt. Lutningen på bilbarnstolen kan du ställa i två olika lägen med hjälp av det främre justerbara stödbenet och nackstödet har tre fasta lägen, allt för att ditt barn ska sitta tryggt och bekvämt. Skulle det behövas ännu mer lutning är vår lutningskil ett bra komplement. Axkid Move är godkänd 9–25 kg och har fått utmärkta omdömen av flera oberoende testinstitut. Den är Plusgodkänd upp till 25 kg, fått utmärkelsen ”Bra Val” av Folksam 2017 och är Rollover-godkänd av VCA. | O20: CN | P20: 94018000 | Q20: 44 | R20: 61 | S20: 56 | T20: 46 | U20: 58 | V20: 66 | W20: 11.6 | X20: 9.8 | Y20: 30° | Z20: Plus approved up to 25kg , Good Chocie 2017 by Folksam, Rullover approved, REACH tested
A21: Axkid Move Svart | B21: 22120103 | C21: Svart | D21: 7350057582183 | E21: 9-25KG | F21: Bilbarnstol ECE R44 | G21: - | I21: 25kg | J21: =$J$1 -> SEK / NOK | K21: =IF(J21="SEK / NOK",(VLOOKUP(B21,'RRP data'!A:E,2,FALSE)),(IF(J21="DKK",(VLOOKUP('Axkid Template - SE'!B21,'RRP data'!A:E,4,FALSE)),(IF(J21="EUR",(VLOOKUP(B21,'RRP data'!A:E,5,FALSE))))))) -> Axkid Move Black | L21: 1 | M21: 1 | N21: Den bakåtvända bilbarnstolen Axkid Move är för dig som söker en prisvärd och säker lösning. Du kan låta ditt barn åka bakåtvänt länge, och du installerar den lätt med bilens trepunktsbälte. Axkid Move tar mycket liten plats i bilen, så du kan installera den i både små och stora bilar. Axkid Move levereras med det innovativa sidokrocksskyddet – ASIP (Axkid Side Impact Protection) som är framtaget tillsammans med ett erkänt krockinstitiut i Tyskland, och ger bästa möjliga skydd för barnet vid eventuell krock från sidan. ASIP ska användas på den sidan av bilbarnstolen som är ut mot bildörren, vid användning i mitten behöver inte ASIP användas. Stödbenet på Axkid Move sträcks ut med enbart en knapp på sidan av stödbenet, som enkelt går att komma åt. Lutningen på bilbarnstolen kan du ställa i två olika lägen med hjälp av det främre justerbara stödbenet och nackstödet har tre fasta lägen, allt för att ditt barn ska sitta tryggt och bekvämt. Skulle det behövas ännu mer lutning är vår lutningskil ett bra komplement. Axkid Move är godkänd 9–25 kg och har fått utmärkta omdömen av flera oberoende testinstitut. Den är Plusgodkänd upp till 25 kg, fått utmärkelsen ”Bra Val” av Folksam 2017 och är Rollover-godkänd av VCA. | O21: CN | P21: 94018000 | Q21: 44 | R21: 61 | S21: 56 | T21: 46 | U21: 58 | V21: 66 | W21: 11.6 | X21: 9.8 | Y21: 30° | Z21: Plus approved up to 25kg , Good Chocie 2017 by Folksam, Rullover approved, REACH tested
A22: Axkid Modukid Infant Solid Tar | B22: 20040016 | C22: Tar
A23: Axkid Modukid Infant Solid Granite | B23: 20040017 | C23: Granite
A24: Axkid Modukid Infant Solid Shellfish | B24: 20040018 | C24: Shellfish
A25: Axkid Modukid Infant Solid Sea | B25: 20040019 | C25: Sea
A26: Axkid Modukid Infant Solid Moss | B26: 20040020 | C26: Moss
A27: Axkid Modukid Infant Premium Shell black | B27: 20040021 | C27: Shell black
A28: Axkid Modukid Infant Premium Granite Melange | B28: 20040022 | C28: Granite Melange
A29: Axkid Modukid Infant Premium Sky Grey | B29: 20040023 | C29: Sky Grey
A30: Axkid Modukid Seat Solid Tar | B30: 24100016 | C30: Tar
A31: Axkid Modukid Seat Solid Granite | B31: 24100017 | C31: Granite
A32: Axkid Modukid Seat Solid Shellfish | B32: 24100018 | C32: Shellfish
A33: Axkid Modukid Seat Solid Sea | B33: 24100019 | C33: Sea
... A37: Axkid Modukid Seat Premium Sky Grey | B37: 24100023 | C37: Sky Grey
A38: Axkid Modukid Infant Röd | B38: 20040001 | C38: Röd | D38: 7350057582466 | E38: I-SIZE | F38: Babyskydd I-SIZE/UN R129 | G38: 0-1 år | I38: 40-75cm (13kg) | J38: =$J$1 -> SEK / NOK | K38: =IF(J38="SEK / NOK",(VLOOKUP(B38,'RRP data'!A:E,2,FALSE)),(IF(J38="DKK",(VLOOKUP('Axkid Template - SE'!B38,'RRP data'!A:E,4,FALSE)),(IF(J38="EUR",(VLOOKUP(B38,'RRP data'!A:E,5,FALSE))))))) -> #N/A | L38: 1 | M38: 1 | N38: Anpassat för nyfödda barn, 40–75 cm och upp till 13 kg. Ett av de lättaste i-Size babyskydden på marknaden. Tack vare den snabba och enkla 2-stegs-installationen får du mer tid till saker som betyder något. Kompatibel med Axkid Life och 90% av alla andra vagnar på marknaden. | O38: CN | P38: 94018000 | Q38: 43 | R38: 54 | S38: 65 | T38: 71 | U38: 44 | V38: 36 | W38: 5.6 | X38: 3.7 | Y38: 30°
A39: Axkid Modukid Infant Grå | B39: 20040002 | C39: Grå | D39: 7350057582473 | E39: I-SIZE | F39: Babyskydd I-SIZE/UN R129 | G39: 0-1 år | I39: 40-75cm (13kg) | J39: =$J$1 -> SEK / NOK | K39: =IF(J39="SEK / NOK",(VLOOKUP(B39,'RRP data'!A:E,2,FALSE)),(IF(J39="DKK",(VLOOKUP('Axkid Template - SE'!B39,'RRP data'!A:E,4,FALSE)),(IF(J39="EUR",(VLOOKUP(B39,'RRP data'!A:E,5,FALSE))))))) -> #N/A | L39: 1 | M39: 1 | N39: Anpassat för nyfödda barn, 40–75 cm och upp till 13 kg. Ett av de lättaste i-Size babyskydden på marknaden. Tack vare den snabba och enkla 2-stegs-installationen får du mer tid till saker som betyder något. Kompatibel med Axkid Life och 90% av alla andra vagnar på marknaden. | O39: CN | P39: 94018000 | Q39: 43 | R39: 54 | S39: 65 | T39: 71 | U39: 44 | V39: 36 | W39: 5.6 | X39: 3.7 | Y39: 30°
A40: Axkid Modukid Infant Svart | B40: 20040003 | C40: Svart | D40: 7350057582480 | E40: I-SIZE | F40: Babyskydd I-SIZE/UN R129 | G40: 0-1 år | I40: 40-75cm (13kg) | J40: =$J$1 -> SEK / NOK | K40: =IF(J40="SEK / NOK",(VLOOKUP(B40,'RRP data'!A:E,2,FALSE)),(IF(J40="DKK",(VLOOKUP('Axkid Template - SE'!B40,'RRP data'!A:E,4,FALSE)),(IF(J40="EUR",(VLOOKUP(B40,'RRP data'!A:E,5,FALSE))))))) -> #N/A | L40: 1 | M40: 1 | N40: Anpassat för nyfödda barn, 40–75 cm och upp till 13 kg. Ett av de lättaste i-Size babyskydden på marknaden. Tack vare den snabba och enkla 2-stegs-installationen får du mer tid till saker som betyder något. Kompatibel med Axkid Life och 90% av alla andra vagnar på marknaden. | O40: CN | P40: 94018000 | Q40: 43 | R40: 54 | S40: 65 | T40: 71 | U40: 44 | V40: 36 | W40: 5.6 | X40: 3.7 | Y40: 30°
A41: Axkid Modukid Infant petrol | B41: 20040011 | C41: Petrol | D41: 7350057582497 | E41: I-SIZE | F41: Babyskydd I-SIZE/UN R129 | G41: 0-1 år | I41: 40-75cm (13kg) | J41: =$J$1 -> SEK / NOK | K41: =IF(J41="SEK / NOK",(VLOOKUP(B41,'RRP data'!A:E,2,FALSE)),(IF(J41="DKK",(VLOOKUP('Axkid Template - SE'!B41,'RRP data'!A:E,4,FALSE)),(IF(J41="EUR",(VLOOKUP(B41,'RRP data'!A:E,5,FALSE))))))) -> #N/A | L41: 1 | M41: 1 | N41: Anpassat för nyfödda barn, 40–75 cm och upp till 13 kg. Ett av de lättaste i-Size babyskydden på marknaden. Tack vare den snabba och enkla 2-stegs-installationen får du mer tid till saker som betyder något. Kompatibel med Axkid Life och 90% av alla andra vagnar på marknaden. | O41: CN | P41: 94018000 | Q41: 43 | R41: 54 | S41: 65 | T41: 71 | U41: 44 | V41: 36 | W41: 5.6 | X41: 3.7 | Y41: 30°
A42: Axkid Modukid Infant Rosa | B42: 20040013 | C42: Rosa | D42: 7350057582510 | E42: I-SIZE | F42: Babyskydd I-SIZE/UN R129 | G42: 0-1 år | I42: 40-75cm (13kg) | J42: =$J$1 -> SEK / NOK | K42: =IF(J42="SEK / NOK",(VLOOKUP(B42,'RRP data'!A:E,2,FALSE)),(IF(J42="DKK",(VLOOKUP('Axkid Template - SE'!B42,'RRP data'!A:E,4,FALSE)),(IF(J42="EUR",(VLOOKUP(B42,'RRP data'!A:E,5,FALSE))))))) -> #N/A | L42: 1 | M42: 1 | N42: Anpassat för nyfödda barn, 40–75 cm och upp till 13 kg. Ett av de lättaste i-Size babyskydden på marknaden. Tack vare den snabba och enkla 2-stegs-installationen får du mer tid till saker som betyder något. Kompatibel med Axkid Life och 90% av alla andra vagnar på marknaden. | O42: CN | P42: 94018000 | Q42: 43 | R42: 54 | S42: 65 | T42: 71 | U42: 44 | V42: 36 | W42: 5.6 | X42: 3.7 | Y42: 30°
A43: Axkid Modukid Base Svart | B43: 21020003 | C43: Svart | D43: 7350057582732 | E43: I-SIZE | F43: Bas till Babyskydd I-SIZE/UN R129 | G43: Se babyskydd eller bilbarnstol | I43: Se babyskydd eller bilbarnstol | J43: =$J$1 -> SEK / NOK | K43: =IF(J43="SEK / NOK",(VLOOKUP(B43,'RRP data'!A:E,2,FALSE)),(IF(J43="DKK",(VLOOKUP('Axkid Template - SE'!B43,'RRP data'!A:E,4,FALSE)),(IF(J43="EUR",(VLOOKUP(B43,'RRP data'!A:E,5,FALSE))))))) -> Axkid Modukid Base | L43: 1 | M43: 1 | N43: Basen är en del av vårt bilstolssystem som består av en bas och två bilbarnstolar. Det går snabb och enkelt att installera basen med både Axkid Modukid Infant och Axkid Modukid Seat. Bilstolssystemet passar i både små och stora bilar och du kan själv välja mellan en kompakt installation eller extra benutrymme för när ditt barn växer. | O43: CN | P43: 94018000 | Q43: 43 | R43: 30 | S43: 65 | T43: 61 | U43: 39 | V43: 23 | W43: 8.8 | X43: 7 | Y43: 30°
A44: Axkid Modukid Röd | B44: 24100001 | C44: Röd | D44: 7350057582671 | E44: I-SIZE | F44: Bilbarnstol I-SIZE/UN R129 | G44: 0-4 år | I44: 61-105cm (18kg) | J44: =$J$1 -> SEK / NOK | K44: =IF(J44="SEK / NOK",(VLOOKUP(B44,'RRP data'!A:E,2,FALSE)),(IF(J44="DKK",(VLOOKUP('Axkid Template - SE'!B44,'RRP data'!A:E,4,FALSE)),(IF(J44="EUR",(VLOOKUP(B44,'RRP data'!A:E,5,FALSE))))))) -> #N/A | L44: 1 | M44: 1 | N44: Anpassat för barn upp till 4 års ålder, 61–105 cm upp till 18 kg. Världens enda i-Size bilstol som anpassas automatiskt efter barnets längd och storlek. Smidig och snabb 2-stegs-installation med ett Sleep-Well-System. Välj mellan en kompakt installation för mer utrymme i bilen eller extra benutrymme, vilket möjliggör att ditt barn kan åka bakåtvänt längre. | O44: CN | P44: 94018000 | Q44: 43 | R44: 62 | S44: 52 | T44: 71 | U44: 47 | V44: 44 | W44: 10.5 | X44: 7.5 | Y44: 30°
A45: Axkid Modukid Grey | B45: 24100002 | C45: Grå | D45: 7350057582688 | E45: I-SIZE | F45: Bilbarnstol I-SIZE/UN R129 | G45: 0-4 år | I45: 61-105cm (18kg) | J45: =$J$1 -> SEK / NOK | K45: =IF(J45="SEK / NOK",(VLOOKUP(B45,'RRP data'!A:E,2,FALSE)),(IF(J45="DKK",(VLOOKUP('Axkid Template - SE'!B45,'RRP data'!A:E,4,FALSE)),(IF(J45="EUR",(VLOOKUP(B45,'RRP data'!A:E,5,FALSE))))))) -> #N/A | L45: 1 | M45: 1 | N45: Anpassat för barn upp till 4 års ålder, 61–105 cm upp till 18 kg. Världens enda i-Size bilstol som anpassas automatiskt efter barnets längd och storlek. Smidig och snabb 2-stegs-installation med ett Sleep-Well-System. Välj mellan en kompakt installation för mer utrymme i bilen eller extra benutrymme, vilket möjliggör att ditt barn kan åka bakåtvänt längre. | O45: CN | P45: 94018000 | Q45: 43 | R45: 62 | S45: 52 | T45: 71 | U45: 47 | V45: 44 | W45: 10.5 | X45: 7.5 | Y45: 30°
A46: Axkid Modukid Svart | B46: 24100003 | C46: Svart | D46: 7350057582695 | E46: I-SIZE | F46: Bilbarnstol I-SIZE/UN R129 | G46: 0-4 år | I46: 61-105cm (18kg) | J46: =$J$1 -> SEK / NOK | K46: =IF(J46="SEK / NOK",(VLOOKUP(B46,'RRP data'!A:E,2,FALSE)),(IF(J46="DKK",(VLOOKUP('Axkid Template - SE'!B46,'RRP data'!A:E,4,FALSE)),(IF(J46="EUR",(VLOOKUP(B46,'RRP data'!A:E,5,FALSE))))))) -> #N/A | L46: 1 | M46: 1 | N46: Anpassat för barn upp till 4 års ålder, 61–105 cm upp till 18 kg. Världens enda i-Size bilstol som anpassas automatiskt efter barnets längd och storlek. Smidig och snabb 2-stegs-installation med ett Sleep-Well-System. Välj mellan en kompakt installation för mer utrymme i bilen eller extra benutrymme, vilket möjliggör att ditt barn kan åka bakåtvänt längre. | O46: CN | P46: 94018000 | Q46: 43 | R46: 62 | S46: 52 | T46: 71 | U46: 47 | V46: 44 | W46: 10.5 | X46: 7.5 | Y46: 30°
A47: Axkid Modukid Petrol | B47: 24100011 | C47: Petrol | D47: 7350057582701 | E47: I-SIZE | F47: Bilbarnstol I-SIZE/UN R129 | G47: 0-4 år | I47: 61-105cm (18kg) | J47: =$J$1 -> SEK / NOK | K47: =IF(J47="SEK / NOK",(VLOOKUP(B47,'RRP data'!A:E,2,FALSE)),(IF(J47="DKK",(VLOOKUP('Axkid Template - SE'!B47,'RRP data'!A:E,4,FALSE)),(IF(J47="EUR",(VLOOKUP(B47,'RRP data'!A:E,5,FALSE))))))) -> #N/A | L47: 1 | M47: 1 | N47: Anpassat för barn upp till 4 års ålder, 61–105 cm upp till 18 kg. Världens enda i-Size bilstol som anpassas automatiskt efter barnets längd och storlek. Smidig och snabb 2-stegs-installation med ett Sleep-Well-System. Välj mellan en kompakt installation för mer utrymme i bilen eller extra benutrymme, vilket möjliggör att ditt barn kan åka bakåtvänt längre. | O47: CN | P47: 94018000 | Q47: 43 | R47: 62 | S47: 52 | T47: 71 | U47: 47 | V47: 44 | W47: 10.5 | X47: 7.5 | Y47: 30°
A48: Axkid Modukid Rosa | B48: 24100013 | C48: Rosa | D48: 7350057582718 | E48: I-SIZE | F48: Bilbarnstol I-SIZE/UN R129 | G48: 0-4 år | I48: 61-105cm (18kg) | J48: =$J$1 -> SEK / NOK | K48: =IF(J48="SEK / NOK",(VLOOKUP(B48,'RRP data'!A:E,2,FALSE)),(IF(J48="DKK",(VLOOKUP('Axkid Template - SE'!B48,'RRP data'!A:E,4,FALSE)),(IF(J48="EUR",(VLOOKUP(B48,'RRP data'!A:E,5,FALSE))))))) -> #N/A | L48: 1 | M48: 1 | N48: Anpassat för barn upp till 4 års ålder, 61–105 cm upp till 18 kg. Världens enda i-Size bilstol som anpassas automatiskt efter barnets längd och storlek. Smidig och snabb 2-stegs-installation med ett Sleep-Well-System. Välj mellan en kompakt installation för mer utrymme i bilen eller extra benutrymme, vilket möjliggör att ditt barn kan åka bakåtvänt längre. | O48: CN | P48: 94018000 | Q48: 43 | R48: 62 | S48: 52 | T48: 71 | U48: 47 | V48: 44 | W48: 10.5 | X48: 7.5 | Y48: 30°
A49: Axkid One Tar | B49: 25110016 | C49: Tar | D49: 7350057584590 | E49: I-SIZE | F49: Car seat I-SIZE/UN R129 | J49: =$J$1 -> SEK / NOK | K49: =IF(J49="SEK / NOK",(VLOOKUP(B49,'RRP data'!A:E,2,FALSE)),(IF(J49="DKK",(VLOOKUP('Axkid Template - SE'!B49,'RRP data'!A:E,4,FALSE)),(IF(J49="EUR",(VLOOKUP(B49,'RRP data'!A:E,5,FALSE))))))) -> Axkid ONE Tar | L49: 1 | M49: 1 | O49: CN | P49: 94018000
A50: Axkid One Granite Melange | B50: 25110021 | C50: Granite Melange | D50: 7350057584606 | E50: I-SIZE | F50: Car seat I-SIZE/UN R129 | J50: =$J$1 -> SEK / NOK | K50: =IF(J50="SEK / NOK",(VLOOKUP(B50,'RRP data'!A:E,2,FALSE)),(IF(J50="DKK",(VLOOKUP('Axkid Template - SE'!B50,'RRP data'!A:E,4,FALSE)),(IF(J50="EUR",(VLOOKUP(B50,'RRP data'!A:E,5,FALSE))))))) -> Axkid ONE Granite Melange | L50: 1 | M50: 1 | O50: CN | P50: 94018000
A51: Axkid One Brick Melange | B51: 25110024 | C51: Brick Melange | D51: 7350057584613 | E51: I-SIZE | F51: Car seat I-SIZE/UN R129 | J51: =$J$1 -> SEK / NOK | K51: =IF(J51="SEK / NOK",(VLOOKUP(B51,'RRP data'!A:E,2,FALSE)),(IF(J51="DKK",(VLOOKUP('Axkid Template - SE'!B51,'RRP data'!A:E,4,FALSE)),(IF(J51="EUR",(VLOOKUP(B51,'RRP data'!A:E,5,FALSE))))))) -> Axkid ONE Brick Melange | L51: 1 | M51: 1 | O51: CN | P51: 94018000
A52: Axkid One Tile Melange | B52: 25110025 | C52: Tile Melange | D52: 7350057584620 | E52: I-SIZE | F52: Car seat I-SIZE/UN R129 | J52: =$J$1 -> SEK / NOK | K52: =IF(J52="SEK / NOK",(VLOOKUP(B52,'RRP data'!A:E,2,FALSE)),(IF(J52="DKK",(VLOOKUP('Axkid Template - SE'!B52,'RRP data'!A:E,4,FALSE)),(IF(J52="EUR",(VLOOKUP(B52,'RRP data'!A:E,5,FALSE))))))) -> Axkid ONE Tile Melange | L52: 1 | M52: 1 | O52: CN | P52: 94018000
A53: Axkid One + Tar | B53: 25120016 | C53: Tar | D53: 7350057584637 | E53: I-SIZE | F53: Car seat I-SIZE/UN R129 | J53: =$J$1 -> SEK / NOK | K53: =IF(J53="SEK / NOK",(VLOOKUP(B53,'RRP data'!A:E,2,FALSE)),(IF(J53="DKK",(VLOOKUP('Axkid Template - SE'!B53,'RRP data'!A:E,4,FALSE)),(IF(J53="EUR",(VLOOKUP(B53,'RRP data'!A:E,5,FALSE))))))) -> Axkid ONE + Tar | L53: 1 | M53: 1 | O53: CN | P53: 94018000
A54: Axkid One + Granite Melange | B54: 25120021 | C54: Granite Melange | D54: 7350057584644 | E54: I-SIZE | F54: Car seat I-SIZE/UN R129 | J54: =$J$1 -> SEK / NOK | K54: =IF(J54="SEK / NOK",(VLOOKUP(B54,'RRP data'!A:E,2,FALSE)),(IF(J54="DKK",(VLOOKUP('Axkid Template - SE'!B54,'RRP data'!A:E,4,FALSE)),(IF(J54="EUR",(VLOOKUP(B54,'RRP data'!A:E,5,FALSE))))))) -> Axkid ONE + Granite Melange | L54: 1 | M54: 1 | O54: CN | P54: 94018000
A55: Axkid One + Brick Melange | B55: 25120024 | C55: Brick Melange | D55: 7350057584651 | E55: I-SIZE | F55: Car seat I-SIZE/UN R129 | J55: =$J$1 -> SEK / NOK | K55: =IF(J55="SEK / NOK",(VLOOKUP(B55,'RRP data'!A:E,2,FALSE)),(IF(J55="DKK",(VLOOKUP('Axkid Template - SE'!B55,'RRP data'!A:E,4,FALSE)),(IF(J55="EUR",(VLOOKUP(B55,'RRP data'!A:E,5,FALSE))))))) -> Axkid ONE + Brick Melange | L55: 1 | M55: 1 | O55: CN | P55: 94018000
A56: Axkid One + Tile Melange | B56: 25120025 | C56: Tile Melange | D56: 7350057584668 | E56: I-SIZE | F56: Car seat I-SIZE/UN R129 | J56: =$J$1 -> SEK / NOK | K56: =IF(J56="SEK / NOK",(VLOOKUP(B56,'RRP data'!A:E,2,FALSE)),(IF(J56="DKK",(VLOOKUP('Axkid Template - SE'!B56,'RRP data'!A:E,4,FALSE)),(IF(J56="EUR",(VLOOKUP(B56,'RRP data'!A:E,5,FALSE))))))) -> Axkid ONE + Tile Melange | L56: 1 | M56: 1 | O56: CN | P56: 94018000
A57: Axkid Rekid Röd | B57: 260301 | C57: Röd | D57: 7350057581841 | E57: 9-18KG | F57: Bilbarnstol ECE R44 | G57: - | I57: 18kg | J57: =$J$1 -> SEK / NOK | K57: =IF(J57="SEK / NOK",(VLOOKUP(B57,'RRP data'!A:E,2,FALSE)),(IF(J57="DKK",(VLOOKUP('Axkid Template - SE'!B57,'RRP data'!A:E,4,FALSE)),(IF(J57="EUR",(VLOOKUP(B57,'RRP data'!A:E,5,FALSE))))))) -> Axkid Rekid Red | L57: 1 | M57: 1 | N57: Bakåtvända bilbarnstolen Axkid Rekid kan installeras med ISOFIX upp till 18 kg, eller bilens trepunktsbälte upp till 25 kg. Precis som för Axkid Minikid är detta en bilbarnstol för dig som vill låta ditt barn resa med maximal säkerhet. Axkid Rekid har många säkerhetsfunktioner som du behöver: ett enkelt justerbart nackstöd med integrerad internsele, som du med ett enkelt handgrepp drar åt så det anpassas till ditt barns längd och storlek. Stolen har dessutom tre lutningslägen för att ditt barn ska sitta så bekvämt som möjligt samt extra långt stödben, vilket möjliggör installation i både små och stora bilar. Axkid Rekid är godkänd enligt ECE R44/04 upp till 25 kg, cirka 125 cm, 6 år och har fått goda omdömen av diverse oberoende testinstitut; Axkid Rekid är Plusgodkänd upp till 18 kg och har fått utmärkelsen ”Bra Val” av Folksam 2015. | O57: CN | P57: 94018000 | Q57: 44 | R57: 62 | S57: 58 | T57: 46 | U57: 58 | V57: 66 | W57: 16.8 | X57: 14.1 | Y57: 30° | Z57: Plus approved up to 18kg , Good pick 2015 by Folksam, REACH tested
A58: Axkid Rekid Grå | B58: 260302 | C58: Grå | D58: 7350057581858 | E58: 9-18KG | F58: Bilbarnstol ECE R44 | G58: - | I58: 18kg | J58: =$J$1 -> SEK / NOK | K58: =IF(J58="SEK / NOK",(VLOOKUP(B58,'RRP data'!A:E,2,FALSE)),(IF(J58="DKK",(VLOOKUP('Axkid Template - SE'!B58,'RRP data'!A:E,4,FALSE)),(IF(J58="EUR",(VLOOKUP(B58,'RRP data'!A:E,5,FALSE))))))) -> Axkid Rekid Grey | L58: 1 | M58: 1 | N58: Bakåtvända bilbarnstolen Axkid Rekid kan installeras med ISOFIX upp till 18 kg, eller bilens trepunktsbälte upp till 25 kg. Precis som för Axkid Minikid är detta en bilbarnstol för dig som vill låta ditt barn resa med maximal säkerhet. Axkid Rekid har många säkerhetsfunktioner som du behöver: ett enkelt justerbart nackstöd med integrerad internsele, som du med ett enkelt handgrepp drar åt så det anpassas till ditt barns längd och storlek. Stolen har dessutom tre lutningslägen för att ditt barn ska sitta så bekvämt som möjligt samt extra långt stödben, vilket möjliggör installation i både små och stora bilar. Axkid Rekid är godkänd enligt ECE R44/04 upp till 25 kg, cirka 125 cm, 6 år och har fått goda omdömen av diverse oberoende testinstitut; Axkid Rekid är Plusgodkänd upp till 18 kg och har fått utmärkelsen ”Bra Val” av Folksam 2015. | O58: CN | P58: 94018000 | Q58: 44 | R58: 62 | S58: 58 | T58: 46 | U58: 58 | V58: 66 | W58: 16.8 | X58: 14.1 | Y58: 30° | Z58: Plus approved up to 18kg , Good pick 2015 by Folksam, REACH tested
A59: Axkid Rekid Svart | B59: 260303 | C59: Svart | D59: 7350057581865 | E59: 9-18KG | F59: Bilbarnstol ECE R44 | G59: - | I59: 18kg | J59: =$J$1 -> SEK / NOK | K59: =IF(J59="SEK / NOK",(VLOOKUP(B59,'RRP data'!A:E,2,FALSE)),(IF(J59="DKK",(VLOOKUP('Axkid Template - SE'!B59,'RRP data'!A:E,4,FALSE)),(IF(J59="EUR",(VLOOKUP(B59,'RRP data'!A:E,5,FALSE))))))) -> Axkid Rekid Black | L59: 1 | M59: 1 | N59: Bakåtvända bilbarnstolen Axkid Rekid kan installeras med ISOFIX upp till 18 kg, eller bilens trepunktsbälte upp till 25 kg. Precis som för Axkid Minikid är detta en bilbarnstol för dig som vill låta ditt barn resa med maximal säkerhet. Axkid Rekid har många säkerhetsfunktioner som du behöver: ett enkelt justerbart nackstöd med integrerad internsele, som du med ett enkelt handgrepp drar åt så det anpassas till ditt barns längd och storlek. Stolen har dessutom tre lutningslägen för att ditt barn ska sitta så bekvämt som möjligt samt extra långt stödben, vilket möjliggör installation i både små och stora bilar. Axkid Rekid är godkänd enligt ECE R44/04 upp till 25 kg, cirka 125 cm, 6 år och har fått goda omdömen av diverse oberoende testinstitut; Axkid Rekid är Plusgodkänd upp till 18 kg och har fått utmärkelsen ”Bra Val” av Folksam 2015. | O59: CN | P59: 94018000 | Q59: 44 | R59: 62 | S59: 58 | T59: 46 | U59: 58 | V59: 66 | W59: 16.8 | X59: 14.1 | Y59: 30° | Z59: Plus approved up to 18kg , Good pick 2015 by Folksam, REACH tested
A60: Axkid Rekid Petrol | B60: 260311 | C60: Petrol | D60: 7350057581872 | E60: 9-18KG | F60: Bilbarnstol ECE R44 | G60: - | I60: 18kg | J60: =$J$1 -> SEK / NOK | K60: =IF(J60="SEK / NOK",(VLOOKUP(B60,'RRP data'!A:E,2,FALSE)),(IF(J60="DKK",(VLOOKUP('Axkid Template - SE'!B60,'RRP data'!A:E,4,FALSE)),(IF(J60="EUR",(VLOOKUP(B60,'RRP data'!A:E,5,FALSE))))))) -> Axkid Rekid Petrol | L60: 1 | M60: 1 | N60: Bakåtvända bilbarnstolen Axkid Rekid kan installeras med ISOFIX upp till 18 kg, eller bilens trepunktsbälte upp till 25 kg. Precis som för Axkid Minikid är detta en bilbarnstol för dig som vill låta ditt barn resa med maximal säkerhet. Axkid Rekid har många säkerhetsfunktioner som du behöver: ett enkelt justerbart nackstöd med integrerad internsele, som du med ett enkelt handgrepp drar åt så det anpassas till ditt barns längd och storlek. Stolen har dessutom tre lutningslägen för att ditt barn ska sitta så bekvämt som möjligt samt extra långt stödben, vilket möjliggör installation i både små och stora bilar. Axkid Rekid är godkänd enligt ECE R44/04 upp till 25 kg, cirka 125 cm, 6 år och har fått goda omdömen av diverse oberoende testinstitut; Axkid Rekid är Plusgodkänd upp till 18 kg och har fått utmärkelsen ”Bra Val” av Folksam 2015. | O60: CN | P60: 94018000 | Q60: 44 | R60: 62 | S60: 58 | T60: 46 | U60: 58 | V60: 66 | W60: 16.8 | X60: 14.1 | Y60: 30° | Z60: Plus approved up to 18kg , Good pick 2015 by Folksam, REACH tested
A61: Axkid Bigkid ISOFIX Grå | B61: 27040002 | C61: Grå | D61: 7350057582794 | E61: 15-36KG | F61: Bältesstol ECE R44 | G61: - | I61: 36kg | J61: =$J$1 -> SEK / NOK | K61: =IF(J61="SEK / NOK",(VLOOKUP(B61,'RRP data'!A:E,2,FALSE)),(IF(J61="DKK",(VLOOKUP('Axkid Template - SE'!B61,'RRP data'!A:E,4,FALSE)),(IF(J61="EUR",(VLOOKUP(B61,'RRP data'!A:E,5,FALSE))))))) -> #N/A | L61: 1 | M61: 1 | N61: Axkid Bigkid är en framåtvänd bilbarnstol godkänd för barn mellan 15 och 36 kg, och som inte längre har möjlighet att åka i en bakåktvänd bilbarnstol. Axkid Bigkid kan installeras med hjälp av bilens trepunktsbälte eller med ISOFIX-armarna vilket garanterar en stabil och säker bilfärd för barnet. | O61: CN | P61: 94018000 | Q61: 48 | R61: 59.5 | S61: 53 | T61: 48 | U61: 47 | V61: 65 | W61: 9.5 | X61: 7.5 | Y61: 30°
A62: Axkid Bigkid ISOFIX Svart | B62: 27040003 | C62: Svart | D62: 7350057582800 | E62: 15-36KG | F62: Bältesstol ECE R44 | G62: - | I62: 36kg | J62: =$J$1 -> SEK / NOK | K62: =IF(J62="SEK / NOK",(VLOOKUP(B62,'RRP data'!A:E,2,FALSE)),(IF(J62="DKK",(VLOOKUP('Axkid Template - SE'!B62,'RRP data'!A:E,4,FALSE)),(IF(J62="EUR",(VLOOKUP(B62,'RRP data'!A:E,5,FALSE))))))) -> #N/A | L62: 1 | M62: 1 | N62: Axkid Bigkid är en framåtvänd bilbarnstol godkänd för barn mellan 15 och 36 kg, och som inte längre har möjlighet att åka i en bakåktvänd bilbarnstol. Axkid Bigkid kan installeras med hjälp av bilens trepunktsbälte eller med ISOFIX-armarna vilket garanterar en stabil och säker bilfärd för barnet. | O62: CN | P62: 94018000 | Q62: 48 | R62: 59.5 | S62: 53 | T62: 48 | U62: 47 | V62: 65 | W62: 9.5 | X62: 7.5 | Y62: 30°
A63: Axkid Bigkid Grå | B63: 26040002 | C63: Grå | D63: 7350057582817 | E63: 15-36KG | F63: Bältesstol ECE R44 | G63: - | I63: 36kg | J63: =$J$1 -> SEK / NOK | K63: =IF(J63="SEK / NOK",(VLOOKUP(B63,'RRP data'!A:E,2,FALSE)),(IF(J63="DKK",(VLOOKUP('Axkid Template - SE'!B63,'RRP data'!A:E,4,FALSE)),(IF(J63="EUR",(VLOOKUP(B63,'RRP data'!A:E,5,FALSE))))))) -> Axkid Bigkid Grey | L63: 1 | M63: 1 | N63: Axkid Bigkid är en framåtvänd bilbarnstol godkänd för barn mellan 15 och 36 kg, och som inte längre har möjlighet att åka i en bakåktvänd bilbarnstol. Axkid Bigkid kan installeras med hjälp av bilens trepunktsbälte vilket garanterar en stabil och säker bilfärd för barnet. | O63: CN | P63: 94018000 | Q63: 48 | R63: 59.5 | S63: 53 | T63: 48 | U63: 47 | V63: 65 | W63: 8.5 | X63: 6.5 | Y63: 30°
A64: Axkid Bigkid Svart | B64: 26040003 | C64: Svart | D64: 7350057582824 | E64: 15-36KG | F64: Bältesstol ECE R44 | G64: - | I64: 36kg | J64: =$J$1 -> SEK / NOK | K64: =IF(J64="SEK / NOK",(VLOOKUP(B64,'RRP data'!A:E,2,FALSE)),(IF(J64="DKK",(VLOOKUP('Axkid Template - SE'!B64,'RRP data'!A:E,4,FALSE)),(IF(J64="EUR",(VLOOKUP(B64,'RRP data'!A:E,5,FALSE))))))) -> Axkid Bigkid Black | L64: 1 | M64: 1 | N64: Axkid Bigkid är en framåtvänd bilbarnstol godkänd för barn mellan 15 och 36 kg, och som inte längre har möjlighet att åka i en bakåktvänd bilbarnstol. Axkid Bigkid kan installeras med hjälp av bilens trepunktsbälte vilket garanterar en stabil och säker bilfärd för barnet. | O64: CN | P64: 94018000 | Q64: 48 | R64: 59.5 | S64: 53 | T64: 48 | U64: 47 | V64: 65 | W64: 8.5 | X64: 6.5 | Y64: 30°
A65: Axkid Dallas Svart | B65: 240303 | C65: Svart | D65: 7350057580493 | E65: 15-36KG | F65: Bältesstol ECE R44 | G65: - | I65: 36kg | J65: =$J$1 -> SEK / NOK | K65: =IF(J65="SEK / NOK",(VLOOKUP(B65,'RRP data'!A:E,2,FALSE)),(IF(J65="DKK",(VLOOKUP('Axkid Template - SE'!B65,'RRP data'!A:E,4,FALSE)),(IF(J65="EUR",(VLOOKUP(B65,'RRP data'!A:E,5,FALSE))))))) -> Axkid Dallas Black | L65: 2 | M65: 1 | N65: När barnen börjar bli stora och den bakåtvända bilbarnstolen inte längre räcker till, hur mycket vi än vill, är det dags för en framåtvänd bältesstol. Axkid Dallas är en framåtvänd bältesstol som ser till att äldre barn mellan 15 och 36 kg sitter säkert och stabilt i bilen. Nackstödet kan justeras för att anpassa barnets längd. Sittdynan och ryggen har extra tjock fyllning för att ge barnet optimal komfort och åkupplevelse. Tack vare den smidiga designen så tar sig barnet lätt i och ur bältesstolen själv. | O65: CN | P65: 94018000 | Q65: 44 | R65: 69 | S65: 40 | T65: 61 | U65: 46.5 | V65: 67.5 | W65: 8.5 | X65: 3.5 | Y65: 30°
A66: Axkid Mate Svart | B66: 280303 | C66: Svart | D66: 7350057582299 | E66: 15-36KG | F66: Bältesstol ECE R44 | G66: - | I66: 36kg | J66: =$J$1 -> SEK / NOK | K66: =IF(J66="SEK / NOK",(VLOOKUP(B66,'RRP data'!A:E,2,FALSE)),(IF(J66="DKK",(VLOOKUP('Axkid Template - SE'!B66,'RRP data'!A:E,4,FALSE)),(IF(J66="EUR",(VLOOKUP(B66,'RRP data'!A:E,5,FALSE))))))) -> #N/A | L66: 8 | M66: 1 | N66: När barnen börjar bli stora och bältesstolen inte längre räcker till, är det dags för den avslutande bälteskudden. Axkid Grow Pillow är en enkel och flexibel lösning för ditt lite större barn. Du flyttar den lätt och smidigt, hemma eller med på resan. Bälteskudden gör att bilens trepunktsbälte får rätt placering på ditt barns kropp vilket är avgörande för säkerheten. Bälteskudden Axkid Grow Pillow är godkänd 15-36 kg enligt ECE R44/04. | O66: CN | P66: 94018000 | Q66: 42 | R66: 17 | S66: 36 | T66: 43.5 | U66: 38 | V66: 72 | W66: 9.2 | X66: 1 | Y66: 30°
A67: Axkid Mate Röd | B67: 280201 | C67: Röd | D67: 7350057582305 | E67: 15-36KG | F67: Bältesstol ECE R44 | G67: - | I67: 36kg | J67: =$J$1 -> SEK / NOK | K67: =IF(J67="SEK / NOK",(VLOOKUP(B67,'RRP data'!A:E,2,FALSE)),(IF(J67="DKK",(VLOOKUP('Axkid Template - SE'!B67,'RRP data'!A:E,4,FALSE)),(IF(J67="EUR",(VLOOKUP(B67,'RRP data'!A:E,5,FALSE))))))) -> #N/A | L67: 8 | M67: 1 | N67: När barnen börjar bli stora och bältesstolen inte längre räcker till, är det dags för den avslutande bälteskudden. Axkid Grow Pillow är en enkel och flexibel lösning för ditt lite större barn. Du flyttar den lätt och smidigt, hemma eller med på resan. Bälteskudden gör att bilens trepunktsbälte får rätt placering på ditt barns kropp vilket är avgörande för säkerheten. Bälteskudden Axkid Grow Pillow är godkänd 15-36 kg enligt ECE R44/04. | O67: CN | P67: 94018000 | Q67: 42 | R67: 17 | S67: 36 | T67: 43.5 | U67: 38 | V67: 72 | W67: 9.2 | X67: 1 | Y67: 30°
A68: Axkid Sparkskydd | B68: 800003 | C68: Svart | D68: 7350057580172 | E68: TILLBEHÖR TILL BILBARNSTOL | F68: - | G68: - | I68: - | J68: =$J$1 -> SEK / NOK | K68: =IF(J68="SEK / NOK",(VLOOKUP(B68,'RRP data'!A:E,2,FALSE)),(IF(J68="DKK",(VLOOKUP('Axkid Template - SE'!B68,'RRP data'!A:E,4,FALSE)),(IF(J68="EUR",(VLOOKUP(B68,'RRP data'!A:E,5,FALSE))))))) -> Axkid Seat protection | L68: 20 | M68: 1 | N68: Axkids sparkskydd är till för att skydda bilens klädsel mot slitage och smuts. Tack vare vår unika design passar Axkids sparkskydd både till stolar med och utan ISOFIX. Sparkskyddet kan monteras både i fram- och i baksäte. På sparkskyddet finns två fack för att förvara saker i. | O68: CN | P68: 94019010 | Q68: 139 | R68: 58 | S68: 1 | T68: 23.5 | U68: 7 | V68: 37 | W68: 0.65 | X68: 0.44 | Y68: Ej tvättbar
A69: Axkid Förankringsband | B69: 800203 | C69: Svart | D69: 7350057580189 | E69: TILLBEHÖR TILL BILBARNSTOL | F69: - | G69: - | I69: - | J69: =$J$1 -> SEK / NOK | K69: =IF(J69="SEK / NOK",(VLOOKUP(B69,'RRP data'!A:E,2,FALSE)),(IF(J69="DKK",(VLOOKUP('Axkid Template - SE'!B69,'RRP data'!A:E,4,FALSE)),(IF(J69="EUR",(VLOOKUP(B69,'RRP data'!A:E,5,FALSE))))))) -> Axkid Tether strap | L69: 70 | M69: 1 | N69: Förlängningsband för bakåtvänd montering där fästöglor saknas eller där extra längd behövs. Levereras två stycken i varje förpackning. | O69: CN | P69: 94019010 | Q69: 4 | R69: 110 | S69: 0.2 | T69: 13 | U69: 5 | V69: 9 | W69: 0.18 | X69: 0.14 | Y69: Ej tvättbar
A70: Axkid Baby on board skylt | B70: 800507 | C70: Gul | D70: 7350057580219 | E70: TILLBEHÖR TILL BILBARNSTOL | F70: - | G70: - | I70: - | J70: =$J$1 -> SEK / NOK | K70: =IF(J70="SEK / NOK",(VLOOKUP(B70,'RRP data'!A:E,2,FALSE)),(IF(J70="DKK",(VLOOKUP('Axkid Template - SE'!B70,'RRP data'!A:E,4,FALSE)),(IF(J70="EUR",(VLOOKUP(B70,'RRP data'!A:E,5,FALSE))))))) -> Axkid Baby on board sign | L70: 100 | M70: 1 | N70: Med denna skylt visar du dina medtrafikanter att du har barn i bilen. Skylten monterar du enkelt med sugpropp på insidan av bakrutan. | O70: CN | P70: 94019010 | Q70: 12 | R70: 12 | S70: 0.2 | T70: 14 | U70: 5 | V70: 0.5 | W70: 0.024 | X70: 0.017 | Y70: Ej tvättbar
A71: Axkid Förankringsöglor | B71: 800608 | C71: Svart | D71: 7350057580226 | E71: TILLBEHÖR TILL BILBARNSTOL | F71: - | G71: - | I71: - | J71: =$J$1 -> SEK / NOK | K71: =IF(J71="SEK / NOK",(VLOOKUP(B71,'RRP data'!A:E,2,FALSE)),(IF(J71="DKK",(VLOOKUP('Axkid Template - SE'!B71,'RRP data'!A:E,4,FALSE)),(IF(J71="EUR",(VLOOKUP(B71,'RRP data'!A:E,5,FALSE))))))) -> Axkid Attachment loops | L71: 100 | M71: 1 | N71: Axkids förankringsöglor är framtagna för att underlätta monteringen av bilbarnstolen i din bil. Levereras två stycken i varje förpackning. | O71: CN | P71: 94019010 | T71: 14 | U71: 5 | V71: 0.5 | W71: 0.087 | X71: 0.08 | Y71: Ej tvättbar
A72: Axkid Babydyna | B72: 800803 | C72: Svart | D72: 7350057580233 | E72: TILLBEHÖR TILL BILBARNSTOL | F72: - | G72: - | I72: - | J72: =$J$1 -> SEK / NOK | K72: =IF(J72="SEK / NOK",(VLOOKUP(B72,'RRP data'!A:E,2,FALSE)),(IF(J72="DKK",(VLOOKUP('Axkid Template - SE'!B72,'RRP data'!A:E,4,FALSE)),(IF(J72="EUR",(VLOOKUP(B72,'RRP data'!A:E,5,FALSE))))))) -> Axkid Baby cushion | L72: 40 | M72: 1 | N72: Mjuk dyna som ger de mindre barnen bättre stöd. Dynan lyfter upp barnet så att bältesbanan förbättras och gör att ditt barn sitter bättre och stadigare. Kompatibel med alla bakåtvända bilbarnstolar från Axkid. | O72: CN | P72: 94019010 | Q72: 47.5 | R72: 38 | S72: 1 | T72: 23.5 | U72: 7 | V72: 37 | W72: 0.355 | X72: 0.145 | Y72: Ej tvättbar
A73: Axkid Adapter babyfix | B73: 801003 | C73: Svart | D73: 7350057580509 | E73: TILLBEHÖR TILL BILBARNSTOL | F73: - | G73: - | I73: - | J73: =$J$1 -> SEK / NOK | K73: =IF(J73="SEK / NOK",(VLOOKUP(B73,'RRP data'!A:E,2,FALSE)),(IF(J73="DKK",(VLOOKUP('Axkid Template - SE'!B73,'RRP data'!A:E,4,FALSE)),(IF(J73="EUR",(VLOOKUP(B73,'RRP data'!A:E,5,FALSE))))))) -> Axkid Adapter babyfix | L73: 100 | M73: 1 | N73: Adapter för Axkid Babyfix som ger dig möjligheten att montera babyskyddet på alla vagnar som är anpassade för Maxi-Cosi. Perfekt lösning vid kortare turer eller när du helt enkelt inte vill väcka ditt sovande barn. Adapter Babyfix levereras två stycken i varje förpackning. | O73: CN | P73: 94019010 | Q73: 10 | R73: 5 | S73: 7 | T73: 18 | U73: 6 | V73: 16 | W73: 0.12 | X73: 0.035 | Y73: Ej tvättbar
A74: Axkid Sommarklädsel Minikid, rekid & Modukid | B74: 801106 | C74: Vit | D74: 7350057580714 | E74: TILLBEHÖR TILL BILBARNSTOL | F74: - | G74: - | I74: - | J74: =$J$1 -> SEK / NOK | K74: =IF(J74="SEK / NOK",(VLOOKUP(B74,'RRP data'!A:E,2,FALSE)),(IF(J74="DKK",(VLOOKUP('Axkid Template - SE'!B74,'RRP data'!A:E,4,FALSE)),(IF(J74="EUR",(VLOOKUP(B74,'RRP data'!A:E,5,FALSE))))))) -> Axkid Summer cover Minikid, rekid & Modukid seat | L74: 20 | M74: 1 | N74: Klädsel för att slippa att bilbarnstolen blir för varm på sommaren. Kompatibelt med alla bakåtvända bilbarnstolar från Axkid. | O74: CN | P74: 94019010 | Q74: 85 | R74: 45 | S74: 0.2 | T74: 30 | U74: 30 | V74: 0.5 | W74: 0.103 | X74: 0.1 | Y74: Ej tvättbar
A75: Axkid Sommarklädsel Dallas/Grow | B75: 801206 | C75: Vit | D75: 7350057580721 | E75: TILLBEHÖR TILL BILBARNSTOL | F75: - | G75: - | I75: - | J75: =$J$1 -> SEK / NOK | K75: =IF(J75="SEK / NOK",(VLOOKUP(B75,'RRP data'!A:E,2,FALSE)),(IF(J75="DKK",(VLOOKUP('Axkid Template - SE'!B75,'RRP data'!A:E,4,FALSE)),(IF(J75="EUR",(VLOOKUP(B75,'RRP data'!A:E,5,FALSE))))))) -> Axkid Summer cover Dallas/Grow | L75: 20 | M75: 1 | N75: Klädsel för att slippa att stolen blir för varm på sommaren. Kompatibelt med alla framåtvända bältesstolar från Axkid. | O75: CN | P75: 94019010 | Q75: 85 | R75: 45 | S75: 0.2 | T75: 30 | U75: 30 | V75: 0.5 | W75: 0.23 | X75: 0.052 | Y75: Ej tvättbar
A76: Axkid Lutningskil | B76: 801403 | C76: Svart | D76: 7350057581087 | E76: TILLBEHÖR TILL BILBARNSTOL | F76: - | G76: - | I76: - | J76: =$J$1 -> SEK / NOK | K76: =IF(J76="SEK / NOK",(VLOOKUP(B76,'RRP data'!A:E,2,FALSE)),(IF(J76="DKK",(VLOOKUP('Axkid Template - SE'!B76,'RRP data'!A:E,4,FALSE)),(IF(J76="EUR",(VLOOKUP(B76,'RRP data'!A:E,5,FALSE))))))) -> Axkid Angle adjusting wedge | L76: 40 | M76: 1 | N76: Lutningskil som hjälper till att fylla ut tomrummet mellan bilbarnstolen och bilens säte för att ge bättre lutning på bilbarnstolen. Observera att bilbarnstolen inte bör luta mer än 32 grader. Kompatibel med alla bakåtvända bilbarnstolar från Axkid. | O76: CN | P76: 94019010 | Q76: 16.5 | R76: 23 | S76: 7.5 | T76: 30 | U76: 8 | V76: 20 | W76: 0.44 | X76: 0.263 | Y76: Ej tvättbar
A77: Axkid Baby spegel | B77: 803303 | C77: Svart | D77: 7350057581339 | E77: TILLBEHÖR TILL BILBARNSTOL | F77: - | G77: - | I77: - | J77: =$J$1 -> SEK / NOK | K77: =IF(J77="SEK / NOK",(VLOOKUP(B77,'RRP data'!A:E,2,FALSE)),(IF(J77="DKK",(VLOOKUP('Axkid Template - SE'!B77,'RRP data'!A:E,4,FALSE)),(IF(J77="EUR",(VLOOKUP(B77,'RRP data'!A:E,5,FALSE))))))) -> Axkid Baby mirror | L77: 10 | M77: 1 | N77: Spegel som gör att du som förälder kan se ditt barn sittandes i sin bakåtvända bilbarnstol, under pågående färd. Monteras i baksätet på bilsätets nackstöd. | O77: CN | P77: 94019010 | Q77: 21.5 | R77: 17.5 | T77: 30 | U77: 8 | V77: 20 | W77: 1.05 | X77: 0.71 | Y77: Ej tvättbar
A78: Axkid Sparkskydd Premium | B78: 803803 | C78: Svart | D78: 7350057582008 | E78: TILLBEHÖR TILL BILBARNSTOL | F78: - | G78: - | I78: - | J78: =$J$1 -> SEK / NOK | K78: =IF(J78="SEK / NOK",(VLOOKUP(B78,'RRP data'!A:E,2,FALSE)),(IF(J78="DKK",(VLOOKUP('Axkid Template - SE'!B78,'RRP data'!A:E,4,FALSE)),(IF(J78="EUR",(VLOOKUP(B78,'RRP data'!A:E,5,FALSE))))))) -> Axkid Seat protection Premium | L78: 10 | M78: 1 | N78: Ett tjockare, mer vadderat sparkskydd för att skydda sätena mot smuts och slitage. Med två förvaringsfack och hållare för iPad eller annan surfplatta. Fungerar både för bilbarnstolar med eller utan ISOFIX. Kan användas i både fram- och baksäte. Kompatibelt med alla bakåtvända bilbarnstolar från Axkid. | O78: CN | P78: 94019010 | Q78: 122 | R78: 47 | S78: 1 | T78: 28.5 | U78: 8 | V78: 58 | W78: 0.2 | X78: 0.12 | Y78: Ej tvättbar
A79: Axkid Solskydd Fönster 2-pack | B79: 803906 | C79: Vit | D79: 7350057582015 | E79: TILLBEHÖR TILL BILBARNSTOL | F79: - | G79: - | I79: - | J79: =$J$1 -> SEK / NOK | K79: =IF(J79="SEK / NOK",(VLOOKUP(B79,'RRP data'!A:E,2,FALSE)),(IF(J79="DKK",(VLOOKUP('Axkid Template - SE'!B79,'RRP data'!A:E,4,FALSE)),(IF(J79="EUR",(VLOOKUP(B79,'RRP data'!A:E,5,FALSE))))))) -> Axkid Sunshades for window self attaching | L79: 48 | M79: 1 | N79: Axkids solskydd för fönster passar perfekt för att skugga ditt barn under bilfärden när solen lyser. De är självhäftande solskydd, med Axkid logga, som fästs på insidan av sidorutan. Levereras två stycken i varje förpackning. Hopfällbar. | O79: CN | P79: 94019010 | Q79: 38 | R79: 44 | S79: 0.2 | T79: 18 | U79: 6 | V79: 16 | W79: 0.33 | X79: 0.16 | Y79: Ej tvättbar
A80: Axkid iPad-hållare | B80: 804003 | C80: Svart | D80: 7350057582022 | E80: TILLBEHÖR TILL BILBARNSTOL | F80: - | G80: - | I80: - | J80: =$J$1 -> SEK / NOK | K80: =IF(J80="SEK / NOK",(VLOOKUP(B80,'RRP data'!A:E,2,FALSE)),(IF(J80="DKK",(VLOOKUP('Axkid Template - SE'!B80,'RRP data'!A:E,4,FALSE)),(IF(J80="EUR",(VLOOKUP(B80,'RRP data'!A:E,5,FALSE))))))) -> Axkid iPad holder | L80: 20 | M80: 1 | N80: Hållare för iPad eller annan surfplatta. Monteras på baksidan av nackstödet på förar- eller passagerarsätet. | O80: CN | P80: 94019010 | Q80: 27.5 | R80: 19.5 | S80: 2 | T80: 30 | U80: 8 | V80: 20 | W80: 0.45 | X80: 0.24 | Y80: Ej tvättbar
A81: Axkid Sparkskydd framåtvänt | B81: 804103 | C81: Svart | D81: 7350057582039 | E81: TILLBEHÖR TILL BILBARNSTOL | F81: - | G81: - | I81: - | J81: =$J$1 -> SEK / NOK | K81: =IF(J81="SEK / NOK",(VLOOKUP(B81,'RRP data'!A:E,2,FALSE)),(IF(J81="DKK",(VLOOKUP('Axkid Template - SE'!B81,'RRP data'!A:E,4,FALSE)),(IF(J81="EUR",(VLOOKUP(B81,'RRP data'!A:E,5,FALSE))))))) -> Axkid Backseat organizer | L81: 20 | M81: 1 | N81: Sparkskydd för framåtvända bältesstolar med flera smarta förvaringsfack och hållare för iPad eller annan surfplatta. Monteras på baksidan av förar- eller passagerarsätet. | O81: CN | P81: 94019010 | Q81: 42.5 | R81: 57 | S81: 1 | T81: 23.5 | U81: 7 | V81: 37 | W81: 0.16 | X81: 0.16 | Y81: Ej tvättbar
A82: Axkid Förankringsband för Move/Wolmax | B82: 804303 | C82: Svart | D82: 7350057582060 | E82: TILLBEHÖR TILL BILBARNSTOL | F82: - | G82: - | I82: - | J82: =$J$1 -> SEK / NOK | K82: =IF(J82="SEK / NOK",(VLOOKUP(B82,'RRP data'!A:E,2,FALSE)),(IF(J82="DKK",(VLOOKUP('Axkid Template - SE'!B82,'RRP data'!A:E,4,FALSE)),(IF(J82="EUR",(VLOOKUP(B82,'RRP data'!A:E,5,FALSE))))))) -> Axkid Tether straps for Move | L82: 100 | M82: 1 | N82: Förankringsband för Axkid Move. Levereras två stycken i varje förpackning. | O82: CN | P82: 94019010 | Q82: 4 | R82: 133 | S82: 0.2 | T82: 18 | U82: 6 | V82: 16 | W82: 0.15 | X82: 0.14 | Y82: Ej tvättbar
A83: Axkid Solskydd | B83: 804503 | C83: Svart | D83: 7350057582749 | E83: TILLBEHÖR TILL BILBARNSTOL | F83: - | G83: - | I83: - | J83: =$J$1 -> SEK / NOK | K83: =IF(J83="SEK / NOK",(VLOOKUP(B83,'RRP data'!A:E,2,FALSE)),(IF(J83="DKK",(VLOOKUP('Axkid Template - SE'!B83,'RRP data'!A:E,4,FALSE)),(IF(J83="EUR",(VLOOKUP(B83,'RRP data'!A:E,5,FALSE))))))) -> Axkid Sun cover (seat sunshade) | L83: 40 | M83: 1 | N83: Solskyddet är skapat och utformat för att skugga ditt barn under färd och minska uppvärmning av stolen, då bilen står i solen. Kompatibelt med alla bakåtvända bilbarnstolar från Axkid. | O83: CN | P83: 94019010 | Q83: 41 | R83: 21 | S83: 47 | T83: 30 | U83: 8 | V83: 20 | W83: 0.61 | X83: 0.3 | Y83: Ej tvättbar
A84: Axkid Stödbensadapter | B84: 804603 | C84: Svart | D84: 7350057582756 | E84: TILLBEHÖR TILL BILBARNSTOL | F84: - | G84: - | I84: - | J84: =$J$1 -> SEK / NOK | K84: =IF(J84="SEK / NOK",(VLOOKUP(B84,'RRP data'!A:E,2,FALSE)),(IF(J84="DKK",(VLOOKUP('Axkid Template - SE'!B84,'RRP data'!A:E,4,FALSE)),(IF(J84="EUR",(VLOOKUP(B84,'RRP data'!A:E,5,FALSE))))))) -> Axkid Support leg adapter | L84: 10 | M84: 1 | N84: Denna förlängningsadapter förlänger Axkid Minikid och Moves stödben om du har en stor bil eller van, och om stödbenet inte når ner golvet i fordonet. | O84: CN | P84: 94019010 | Q84: 8 | R84: 27.5 | S84: 3.5 | T84: 30 | U84: 8 | V84: 20 | W84: 0.8 | X84: 0.5 | Y84: Ej tvättbar
A85: Axkid Connect | B85: 804916 | C85: Tar | D85: 7350057584347 | E85: TILLBEHÖR TILL BILBARNSTOL | F85: - | G85: - | I85: - | J85: EUR | L85: 1 | M85: 1 | O85: CN | P85: 94019010
A86: Axkid Life Grå | B86: 30100002 | C86: Grå | D86: 7350057582428 | E86: VAGN 4 HJUL | F86: EN 1888 | G86: - | I86: 22kg | J86: =$J$1 -> SEK / NOK | K86: =IF(J86="SEK / NOK",(VLOOKUP(B86,'RRP data'!A:E,2,FALSE)),(IF(J86="DKK",(VLOOKUP('Axkid Template - SE'!B86,'RRP data'!A:E,4,FALSE)),(IF(J86="EUR",(VLOOKUP(B86,'RRP data'!A:E,5,FALSE))))))) -> #N/A | L86: 1 | M86: 1 | N86: Axkid Life tar mobilitet till en ny nivå. Lätt att använda och lätt att fälla ihop. Du kan till och med ta med den som handbagage när du flyger. Trygg och säker, lätt och smidig för dig och ditt barn. En barnvagn för dig som vill fortsätta att resa och upptäcka världen med ditt barn. Axkid Life blir liten och smidig hopfälld, enbart 56 x 45 x 25 cm, vilket uppfyller kravet för handbagage hos en del flygbolag*. Väger endast 6,5 kg och är utrustad med axelrem för att enkelt kunna bära. Axkid Life levereras alltid med en svart reseväska med handtag samt en bygel som enkelt går att klicka av och på. Steglösa rygglägen, som även går att fälla till fullt liggläge (vagnen är utrustad med huvudskydd som skyddar barnet vid fullt liggläge) och en 5-punktssele gör resan för barnet både säker och komfortabel. Bra fjädring på alla 4 hjul som är punkteringsfria och utrustade med en fotbroms som enkelt manövreras och som låser båda bakhjul. Sulkyn kommer i svart och grått, och klädseln går att ta av för att rengöra och kan tvättas i 30° maskintvätt eller torkas av med vatten och såpa. Handtagsbågen samt bygeln är trendig och modern i svart läderette material. Köp till Axkid Life liggdel och vagnen kan användas även för de allra minsta, från 0–6 månader, för att maximera användningen. Liggdelen finns i svart och grått och är smidig att ta av och på sulkyn. Andra tillbehör som är kompatibla med Axkid Life är regnskydd, myggnät, adapter för babyskydd samt skötväska. Möjlighet att använda babyskyddet direkt på sulkyn finns med tillbehöret Axkid Life adapter, som är kompatibla med babyskydd som har Maxi-Cosi infästning. *Måtten för Axkid Life kontrolleras mot det flygbolag du ska resa med, för att se om de accepterar Axkid Life som handbagage. Här finns de flesta flygbolagens övergripande policy gällande kabinbagage. Rekommenderad maxstorlek för kabinbagage från IATA (International Air Transport Association) är 56 x 45 x 25 cm. | O86: CN | P86: 8715001000 | Q86: 45 | R86: 100 | S86: 85 | T86: 51 | U86: 59.5 | V86: 29 | W86: 9.5 | X86: 7.3 | Y86: 30°
A87: Axkid Life Svart | B87: 30100003 | C87: Svart | D87: 7350057582435 | E87: VAGN 4 HJUL | F87: EN 1888 | G87: - | I87: 22kg | J87: =$J$1 -> SEK / NOK | K87: =IF(J87="SEK / NOK",(VLOOKUP(B87,'RRP data'!A:E,2,FALSE)),(IF(J87="DKK",(VLOOKUP('Axkid Template - SE'!B87,'RRP data'!A:E,4,FALSE)),(IF(J87="EUR",(VLOOKUP(B87,'RRP data'!A:E,5,FALSE))))))) -> #N/A | L87: 1 | M87: 1 | N87: Axkid Life tar mobilitet till en ny nivå. Lätt att använda och lätt att fälla ihop. Du kan till och med ta med den som handbagage när du flyger. Trygg och säker, lätt och smidig för dig och ditt barn. En barnvagn för dig som vill fortsätta att resa och upptäcka världen med ditt barn. Axkid Life blir liten och smidig hopfälld, enbart 56 x 45 x 25 cm, vilket uppfyller kravet för handbagage hos en del flygbolag*. Väger endast 6,5 kg och är utrustad med axelrem för att enkelt kunna bära. Axkid Life levereras alltid med en svart reseväska med handtag samt en bygel som enkelt går att klicka av och på. Steglösa rygglägen, som även går att fälla till fullt liggläge (vagnen är utrustad med huvudskydd som skyddar barnet vid fullt liggläge) och en 5-punktssele gör resan för barnet både säker och komfortabel. Bra fjädring på alla 4 hjul som är punkteringsfria och utrustade med en fotbroms som enkelt manövreras och som låser båda bakhjul. Sulkyn kommer i svart och grått, och klädseln går att ta av för att rengöra och kan tvättas i 30° maskintvätt eller torkas av med vatten och såpa. Handtagsbågen samt bygeln är trendig och modern i svart läderette material. Köp till Axkid Life liggdel och vagnen kan användas även för de allra minsta, från 0–6 månader, för att maximera användningen. Liggdelen finns i svart och grått och är smidig att ta av och på sulkyn. Andra tillbehör som är kompatibla med Axkid Life är regnskydd, myggnät, adapter för babyskydd samt skötväska. Möjlighet att använda babyskyddet direkt på sulkyn finns med tillbehöret Axkid Life adapter, som är kompatibla med babyskydd som har Maxi-Cosi infästning. *Måtten för Axkid Life kontrolleras mot det flygbolag du ska resa med, för att se om de accepterar Axkid Life som handbagage. Här finns de flesta flygbolagens övergripande policy gällande kabinbagage. Rekommenderad maxstorlek för kabinbagage från IATA (International Air Transport Association) är 56 x 45 x 25 cm. | O87: CN | P87: 8715001000 | Q87: 45 | R87: 100 | S87: 85 | T87: 51 | U87: 59.5 | V87: 29 | W87: 9.5 | X87: 7.3 | Y87: 30°
A88: Axkid Life liggdel Grå | B88: 90100102 | C88: Grå | D88: 7350057582442 | E88: LIGGDEL TILL VAGN | F88: EN 1888 | G88: 0-6mån | I88: - | J88: =$J$1 -> SEK / NOK | K88: =IF(J88="SEK / NOK",(VLOOKUP(B88,'RRP data'!A:E,2,FALSE)),(IF(J88="DKK",(VLOOKUP('Axkid Template - SE'!B88,'RRP data'!A:E,4,FALSE)),(IF(J88="EUR",(VLOOKUP(B88,'RRP data'!A:E,5,FALSE))))))) -> #N/A | L88: 1 | M88: 1 | N88: Axkid Life liggdel kommer i två färger, svart och grått, och gör det möjligt att använda Axkid Life även från nyfödd upp till ca 6 månader. Stor och rymlig liggdel med ett innermått på 76 cm inklusive justerbar sufflett, löstagbart liggdelslock, madrass samt praktiska bärhandtag. Inuti liggdelen finns det fästen för sele (sele ingår ej) och liggdelen har kuddar i plast undertill för att liggdelen ska kunna ställas ner på marken, oavsett väder och vind. Hela klädseln är avtagbar och kan tvättas i 30° maskintvätt. Hårdlift Rymligt innermått Vikt: 3kg Yttermått: L: 85cm, B: 35cm, H (sufflett uppfälld): 50cm, H (sufflett hopfälld): 25cm Innermått: L: 75cm, B: 30cm, H: 20cm | O88: CN | P88: 8715009000 | Q88: 35 | R88: 85 | S88: 25 | T88: 37 | U88: 86 | V88: 10.5 | W88: 4.3 | X88: 2.8 | Y88: 30°
A89: Axkid Life liggdel Svart | B89: 90100103 | C89: Svart | D89: 7350057582459 | E89: LIGGDEL TILL VAGN | F89: EN 1888 | G89: 0-6mån | I89: - | J89: =$J$1 -> SEK / NOK | K89: =IF(J89="SEK / NOK",(VLOOKUP(B89,'RRP data'!A:E,2,FALSE)),(IF(J89="DKK",(VLOOKUP('Axkid Template - SE'!B89,'RRP data'!A:E,4,FALSE)),(IF(J89="EUR",(VLOOKUP(B89,'RRP data'!A:E,5,FALSE))))))) -> #N/A | L89: 1 | M89: 1 | N89: Axkid Life liggdel kommer i två färger, svart och grått, och gör det möjligt att använda Axkid Life även från nyfödd upp till ca 6 månader. Stor och rymlig liggdel med ett innermått på 76 cm inklusive justerbar sufflett, löstagbart liggdelslock, madrass samt praktiska bärhandtag. Inuti liggdelen finns det fästen för sele (sele ingår ej) och liggdelen har kuddar i plast undertill för att liggdelen ska kunna ställas ner på marken, oavsett väder och vind. Hela klädseln är avtagbar och kan tvättas i 30° maskintvätt. Hårdlift Rymligt innermått Vikt: 3kg Yttermått: L: 85cm, B: 35cm, H (sufflett uppfälld): 50cm, H (sufflett hopfälld): 25cm Innermått: L: 75cm, B: 30cm, H: 20cm | O89: CN | P89: 8715009000 | Q89: 35 | R89: 85 | S89: 25 | T89: 37 | U89: 86 | V89: 10.5 | W89: 4.3 | X89: 2.8 | Y89: 30°
A90: Axkid Regnskydd | B90: 90100214 | C90: TRANSP | D90: 7350057582619 | E90: TILLBEHÖR TILL VAGN | F90: - | G90: - | I90: - | J90: =$J$1 -> SEK / NOK | K90: =IF(J90="SEK / NOK",(VLOOKUP(B90,'RRP data'!A:E,2,FALSE)),(IF(J90="DKK",(VLOOKUP('Axkid Template - SE'!B90,'RRP data'!A:E,4,FALSE)),(IF(J90="EUR",(VLOOKUP(B90,'RRP data'!A:E,5,FALSE))))))) -> #N/A | L90: 30 | M90: 1 | N90: Transparent regnskydd som passar sulkyn Axkid Life. | O90: CN | P90: 8715009000 | Q90: 12 | R90: 20 | S90: 12 | T90: 54 | U90: 48 | V90: 51.5 | W90: 0.51 | X90: 0.34 | Y90: Ej tvättbar
A91: Axkid Regnskydd för liggdel | B91: 90100314 | C91: TRANSP | D91: 7350057582626 | E91: TILLBEHÖR TILL VAGN | F91: - | G91: - | I91: - | J91: =$J$1 -> SEK / NOK | K91: =IF(J91="SEK / NOK",(VLOOKUP(B91,'RRP data'!A:E,2,FALSE)),(IF(J91="DKK",(VLOOKUP('Axkid Template - SE'!B91,'RRP data'!A:E,4,FALSE)),(IF(J91="EUR",(VLOOKUP(B91,'RRP data'!A:E,5,FALSE))))))) -> #N/A | L91: 30 | M91: 1 | N91: Transparent regnskydd som passar liggdelen för Axkid Life. | O91: CN | P91: 8715009000 | Q91: 12 | R91: 20 | S91: 12 | T91: 54 | U91: 48 | V91: 51.5 | W91: 0.51 | X91: 0.34 | Y91: Ej tvättbar
A92: Axkid Adapter för babyskydd | B92: 90100403 | C92: Svart | D92: 7350057582633 | E92: TILLBEHÖR TILL VAGN | F92: - | G92: - | I92: - | J92: =$J$1 -> SEK / NOK | K92: =IF(J92="SEK / NOK",(VLOOKUP(B92,'RRP data'!A:E,2,FALSE)),(IF(J92="DKK",(VLOOKUP('Axkid Template - SE'!B92,'RRP data'!A:E,4,FALSE)),(IF(J92="EUR",(VLOOKUP(B92,'RRP data'!A:E,5,FALSE))))))) -> #N/A | L92: 12 | M92: 1 | N92: Adapter som möjliggör montering av babyskydd på Axkid Life. Levereras två stycken, svarta. Kompatibla med babyskydd som har Maxi-Cosi infästning. | O92: CN | P92: 8715009000 | Q92: 13.5 | R92: 9.5 | S92: 22 | T92: 46.5 | U92: 28.5 | V92: 30 | W92: 1.47 | X92: 1.3 | Y92: Ej tvättbar
A93: Axkid Myggnät | B93: 90100506 | C93: Svart | D93: 7350057582640 | E93: TILLBEHÖR TILL VAGN | F93: - | G93: - | I93: - | J93: =$J$1 -> SEK / NOK | K93: =IF(J93="SEK / NOK",(VLOOKUP(B93,'RRP data'!A:E,2,FALSE)),(IF(J93="DKK",(VLOOKUP('Axkid Template - SE'!B93,'RRP data'!A:E,4,FALSE)),(IF(J93="EUR",(VLOOKUP(B93,'RRP data'!A:E,5,FALSE))))))) -> #N/A | L93: 70 | M93: 1 | N93: Myggnät i svart som passar sulkyn Axkid Life. | O93: CN | P93: 8715009000 | Q93: 12 | R93: 7 | S93: 12 | T93: 54 | U93: 48 | V93: 51.5 | W93: 0.14 | X93: 0.08 | Y93: Ej tvättbar
A94: Axkid Myggnät för liggdel | B94: 90100606 | C94: Svart | D94: 7350057582657 | E94: TILLBEHÖR TILL VAGN | F94: - | G94: - | I94: - | J94: =$J$1 -> SEK / NOK | K94: =IF(J94="SEK / NOK",(VLOOKUP(B94,'RRP data'!A:E,2,FALSE)),(IF(J94="DKK",(VLOOKUP('Axkid Template - SE'!B94,'RRP data'!A:E,4,FALSE)),(IF(J94="EUR",(VLOOKUP(B94,'RRP data'!A:E,5,FALSE))))))) -> #N/A | L94: 70 | M94: 1 | N94: Myggnät i svart som passar liggdelen för Axkid Life. | O94: CN | P94: 8715009000 | Q94: 12 | R94: 7 | S94: 12 | T94: 54 | U94: 48 | V94: 51.5 | W94: 0.14 | X94: 0.08 | Y94: Ej tvättbar
A95: Axkid Skötväska Svart | B95: 90100703 | C95: Svart | D95: 7350057582664 | E95: TILLBEHÖR TILL VAGN | F95: - | G95: - | I95: - | J95: =$J$1 -> SEK / NOK | K95: =IF(J95="SEK / NOK",(VLOOKUP(B95,'RRP data'!A:E,2,FALSE)),(IF(J95="DKK",(VLOOKUP('Axkid Template - SE'!B95,'RRP data'!A:E,4,FALSE)),(IF(J95="EUR",(VLOOKUP(B95,'RRP data'!A:E,5,FALSE))))))) -> #N/A | L95: 16 | M95: 1 | N95: Svart skötväska som enkelt går att fästa med tryckknappar på barnvagnens handtagsbåge. Flera smarta fack för att enkelt kunna organisera inuti väskan. En svart vadderad skötbädd inkluderad | O95: CN | P95: 8715009000 | Q95: 34 | R95: 60 | S95: 40 | T95: 54 | U95: 48 | V95: 51.5 | W95: 0.52 | X95: 0.32 | Y95: Ej tvättbar
